Workbook

Sheet CS-Estruturante
A1: Controle/Correlação | B1: Componente | C1: Riscos | D1: STRIDE LM | E1: OWASP-TOP10 | F1: On-Prem | G1: IaaS | H1: PaaS | I1: SaaS | J1: Tecnologia/Processo
A2: Obrigatorio publicar serviços na arquitetura “Hub-Spoken”, estabelecidas durante cada Landingzone, com todas as proteções | B2: Cloud Security - Estruturante | C2: Vazamento de dados | D2: STRIDE | E2: A04:2021-Insecure Design | F2: Não | G2: Sim | H2: Sim | I2: Não | J2: IPS, WAF, Firewall, TLS, API Gateway etc.
A3: A arquitetura deve seguir o modelo de segregação por funcionalidades. (Apresentação, Lógica de negócio, Persistência/Dados) | B3: Cloud Security - Estruturante | C3: Indisponibilidade | D3: Lateral Movement | E3: A04:2021-Insecure Design | F3: Não | G3: Sim | H3: Sim | I3: Não
A4: O control plane deve seguir modelos de segurança adaptativo | B4: Cloud Security - Estruturante | C4: Vazamento de dados | D4: Elevation of Privilege | E4: A01:2021-Broken Access Control | F4: Não | G4: Sim | H4: Sim | I4: Não
A5: Especificar política a nível de organização para NÃO PERMITIR que portas de serviços sejam expostas para internet. Ex: 22, 1433, 1521, 3306, 3389, 5432, 6379, 6380, 8000, 8080, 27017 e 21 | B5: Cloud Security - Estruturante | C5: Vazamento de dados | D5: Tampering | E5: A05:2021-Security Misconfiguration | F5: Não | G5: Sim | H5: Sim | I5: Não
A6: Especificar política a nível de organização para NÃO PERMITIR exposição na internet de interfaces administrativas de recursos. | B6: Cloud Security - Estruturante | C6: Vazamento de dados | D6: Tampering | E6: A05:2021-Security Misconfiguration | F6: Não | G6: Sim | H6: Sim | I6: Não
A7: Especificar política a nível de organização para NÃO PERMITIR provisionamento de endereços sem filtragem de origem; destino e serviço/porta | B7: Cloud Security - Estruturante | C7: Vazamento de dados | D7: Tampering | E7: A02:2021-Cryptographic Failures | F7: Não | G7: Sim | H7: Sim | I7: Não
A8: Todos os recursos provisionados deveram estar com sua trilha de logs cyber habilitados | B8: Cloud Security - Estruturante | C8: Regulatório/Compliance | D8: Repudiation | E8: A09:2021-Security Logging and Monitoring Failures | F8: Não | G8: Sim | H8: Sim | I8: Não
A9: Recursos provisionados não podem ter interface exposta para a internet, o consumo deverá passar por camadas de proteção. | B9: Cloud Security - Estruturante | C9: Vazamento de dados | D9: Information Disclosure | E9: A02:2021-Cryptographic Failures | F9: Não | G9: Sim | H9: Sim | I9: Não
A10: Em novas construções de Landing Zone considerar a implementação dos Guardrails (políticas de segurança da Companhia) a nível do novo Tenant | B10: Cloud Security - Estruturante | C10: Vazamento de dados | D10: Tampering | F10: Não | G10: Sim | H10: Sim | I10: Não
A11: Integrar o tenant a ferramenta corporativa de CNAPP (mandatório as funções de CSPM e CWPP) | B11: Cloud Security - Estruturante | C11: Regulatório/Compliance | D11: Tampering | F11: Não | G11: Sim | H11: Sim | I11: Não
A12: Respeitar o processo de exceções estabelecido por governança | B12: Cloud Security - Estruturante | C12: Regulatório/Compliance | D12: Information Disclosure | F12: Não | G12: Sim | H12: Sim | I12: Não

Sheet Servidores
A1: Risco Iminente | B1: Risco Secundário | C1: Ameaça - Stride-LM | D1: Componente | E1: OWASP-10 | F1: Ameaça | G1: Controle | H1: Responsabilidade | I1: Aplicabilidade (On-Prem) | J1: Aplicabilidade (IAAS) | K1: Aplicabilidade (PAAS) | L1: Aplicabilidade (SAAS) | M1: Aplicabilidade (Mobile) | N1: Tecnologia/Processo recomendada | O1: Como fazer
A2: Vazamento de dados | B2: Danos a imagem | C2: Tampering, Repudiation | D2: Servidores | E2: A01:2021-Controle de acesso quebrado, A09:2021-Falhas de registro e monitoramento de segurança | F2: Roubo de credenciais | G2: Implementar autenticação multifatorial (MFA) para todas as contas | H2: Time de SO | I2: Sim | J2: Sim | K2: N/A | L2: N/A | M2: N/A | N2: Autheticator
A3: Vazamento de dados | B3: Regulatório/Compliance | C3: Tampering, Repudiation | D3: Servidores | E3: A01:2021-Controle de acesso quebrado, A09:2021-Falhas de registro e monitoramento de segurança | F3: Reutilização de credenciais | G3: O servidor deverá estar integrado a uma solução de PAM | H3: Time de SO | I3: Sim | J3: Sim | K3: N/A | L3: N/A | M3: N/A | N3: Autheticator
A4: Vazamento de dados | B4: Perda Financeira | C4: Tampering, Repudiation | D4: Servidores | E4: A01:2021-Controle de acesso quebrado, A09:2021-Falhas de registro e monitoramento de segurança | F4: Ataques de malware | G4: Todos os servidores devem possuir imagem de SO e BD padrão da Vivo (com EDR, Antivírus, agente do SIEM e agente de Scan de Infra) | H4: Time de SO | I4: Sim | J4: Sim | K4: N/A | L4: N/A | M4: N/A | N4: Autheticator
A5: Vazamento de dados | B5: Danos a imagem | C5: Information disclosure | D5: Servidores | E5: A04:2021 – Design Inseguro | F5: Movimentação lateral | H5: Time de SO | I5: Sim | J5: Sim | K5: N/A | L5: N/A | M5: N/A | N5: SIEM
A6: Vazamento de dados | B6: Regulatório/Compliance | C6: Information disclosure | D6: Servidores | E6: A04:2021 – Design Inseguro | F6: Acesso não autorizado | G6: Implementar políticas que garantam a retenção adequada de logs para auditoria e investigação. | H6: Time de SO | I6: Sim | J6: Sim | K6: N/A | L6: N/A | M6: N/A | N6: SIEM
A7: Vazamento de dados | C7: Information disclosure | D7: Servidores | E7: A04:2021 – Design Inseguro | F7: Man-In-the-Middle | G7: Implementar criptografia para dados em repouso e em trânsito, protegendo informações sensíveis de acesso não autorizado. | H7: Time de SO | I7: Sim | J7: Sim | K7: N/A | L7: N/A | M7: N/A | N7: Bitlocker (Windows), dm-crypt (Linux), TLS
A8: Vazamento de dados | B8: Regulatório/Compliance | C8: Information disclosure | D8: Servidores | E8: A04:2021 – Design Inseguro | F8: Vazamento de dados | H8: Time de SO | I8: Sim | J8: Sim | K8: N/A | L8: N/A | M8: N/A | N8: Bitlocker (Windows), dm-crypt (Linux), TLS
A9: Vazamento de dados | C9: Information disclosure | D9: Servidores | E9: A04:2021 – Design Inseguro | F9: Alteração dos dados | H9: Time de SO | I9: Sim | J9: Sim | K9: N/A | L9: N/A | M9: N/A | N9: Bitlocker (Windows), dm-crypt (Linux), TLS
A10: Vazamento de dados | B10: Regulatório/Compliance | C10: Information disclosure | D10: Servidores | E10: A04:2021 – Design Inseguro | F10: Exfiltração de dados | G10: Utilizar soluções de prevenção de perda de dados para monitorar e proteger dados sensíveis. | H10: Time de Proteção de dados | I10: Sim | J10: Sim | K10: N/A | L10: N/A | M10: N/A | N10: DLP, XDR
A11: Vazamento de dados | C11: Information disclosure | D11: Servidores | E11: A04:2021 – Design Inseguro | F11: Vazamento de dados | H11: Time de Proteção de dados | I11: Sim | J11: Sim | K11: N/A | L11: N/A | M11: N/A | N11: DLP, XDR
A12: Vazamento de dados | C12: Elevation of Privilege | D12: Servidores | E12: A01:2021-Controle de acesso quebrado | F12: Elevação de privilegio | G12: Implementar RBAC para gerenciar acesso a nivel infra | H12: Time de Gestão de acessos | I12: Sim | J12: Sim | K12: N/A | L12: N/A | M12: N/A | N12: IDP
A13: Vazamento de dados | C13: Lateral Movement | D13: Servidores | E13: A04:2021-Design inseguro | F13: Movimentação lateral | G13: Implementar segmentação de rede para limitar o movimento lateral | H13: Time de SO | I13: Sim | J13: Sim | K13: N/A | L13: N/A | M13: N/A | N13: Microsegmentação
G14: É necessário garantir que os projetos estejam com os SO adequados (não é permitido a subida de SO obsoleto) | H14: Time de SO | I14: Sim | J14: Sim | K14: N/A | L14: N/A | M14: N/A | N14: Hardenização
G15: O ativo precisa estar integrado ao CMDB, garantindo a centralização dos ativos no inventário oficial | H15: Time de TI | I15: Sim | J15: Sim | K15: N/A | L15: N/A | M15: N/A | N15: CMDB
G16: Todos os servidores devem possuir imagem de SO e BD padrão da Vivo (com EDR, Antivírus, agente do SIEM e agente de Scan de Infra) | H16: Time de SO | I16: Sim | J16: Sim | K16: N/A | L16: N/A | M16: N/A | N16: Hardenização

Sheet Versão3
A1: Risco Iminente | B1: Risco Secundário | C1: Ameaça - Stride-LM | D1: Componente | E1: OWASP-10 | F1: Ameaça | G1: Controle | H1: Responsabilidade | I1: Aplicabilidade (On-Prem) | J1: Aplicabilidade (IAAS) | K1: Aplicabilidade (PAAS) | L1: Aplicabilidade (SAAS) | M1: Aplicabilidade (Mobile) | N1: Tecnologia/Processo recomendada | O1: Como fazer
A2: Vazamento de dados | B2: Dano a imagem | C2: Information disclosure | D2: Aplicação | E2: A04:2021 – Design Inseguro | F2: Man-In-the-Middle | G2: Implementar a pinagem do Certificado Digital em soluções mobile | H2: Owner da aplicação | I2: N/A | J2: N/A | K2: N/A | L2: N/A | M2: Sim
A3: Vazamento de dados | B3: Dano a imagem | C3: Information disclosure | D3: Aplicação | E3: A02:2021 – Falhas Criptográficas | F3: Man-In-the-Middle | G3: Ativação da criptografia de payload e handshake entre front-end e camada de exposição de APIs | H3: Owner da aplicação | I3: Sim | J3: Sim | K3: Sim | L3: Sim | M3: Sim
A4: Vazamento de dados | B4: Perca financeira | C4: Spoofing | D4: Aplicação | E4: A09:2021 – Falhas de Segurança na Aplicação | F4: Roubo de sessão | G4: A aplicação deve implementar controle de sessão (timeout, sessão simultânea, etc) | H4: Owner da aplicação | I4: Sim | J4: Sim | K4: Sim | L4: Sim | M4: Sim
A5: Vazamento de dados | B5: Perca financeira | C5: Spoofing | D5: Aplicação | E5: A09:2021 – Falhas de Segurança na Aplicação | F5: Roubo de sessão | G5: A aplicação deve implementar validação de sessão (Front e Back via Mutual TLS) | H5: Owner da aplicação | I5: Sim | J5: Sim | K5: Sim | L5: Sim | M5: Sim
D6: Aplicação | G6: Implementar mecanismos para controle de Abuso de recursos/limite de requisições
D7: Aplicação | G7: Implementar mecanismos para bloqueio de ataques de “Brute Force” (exemplo: CAPTCH)
D8: Aplicação | G8: A aplicação deve efetuar a ofuscação de dados sensíveis, tanto no frontend quanto no backend
D9: Aplicação | G9: Prevenir mensagens de erro que permitam enumeração de usuários (Alterar as mensagens de retornos)
D10: Aplicação | G10: Garantir que cada token OTP (One Time Password), se aplicável, só possa ser usado uma única vez
D11: Aplicação | G11: Todas as aplicações WEB devem ser protegidas contra-ataques de CSRF (Cross Site Request Forgery) e CORS (Cross Origin Resource Sharing)
D12: Aplicação | G12: Os Bancos de Dados utilizados pela aplicação devem possuir uma rotina de backup documentada, aplicada e testada periodicamente
D13: Aplicação | G13: É necessário criptografar todas as comunicações entre o cliente e a API utilizando o protocolo TLS (HTTPs) 1.2 ou superior.
D14: Aplicação | G14: Utilize assinaturas digitais para garantir a autenticidade e a origem das mensagens, permitindo que a fonte seja verificada de forma irrefutável.
D15: Aplicação | G15: Caso o sistema/aplicação possa ser acessado à partir da Internet, ele precisa estar segregado por uma DMZ
D16: Aplicação | F16: Ataque de Força Bruta
C19: Tampering, Repudiation | D19: Servidores | E19: A01:2021-Controle de acesso quebrado, A09:2021-Falhas de registro e monitoramento de segurança | F19: Roubo de credenciais | G19: Implementar autenticação multifatorial (MFA) | H19: Time de SO | I19: Sim | J19: Sim | K19: N/A | L19: N/A | M19: N/A
C20: Tampering, Repudiation | D20: Servidores | E20: A01:2021-Controle de acesso quebrado, A09:2021-Falhas de registro e monitoramento de segurança | F20: Reutilização de credenciais | G20: Implementar autenticação multifatorial (MFA) | H20: Time de SO | I20: Sim | J20: Sim | K20: N/A | L20: N/A | M20: N/A
C21: Tampering, Repudiation | D21: Servidores | E21: A01:2021-Controle de acesso quebrado, A09:2021-Falhas de registro e monitoramento de segurança | F21: Ataques de malware | G21: Implementar autenticação multifatorial (MFA) | H21: Time de SO | I21: Sim | J21: Sim | K21: N/A | L21: N/A | M21: N/A
C22: Information Disclosure | D22: Servidores | E22: A04:2021 – Design Inseguro | F22: Movimentação lateral | G22: Implementar políticas que garantam a retenção adequada de logs para auditoria e investigação. | H22: Time de SO | I22: Sim | J22: Sim | K22: N/A | L22: N/A | M22: N/A
C23: Information Disclosure | D23: Servidores | E23: A04:2021 – Design Inseguro | F23: Acesso não autorizado | G23: Implementar políticas que garantam a retenção adequada de logs para auditoria e investigação. | H23: Time de SO | I23: Sim | J23: Sim | K23: N/A | L23: N/A | M23: N/A
C24: Information disclosure | D24: Servidores | E24: A04:2021 – Design Inseguro | F24: Man-In-the-Middle | G24: Implementar criptografia para dados em repouso e em trânsito, protegendo informações sensíveis de acesso não autorizado. | H24: Time de SO | I24: Sim | J24: Sim | K24: N/A | L24: N/A | M24: N/A
C25: Information disclosure | D25: Servidores | E25: A04:2021 – Design Inseguro | F25: Vazamento de dados | G25: Implementar criptografia para dados em repouso e em trânsito, protegendo informações sensíveis de acesso não autorizado. | H25: Time de SO | I25: Sim | J25: Sim | K25: N/A | L25: N/A | M25: N/A
C26: Information disclosure | D26: Servidores | E26: A04:2021 – Design Inseguro | F26: Alteração dos dados | G26: Implementar criptografia para dados em repouso e em trânsito, protegendo informações sensíveis de acesso não autorizado. | H26: Time de SO | I26: Sim | J26: Sim | K26: N/A | L26: N/A | M26: N/A
C27: Information disclosure | D27: Servidores | E27: A04:2021 – Design Inseguro | F27: Exfiltração de dados | G27: Utilizar soluções de prevenção de perda de dados para monitorar e proteger dados sensíveis. | H27: Time de Proteção de dados | I27: Sim | J27: Sim | K27: N/A | L27: N/A | M27: N/A
C28: Information disclosure | D28: Servidores | E28: A04:2021 – Design Inseguro | F28: Vazamento de dados | G28: Utilizar soluções de prevenção de perda de dados para monitorar e proteger dados sensíveis. | H28: Time de Proteção de dados | I28: Sim | J28: Sim | K28: N/A | L28: N/A | M28: N/A
C29: Elevation of Privilege | D29: Servidores | E29: A01:2021-Controle de acesso quebrado | F29: Elevação de privilegio | G29: Implementar RBAC para gerenciar acesso | H29: Time de Gestão de acessos | I29: Sim | J29: Sim | K29: N/A | L29: N/A | M29: N/A
C30: Lateral Movement | D30: Servidores | E30: A04:2021-Design inseguro | F30: Movimentação lateral | G30: Implementar segmentação de rede para limitar o movimento lateral | H30: Time de SO | I30: Sim | J30: Sim | K30: N/A | L30: N/A | M30: N/A
D45: Banco de Dados | F45: Injeção SQL | G45: O Banco de Dados deve utilizar validações de entrada para evitar ataques de injeção, como SQL injection, que podem comprometer a integridade dos dados.
D46: Banco de Dados | F46: Ataque de Força Bruta
D47: Banco de Dados | F47: Ataque Man-in-the-Middle (MITM)
D48: Banco de Dados | F48: Exploração de Zero-Day
D49: Banco de Dados | F49: Uso de Credenciais Roubadas
D50: Banco de Dados | F50: Privilégios Excessivos
D51: Banco de Dados | F51: Erros de Configuração
D52: Banco de Dados | F52: Dados Expostos Publicamente
D53: Banco de Dados | F53: Negação de Serviço (DoS/DDoS)
D54: Banco de Dados | F54: Locking e Deadlocks
D55: Banco de Dados | F55: Falta de Criptografia
D56: Banco de Dados | F56: Falta de Backup e Recuperação
D57: Banco de Dados | F57: Falha em Aplicação de Patches
... D59: Banco de Dados | F59: Erros Humanos
A119: Regulatório/Compliance | C119: Exposição de dados sensiveis
A120: Regulatório/Compliance | C120: Transferencia de dados para paises sem acordos regulatorios compativeis
A121: Regulatório/Compliance | C121: Uso indevido de dados pessoais por colaboradores
A122: Regulatório/Compliance | C122: Armazenmento de dados sensiveis em dispositivos não aotorizados
A123: Regulatório/Compliance | C123: Coleta de dados sem consentimento explicito
A124: Regulatório/Compliance | C124: Retenção de dados além do prazo permitido por regulamentações
A125: Regulatório/Compliance | C125: Vazamento de informações confidenciaisem redes sociais
A126: Regulatório/Compliance | C126: Elevação de Privilegio
A127: Regulatório/Compliance | C127: Dados não criptografados em repouso
A128: Regulatório/Compliance | C128: Dados não criptografados em transito
A129: Regulatório/Compliance | C129: Backup de dados sem controles de acesso adequados
A130: Regulatório/Compliance | C130: Falha em excluir ou anonimizar dados conforme solicitado por individuos
... A139: Danos a imagem | C139: Configurações erradas e acessos expostos

Sheet Versão2
A1: Risco Iminente | B1: Risco Secundário | C1: Ameaça - Stride-LM | D1: Componente | E1: OWASP-10 | F1: Controle de Ameaças | G1: Responsabilidade | H1: Aplicabilidade (On-Prem) | I1: Aplicabilidade (IAAS) | J1: Aplicabilidade (PAAS) | K1: Aplicabilidade (SAAS) | L1: Tecnologia/Processo recomendada | M1: Como fazer
A2: Vazamento de Dados | B2: Regulatório/Compliance | C2: Spoofing | D2: Workstation | E2: A9 - Quebra de criptografia | F2: Criptografia de Disco | G2: TI/Workplace | H2: sim | I2: sim | J2: sim | K2: sim | L2: Bitlocker | M2: Falta normativa/modelo para esse controle
A3: Vazamento de Dados | C3: Ransomware | D3: Workstation | F3: Sistemas Operacionais e Softwares Atualizados (Patches atualizados) | G3: Owner/Proteção de Dados | H3: sim | I3: sim | J3: não | K3: não
A4: Vazamento de Dados | C4: Ransomware | D4: Workstation | F4: Politicas de privilegio minimo | G4: Owner/Proteção de Dados | H4: sim | I4: sim | J4: não | K4: não
A5: Vazamento de Dados | C5: Ransomware | D5: Workstation | F5: Detecção e Respostas a Ponto de Extremidades (EDR) | G5: Owner/Proteção de Dados | H5: sim | I5: sim | J5: não | K5: não
A6: Vazamento de Dados | C6: Ransomware | D6: Workstation | F6: Proteção de perda de dados (DLP) | G6: Owner/Proteção de Dados | H6: sim | I6: sim | J6: não | K6: não
A7: Vazamento de Dados | C7: Ransomware | D7: Workstation | F7: Backup imutavel | G7: Owner/Proteção de Dados | H7: sim | I7: sim | J7: não | K7: não
A8: Vazamento de Dados | C8: Ransomware | D8: Workstation | F8: Detecção e Respostas a Ponto de Extremidades (EDR) | G8: Owner/Proteção de Dados | H8: sim | I8: sim | J8: não | K8: não
A9: Vazamento de Dados | C9: Ransomware | D9: Workstation | F9: Proteção de perda de dados (DLP) | G9: Owner/Proteção de Dados | H9: sim | I9: sim | J9: não | K9: não
A10: Vazamento de Dados | C10: Ransomware | D10: Workstation | F10: Backup imutavel | G10: Owner/Proteção de Dados
A11: Vazamento de Dados | C11: Ransomware | D11: Workstation | F11: Segmentação de redes | G11: Owner/Proteção de Dados
A12: Vazamento de Dados | C12: Ransomware | D12: Workstation | F12: Segmentação de redes | G12: Owner/Proteção de Dados
A13: Vazamento de Dados | C13: Ransomware | D13: Workstation | F13: Backup imutavel | G13: Owner/Proteção de Dados
A14: Vazamento de Dados | C14: Ransomware | D14: Workstation | F14: Restringir acesso administrativo | G14: Owner/Proteção de Dados
A15: Vazamento de Dados | C15: Ransomware | D15: Workstation | F15: Segmentação de redes | G15: Owner/Proteção de Dados
A16: Vazamento de Dados | C16: Ransomware | D16: Workstation | F16: Backup imutavel | G16: Owner/Proteção de Dados
A17: Vazamento de Dados | C17: Ransomware | D17: Workstation | F17: Autenticação forte | G17: Owner/Proteção de Dados
A18: Vazamento de Dados | C18: Ransomware | D18: Workstation | F18: Politicas de privilegio minimo | G18: Owner/Proteção de Dados
A19: Vazamento de Dados | C19: Credenciais comprometidas | D19: Workstation | F19: Segmentação de perfis de acesso
A20: Vazamento de Dados | C20: Credenciais comprometidas | D20: Servidores Fisicos | F20: Política e procedimentos de controle de acesso, revisão de acesso
A21: Vazamento de Dados | C21: Exposição de dados em nuvem | D21: Maquinas Virtuais
A22: Vazamento de Dados | C22: Acessos não autorizados | D22: Containers
A23: Vazamento de Dados | C23: Elevação de Privilegio | D23: Serviços Serveless
A24: Vazamento de Dados | C24: Misconfiguration | D24: Bancos Relacionais
A25: Vazamento de Dados | C25: Espionagem Industrial | D25: Storage em bloco ou objeto
A26: Vazamento de Dados | C26: Insider Threats | D26: Balanceadores de carga
A27: Vazamento de Dados | C27: Man-in-the-Middle | D27: Firewalls
A28: Vazamento de Dados | C28: Exploração de Vulnerabilidades em aplicações Web | D28: DNS
A29: Vazamento de Dados | C29: Adulteração de dados | D29: Redes privadas virtuais
A30: Vazamento de Dados | C30: Exposição acidental | D30: Gateways de API
A31: Vazamento de Dados | C31: Ataques a Sistemas Legados | D31: Filas de Mensagem
D32: Streams de dados
C33: Tampering | D33: Banco de Dados | E33: A03:2021 – Injeção | F33: Injeção SQL
C34: Spoofing, Elevation of Privilege | D34: Banco de Dados | E34: A07:2021 – Falhas de Identificação e Autenticação | F34: Ataque de Força Bruta
D35: Banco de Dados | E35: A02:2021 – Falhas Criptográficas | F35: Ataque Man-in-the-Middle (MITM)
D36: Banco de Dados | E36: A06:2021 – Componentes Vulneráveis e Desatualizados | F36: Exploração de Zero-Day
C37: Spoofing, Elevation of Privilege | D37: Banco de Dados | E37: A07:2021 – Falhas de Identificação e Autenticação | F37: Uso de Credenciais Roubadas
C38: Tampering, Information disclosure | D38: Banco de Dados | E38: A05:2021 – Configuração Insegura | F38: Privilégios Excessivos
C39: Tampering, Information disclosure | D39: Banco de Dados | E39: A05:2021 – Configuração Insegura | F39: Erros de Configuração
C40: Elevation of Privilege | D40: Banco de Dados | E40: A01:2021 – Controle de Acesso Quebrado | F40: Dados Expostos Publicamente
D41: Banco de Dados | E41: A08:2021 – Falhas de Integridade e Monitoramento | F41: Negação de Serviço (DoS/DDoS)
D42: Banco de Dados | E42: A09:2021 – Falhas de Segurança na Aplicação | F42: Locking e Deadlocks
C43: Information disclosure, Tampering | D43: Banco de Dados | E43: A02:2021 – Falhas Criptográficas | F43: Falta de Criptografia
D44: Banco de Dados | E44: A08:2021 – Falhas de Integridade e Monitoramento | F44: Falta de Backup e Recuperação
D45: Banco de Dados | E45: A06:2021 – Componentes Vulneráveis e Desatualizados | F45: Falha em Aplicação de Patches
C46: A04:2021-Insecure Design | D46: Banco de Dados | E46: A04:2021 – Design Inseguro | F46: Funcionários Mal-Intencionados
C47: A04:2021-Insecure Design | D47: Banco de Dados | E47: A04:2021 – Design Inseguro | F47: Erros Humanos
A142: Regulatório/Compliance | C142: Exposição de dados sensiveis
A143: Regulatório/Compliance | C143: Transferencia de dados para paises sem acordos regulatorios compativeis
A144: Regulatório/Compliance | C144: Uso indevido de dados pessoais por colaboradores
A145: Regulatório/Compliance | C145: Armazenmento de dados sensiveis em dispositivos não aotorizados
A146: Regulatório/Compliance | C146: Coleta de dados sem consentimento explicito
A147: Regulatório/Compliance | C147: Retenção de dados além do prazo permitido por regulamentações
A148: Regulatório/Compliance | C148: Vazamento de informações confidenciaisem redes sociais
A149: Regulatório/Compliance | C149: Elevação de Privilegio
A150: Regulatório/Compliance | C150: Dados não criptografados em repouso
A151: Regulatório/Compliance | C151: Dados não criptografados em transito
A152: Regulatório/Compliance | C152: Backup de dados sem controles de acesso adequados
A153: Regulatório/Compliance | C153: Falha em excluir ou anonimizar dados conforme solicitado por individuos
... A162: Danos a imagem | C162: Configurações erradas e acessos expostos

Sheet Versão1
A1: Risco | B1: Ameaça - Stride-LM | C1: Componente | D1: OWASP-10 | E1: Controle de Ameaças | G1: Responsabilidade | H1: Aplicabilidade (On-Prem) | I1: Aplicabilidade (IAAS) | J1: Aplicabilidade (PAAS) | K1: Aplicabilidade (SAAS) | L1: Tecnologia/Processo recomendada | M1: Como fazer
B2: Phishing | C2: Aplicação | E2: Autenticação Multiplo Fator de Autenticação | G2: Owner/Proteção de Dados | H2: sim | I2: sim | J2: sim | K2: sim | L2: OAM/Authenticator de mercado | M2: LINK DA NORMATIVA/SHAREPOINT
A3: Vazamento de Dados | B3: Ransomware | C3: Sistema Operacional | E3: Sistemas Operacionais e Softwares Atualizados (Patches atualizados) | G3: Owner/Proteção de Dados | H3: sim | I3: sim | J3: não | K3: não
A4: Vazamento de Dados | B4: Ransomware | C4: Sistema Operacional | E4: Politicas de privilegio minimo | G4: Owner/Proteção de Dados | H4: sim | I4: sim | J4: não | K4: não
A5: Vazamento de Dados | B5: Ransomware | C5: Sistema Operacional | E5: Detecção e Respostas a Ponto de Extremidades (EDR) | G5: Owner/Proteção de Dados | H5: sim | I5: sim | J5: não | K5: não
A6: Vazamento de Dados | B6: Ransomware | C6: Servidores de arquivos | E6: Proteção de perda de dados (DLP) | G6: Owner/Proteção de Dados | H6: sim | I6: sim | J6: não | K6: não
A7: Vazamento de Dados | B7: Ransomware | C7: Servidores de arquivos | E7: Backup imutavel | G7: Owner/Proteção de Dados | H7: sim | I7: sim | J7: não | K7: não
A8: Vazamento de Dados | B8: Ransomware | C8: Endpoint de acesso usuário | E8: Detecção e Respostas a Ponto de Extremidades (EDR) | G8: Owner/Proteção de Dados | H8: sim | I8: sim | J8: não | K8: não
A9: Vazamento de Dados | B9: Ransomware | C9: Endpoint de acesso usuário | E9: Proteção de perda de dados (DLP) | G9: Owner/Proteção de Dados | H9: sim | I9: sim | J9: não | K9: não
A10: Vazamento de Dados | B10: Ransomware | C10: Banco de dados | E10: Backup imutavel | G10: Owner/Proteção de Dados
A11: Vazamento de Dados | B11: Ransomware | C11: Banco de dados | E11: Segmentação de redes | G11: Owner/Proteção de Dados
A12: Vazamento de Dados | B12: Ransomware | C12: Backups | E12: Segmentação de redes | G12: Owner/Proteção de Dados
A13: Vazamento de Dados | B13: Ransomware | C13: Backups | E13: Backup imutavel | G13: Owner/Proteção de Dados
A14: Vazamento de Dados | B14: Ransomware | C14: Servidores de serviço | E14: Restringir acesso administrativo | G14: Owner/Proteção de Dados
A15: Vazamento de Dados | B15: Ransomware | C15: Servidores de serviço | E15: Segmentação de redes | G15: Owner/Proteção de Dados
A16: Vazamento de Dados | B16: Ransomware | C16: Servidores de serviço | E16: Backup imutavel | G16: Owner/Proteção de Dados
A17: Vazamento de Dados | B17: Ransomware | C17: API | E17: autenticação forte | G17: Owner/Proteção de Dados
A18: Vazamento de Dados | B18: Ransomware | C18: API | E18: Politicas de privilegio minimo | G18: Owner/Proteção de Dados
A19: Vazamento de Dados | B19: Credenciais comprometidas | C19: Aplicação | E19: Segmentação de perfis de acesso
A20: Vazamento de Dados | B20: Credenciais comprometidas | E20: Política e procedimentos de controle de acesso, revisão de acesso
A21: Vazamento de Dados | B21: Exposição de dados em nuvem
A22: Vazamento de Dados | B22: Acessos não autorizados
A23: Vazamento de Dados | B23: Elevação de Privilegio
A24: Vazamento de Dados | B24: Misconfiguration
A25: Vazamento de Dados | B25: Espionagem Industrial
A26: Vazamento de Dados | B26: Insider Threats
A27: Vazamento de Dados | B27: Man-in-the-Middle
A28: Vazamento de Dados | B28: Exploração de Vulnerabilidades em aplicações Web
A29: Vazamento de Dados | B29: Adulteração de dados
A30: Vazamento de Dados | B30: Exposição acidental
A31: Vazamento de Dados | B31: Ataques a Sistemas Legados
A32: Regulatório/Compliance | B32: Exposição de dados sensiveis
... A52: Danos a imagem | B52: Configurações erradas e acessos expostos

Sheet NewVersion
A1: Controle/Correlação | B1: Detalhamento do requisito | C1: Componente | D1: Propriedade | E1: STRIDE LM | F1: Riscos/Impacto | G1: OWASP-TOP10 | H1: Estrutura - Sistema de Informação | I1: Categoria de Segurança | J1: On-Prem | K1: IaaS | L1: PaaS | M1: SaaS | N1: Tecnologia/Processo | O1: Como fazer
A2: A aplicação deve ativar a criptografia de payload e handshake entre front-end e camada de exposição de APIs | B2: A criptografia assegura que dados sensíveis trocados entre o cliente e o servidor sejam protegidos contra interceptação. O risco de não aplicar isso é a exposição e/ou modificação de dados pessoais e confidenciais a ataques como Man-in-the-Middle (MITM). | C2: Aplicação - Web/Mobile | D2: {=IF(Tabela1[[#This Row],[STRIDE LM]]="Information Disclosure",Formatação!H$5,IF(Tabela1[[#This Row],[STRIDE LM]]="Repudiation",Formatação!H$4,IF(Tabela1[[#This Row],[STRIDE LM]]="Spoofing",Formatação!H$2,IF(Tabela1[[#This Row],[STRIDE LM]]="Tampering",Formatação!H$3, IF(Tabela1[[#This Row],[STRIDE LM]]="Denial of Service",Formatação!H$6,IF(Tabela1[[#This Row],[STRIDE LM]]="Elevation of Privilege",Formatação!H$7,IF(Tabela1[[#This Row],[STRIDE LM]]="Lateral Movement",Formatação!H$8,Errado)))))))} -> Integridade | E2: Tampering | F2: {=IF(Tabela1[[#This Row],[STRIDE LM]]="Information Disclosure",Formatação!J$5,IF(Tabela1[[#This Row],[STRIDE LM]]="Repudiation",Formatação!J$4,IF(Tabela1[[#This Row],[STRIDE LM]]="Spoofing",Formatação!J$2,IF(Tabela1[[#This Row],[STRIDE LM]]="Tampering",Formatação!J$3, IF(Tabela1[[#This Row],[STRIDE LM]]="Denial of Service",Formatação!J$6,IF(Tabela1[[#This Row],[STRIDE LM]]="Elevation of Privilege",Formatação!J$7,IF(Tabela1[[#This Row],[STRIDE LM]]="Lateral Movement",Formatação!J$8,Errado)))))))} -> Danos a imagem | G2: A02:2021-Cryptographic Failures | H2: Processamento | I2: Application Security | J2: Sim | K2: Sim | L2: Sim | M2: Não | N2: Criptografia de payload / Deve ser implmentado durante o desenvolvimento | O2: Em construção
A3: Prevenir mensagens de erro que permitam enumeração de usuários (Alterar as mensagens de retornos) | B3: Mensagens de erro genéricas evitam que invasores possam identificar a existência de um usuário específico. Caso contrário, o risco de ataques de força bruta ou enumeração de usuários aumenta. | C3: Aplicação - Web/Mobile | D3: {=IF(Tabela1[[#This Row],[STRIDE LM]]="Information Disclosure",Formatação!H$5,IF(Tabela1[[#This Row],[STRIDE LM]]="Repudiation",Formatação!H$4,IF(Tabela1[[#This Row],[STRIDE LM]]="Spoofing",Formatação!H$2,IF(Tabela1[[#This Row],[STRIDE LM]]="Tampering",Formatação!H$3, IF(Tabela1[[#This Row],[STRIDE LM]]="Denial of Service",Formatação!H$6,IF(Tabela1[[#This Row],[STRIDE LM]]="Elevation of Privilege",Formatação!H$7,IF(Tabela1[[#This Row],[STRIDE LM]]="Lateral Movement",Formatação!H$8,Errado)))))))} -> Confidencialidade | E3: Information Disclosure | F3: {=IF(Tabela1[[#This Row],[STRIDE LM]]="Information Disclosure",Formatação!J$5,IF(Tabela1[[#This Row],[STRIDE LM]]="Repudiation",Formatação!J$4,IF(Tabela1[[#This Row],[STRIDE LM]]="Spoofing",Formatação!J$2,IF(Tabela1[[#This Row],[STRIDE LM]]="Tampering",Formatação!J$3, IF(Tabela1[[#This Row],[STRIDE LM]]="Denial of Service",Formatação!J$6,IF(Tabela1[[#This Row],[STRIDE LM]]="Elevation of Privilege",Formatação!J$7,IF(Tabela1[[#This Row],[STRIDE LM]]="Lateral Movement",Formatação!J$8,Errado)))))))} -> Vazamento de dados | G3: A04:2021-Insecure Design | J3: Sim | K3: Sim | L3: Sim | M3: Não | N3: Code Review (DAST)
A4: A aplicação precisa estar protegida com um Web Application Firewall (WAF) - Definições de politicas Telefonica | B4: O WAF monitora o tráfego HTTP e impede ataques como SQL Injection, XSS e outros direcionados à camada de aplicação. Não implementar pode deixar a aplicação vulnerável a ataques conhecidos e comprometimentos de segurança. | C4: Aplicação - Web/Mobile | D4: {=IF(Tabela1[[#This Row],[STRIDE LM]]="Information Disclosure",Formatação!H$5,IF(Tabela1[[#This Row],[STRIDE LM]]="Repudiation",Formatação!H$4,IF(Tabela1[[#This Row],[STRIDE LM]]="Spoofing",Formatação!H$2,IF(Tabela1[[#This Row],[STRIDE LM]]="Tampering",Formatação!H$3, IF(Tabela1[[#This Row],[STRIDE LM]]="Denial of Service",Formatação!H$6,IF(Tabela1[[#This Row],[STRIDE LM]]="Elevation of Privilege",Formatação!H$7,IF(Tabela1[[#This Row],[STRIDE LM]]="Lateral Movement",Formatação!H$8,Errado)))))))} -> Disponibilidade | E4: Denial of Service | F4: {=IF(Tabela1[[#This Row],[STRIDE LM]]="Information Disclosure",Formatação!J$5,IF(Tabela1[[#This Row],[STRIDE LM]]="Repudiation",Formatação!J$4,IF(Tabela1[[#This Row],[STRIDE LM]]="Spoofing",Formatação!J$2,IF(Tabela1[[#This Row],[STRIDE LM]]="Tampering",Formatação!J$3, IF(Tabela1[[#This Row],[STRIDE LM]]="Denial of Service",Formatação!J$6,IF(Tabela1[[#This Row],[STRIDE LM]]="Elevation of Privilege",Formatação!J$7,IF(Tabela1[[#This Row],[STRIDE LM]]="Lateral Movement",Formatação!J$8,Errado)))))))} -> Indisponibilidade | G4: A05:2021-Security Misconfiguration | J4: Não | K4: Sim | L4: Sim | M4: Sim | N4: Implementar rate limiting, requisições com challenge (CAPTCHA), balanceamento de carga e detecção de tráfego anômalo via SIEM. | O4: Configurar rate limiting no API Gateway; Integrar SIEM para alertar sobre picos anormais.
A5: Para implantações em pipelines de CI/CD, é essencial que vulnerabilidades classificadas como altas e críticas sejam corrigidas antes de serem levadas para o ambiente de produção. | B5: Corrigir vulnerabilidades críticas antes da produção reduz a chance de exploração por atacantes. Ignorar vulnerabilidades críticas pode resultar em falhas de segurança graves após o lançamento. | C5: Aplicação - Web/Mobile | D5: {=IF(Tabela1[[#This Row],[STRIDE LM]]="Information Disclosure",Formatação!H$5,IF(Tabela1[[#This Row],[STRIDE LM]]="Repudiation",Formatação!H$4,IF(Tabela1[[#This Row],[STRIDE LM]]="Spoofing",Formatação!H$2,IF(Tabela1[[#This Row],[STRIDE LM]]="Tampering",Formatação!H$3, IF(Tabela1[[#This Row],[STRIDE LM]]="Denial of Service",Formatação!H$6,IF(Tabela1[[#This Row],[STRIDE LM]]="Elevation of Privilege",Formatação!H$7,IF(Tabela1[[#This Row],[STRIDE LM]]="Lateral Movement",Formatação!H$8,Errado)))))))} -> Confidencialidade | E5: Information Disclosure | F5: {=IF(Tabela1[[#This Row],[STRIDE LM]]="Information Disclosure",Formatação!J$5,IF(Tabela1[[#This Row],[STRIDE LM]]="Repudiation",Formatação!J$4,IF(Tabela1[[#This Row],[STRIDE LM]]="Spoofing",Formatação!J$2,IF(Tabela1[[#This Row],[STRIDE LM]]="Tampering",Formatação!J$3, IF(Tabela1[[#This Row],[STRIDE LM]]="Denial of Service",Formatação!J$6,IF(Tabela1[[#This Row],[STRIDE LM]]="Elevation of Privilege",Formatação!J$7,IF(Tabela1[[#This Row],[STRIDE LM]]="Lateral Movement",Formatação!J$8,Errado)))))))} -> Vazamento de dados | G5: A06:2021-Vulnerable and Outdated Components | J5: Sim | K5: Sim | L5: Sim | M5: Sim | N5: Utilização de vaults de segredo (AWS Secrets Manager, HashiCorp Vault), revisão de código com ferramentas DAST e proibição de segredos em repositórios Git. | O5: Configurar CI/CD para bloquear commits com segredos expostos.
A6: Caso o sistema/aplicação possa ser acessado à partir da Internet, ele precisa estar segregado por uma DMZ | B6: A DMZ oferece uma camada extra de segurança, isolando sistemas críticos de acessos diretos da internet. A ausência de uma DMZ pode resultar em acesso não autorizado a sistemas internos. | C6: Aplicação - Web/Mobile | D6: {=IF(Tabela1[[#This Row],[STRIDE LM]]="Information Disclosure",Formatação!H$5,IF(Tabela1[[#This Row],[STRIDE LM]]="Repudiation",Formatação!H$4,IF(Tabela1[[#This Row],[STRIDE LM]]="Spoofing",Formatação!H$2,IF(Tabela1[[#This Row],[STRIDE LM]]="Tampering",Formatação!H$3, IF(Tabela1[[#This Row],[STRIDE LM]]="Denial of Service",Formatação!H$6,IF(Tabela1[[#This Row],[STRIDE LM]]="Elevation of Privilege",Formatação!H$7,IF(Tabela1[[#This Row],[STRIDE LM]]="Lateral Movement",Formatação!H$8,Errado)))))))} -> Disponibilidade | E6: Denial of Service | F6: {=IF(Tabela1[[#This Row],[STRIDE LM]]="Information Disclosure",Formatação!J$5,IF(Tabela1[[#This Row],[STRIDE LM]]="Repudiation",Formatação!J$4,IF(Tabela1[[#This Row],[STRIDE LM]]="Spoofing",Formatação!J$2,IF(Tabela1[[#This Row],[STRIDE LM]]="Tampering",Formatação!J$3, IF(Tabela1[[#This Row],[STRIDE LM]]="Denial of Service",Formatação!J$6,IF(Tabela1[[#This Row],[STRIDE LM]]="Elevation of Privilege",Formatação!J$7,IF(Tabela1[[#This Row],[STRIDE LM]]="Lateral Movement",Formatação!J$8,Errado)))))))} -> Indisponibilidade | G6: A04:2021-Insecure Design | J6: Sim | K6: Sim | L6: Sim | M6: Não | N6: Arquitetura Segura | O6: Em tempo de analise do projeto
A7: A aplicação deve implementar a pinagem do certificado digital em soluções mobile (Evitar MITM) | B7: A pinagem de certificado impede ataques MITM, garantindo que o certificado do servidor seja sempre validado. Caso contrário, um atacante poderia interceptar a comunicação. | C7: Aplicação - Web/Mobile | D7: {=IF(Tabela1[[#This Row],[STRIDE LM]]="Information Disclosure",Formatação!H$5,IF(Tabela1[[#This Row],[STRIDE LM]]="Repudiation",Formatação!H$4,IF(Tabela1[[#This Row],[STRIDE LM]]="Spoofing",Formatação!H$2,IF(Tabela1[[#This Row],[STRIDE LM]]="Tampering",Formatação!H$3, IF(Tabela1[[#This Row],[STRIDE LM]]="Denial of Service",Formatação!H$6,IF(Tabela1[[#This Row],[STRIDE LM]]="Elevation of Privilege",Formatação!H$7,IF(Tabela1[[#This Row],[STRIDE LM]]="Lateral Movement",Formatação!H$8,Errado)))))))} -> Autenticação | E7: Spoofing | F7: {=IF(Tabela1[[#This Row],[STRIDE LM]]="Information Disclosure",Formatação!J$5,IF(Tabela1[[#This Row],[STRIDE LM]]="Repudiation",Formatação!J$4,IF(Tabela1[[#This Row],[STRIDE LM]]="Spoofing",Formatação!J$2,IF(Tabela1[[#This Row],[STRIDE LM]]="Tampering",Formatação!J$3, IF(Tabela1[[#This Row],[STRIDE LM]]="Denial of Service",Formatação!J$6,IF(Tabela1[[#This Row],[STRIDE LM]]="Elevation of Privilege",Formatação!J$7,IF(Tabela1[[#This Row],[STRIDE LM]]="Lateral Movement",Formatação!J$8,Errado)))))))} -> Fraudes/Vazamento de dados | G7: A02:2021-Cryptographic Failures | J7: Sim | K7: Sim | L7: Sim | M7: Não | N7: Desenvolvimento Seguro
A8: A aplicação deve implementar Controle de Sessão (timeout, sessão simultânea, etc) | B8: Controlar sessões previne que sessões inativas ou múltiplas simultâneas comprometam a segurança do sistema. A falta de controle pode levar a invasões de contas por sessões esquecidas ou mal gerenciadas. | C8: Aplicação - Web/Mobile | D8: {=IF(Tabela1[[#This Row],[STRIDE LM]]="Information Disclosure",Formatação!H$5,IF(Tabela1[[#This Row],[STRIDE LM]]="Repudiation",Formatação!H$4,IF(Tabela1[[#This Row],[STRIDE LM]]="Spoofing",Formatação!H$2,IF(Tabela1[[#This Row],[STRIDE LM]]="Tampering",Formatação!H$3, IF(Tabela1[[#This Row],[STRIDE LM]]="Denial of Service",Formatação!H$6,IF(Tabela1[[#This Row],[STRIDE LM]]="Elevation of Privilege",Formatação!H$7,IF(Tabela1[[#This Row],[STRIDE LM]]="Lateral Movement",Formatação!H$8,Errado)))))))} -> Autenticação | E8: Spoofing | F8: {=IF(Tabela1[[#This Row],[STRIDE LM]]="Information Disclosure",Formatação!J$5,IF(Tabela1[[#This Row],[STRIDE LM]]="Repudiation",Formatação!J$4,IF(Tabela1[[#This Row],[STRIDE LM]]="Spoofing",Formatação!J$2,IF(Tabela1[[#This Row],[STRIDE LM]]="Tampering",Formatação!J$3, IF(Tabela1[[#This Row],[STRIDE LM]]="Denial of Service",Formatação!J$6,IF(Tabela1[[#This Row],[STRIDE LM]]="Elevation of Privilege",Formatação!J$7,IF(Tabela1[[#This Row],[STRIDE LM]]="Lateral Movement",Formatação!J$8,Errado)))))))} -> Fraudes/Vazamento de dados | G8: A01:2021-Broken Access Control | J8: Sim | K8: Sim | L8: Sim | M8: Sim | N8: Desenvolvimento Seguro
A9: A aplicação de implementar validação de Sessão (Front e Back via Mutual TLS) | B9: A validação de sessão com Mutual TLS garante que tanto o cliente quanto o servidor sejam autenticados mutuamente, prevenindo acesso não autorizado. Sem isso, a aplicação fica vulnerável a sequestro de sessão. | C9: Aplicação - Web/Mobile | D9: {=IF(Tabela1[[#This Row],[STRIDE LM]]="Information Disclosure",Formatação!H$5,IF(Tabela1[[#This Row],[STRIDE LM]]="Repudiation",Formatação!H$4,IF(Tabela1[[#This Row],[STRIDE LM]]="Spoofing",Formatação!H$2,IF(Tabela1[[#This Row],[STRIDE LM]]="Tampering",Formatação!H$3, IF(Tabela1[[#This Row],[STRIDE LM]]="Denial of Service",Formatação!H$6,IF(Tabela1[[#This Row],[STRIDE LM]]="Elevation of Privilege",Formatação!H$7,IF(Tabela1[[#This Row],[STRIDE LM]]="Lateral Movement",Formatação!H$8,Errado)))))))} -> Autenticação | E9: Spoofing | F9: {=IF(Tabela1[[#This Row],[STRIDE LM]]="Information Disclosure",Formatação!J$5,IF(Tabela1[[#This Row],[STRIDE LM]]="Repudiation",Formatação!J$4,IF(Tabela1[[#This Row],[STRIDE LM]]="Spoofing",Formatação!J$2,IF(Tabela1[[#This Row],[STRIDE LM]]="Tampering",Formatação!J$3, IF(Tabela1[[#This Row],[STRIDE LM]]="Denial of Service",Formatação!J$6,IF(Tabela1[[#This Row],[STRIDE LM]]="Elevation of Privilege",Formatação!J$7,IF(Tabela1[[#This Row],[STRIDE LM]]="Lateral Movement",Formatação!J$8,Errado)))))))} -> Fraudes/Vazamento de dados | G9: A01:2021-Broken Access Control | J9: Sim | K9: Sim | L9: Sim | M9: Sim | N9: Desenvolvimento Seguro
A10: A aplicação deve efetuar a ofuscação de dados sensíveis, tanto no frontend quanto no backend | B10: Ofuscar dados sensíveis ajuda a evitar que informações como senhas ou detalhes pessoais sejam facilmente acessadas em caso de comprometimento. A falta de ofuscação pode resultar em vazamentos de dados sensíveis. | C10: Aplicação - Web/Mobile | D10: {=IF(Tabela1[[#This Row],[STRIDE LM]]="Information Disclosure",Formatação!H$5,IF(Tabela1[[#This Row],[STRIDE LM]]="Repudiation",Formatação!H$4,IF(Tabela1[[#This Row],[STRIDE LM]]="Spoofing",Formatação!H$2,IF(Tabela1[[#This Row],[STRIDE LM]]="Tampering",Formatação!H$3, IF(Tabela1[[#This Row],[STRIDE LM]]="Denial of Service",Formatação!H$6,IF(Tabela1[[#This Row],[STRIDE LM]]="Elevation of Privilege",Formatação!H$7,IF(Tabela1[[#This Row],[STRIDE LM]]="Lateral Movement",Formatação!H$8,Errado)))))))} -> Confidencialidade | E10: Information Disclosure | F10: {=IF(Tabela1[[#This Row],[STRIDE LM]]="Information Disclosure",Formatação!J$5,IF(Tabela1[[#This Row],[STRIDE LM]]="Repudiation",Formatação!J$4,IF(Tabela1[[#This Row],[STRIDE LM]]="Spoofing",Formatação!J$2,IF(Tabela1[[#This Row],[STRIDE LM]]="Tampering",Formatação!J$3, IF(Tabela1[[#This Row],[STRIDE LM]]="Denial of Service",Formatação!J$6,IF(Tabela1[[#This Row],[STRIDE LM]]="Elevation of Privilege",Formatação!J$7,IF(Tabela1[[#This Row],[STRIDE LM]]="Lateral Movement",Formatação!J$8,Errado)))))))} -> Vazamento de dados | G10: A02:2021-Cryptographic Failures | J10: Sim | K10: Sim | L10: Sim | M10: Sim | N10: Desenvolvimento Seguro
A11: Todas as aplicações WEB devem ser protegidas contra-ataques de CSRF (Cross Site Request Forgery) e CORS (Cross Origin Resource Sharing) | B11: Prevenir CSRF e configurar CORS adequadamente evita que ataques externos possam executar ações não autorizadas em nome de um usuário legítimo. Ignorar isso pode permitir ataques de escalonamento de privilégio. | C11: Aplicação - Web/Mobile | D11: {=IF(Tabela1[[#This Row],[STRIDE LM]]="Information Disclosure",Formatação!H$5,IF(Tabela1[[#This Row],[STRIDE LM]]="Repudiation",Formatação!H$4,IF(Tabela1[[#This Row],[STRIDE LM]]="Spoofing",Formatação!H$2,IF(Tabela1[[#This Row],[STRIDE LM]]="Tampering",Formatação!H$3, IF(Tabela1[[#This Row],[STRIDE LM]]="Denial of Service",Formatação!H$6,IF(Tabela1[[#This Row],[STRIDE LM]]="Elevation of Privilege",Formatação!H$7,IF(Tabela1[[#This Row],[STRIDE LM]]="Lateral Movement",Formatação!H$8,Errado)))))))} -> Integridade | E11: Tampering | F11: {=IF(Tabela1[[#This Row],[STRIDE LM]]="Information Disclosure",Formatação!J$5,IF(Tabela1[[#This Row],[STRIDE LM]]="Repudiation",Formatação!J$4,IF(Tabela1[[#This Row],[STRIDE LM]]="Spoofing",Formatação!J$2,IF(Tabela1[[#This Row],[STRIDE LM]]="Tampering",Formatação!J$3, IF(Tabela1[[#This Row],[STRIDE LM]]="Denial of Service",Formatação!J$6,IF(Tabela1[[#This Row],[STRIDE LM]]="Elevation of Privilege",Formatação!J$7,IF(Tabela1[[#This Row],[STRIDE LM]]="Lateral Movement",Formatação!J$8,Errado)))))))} -> Danos a imagem | G11: A03:2021-Injection | J11: Sim | K11: Sim | L11: Sim | M11: Sim | N11: Desenvolvimento Seguro
A12: A aplicação deve implementar validação de Sessão (Front e Back via Mutual TLS) | B12: Garante que apenas sessões legítimas permaneçam ativas, prevenindo uso indevido por terceiros. Protege contra ataques de sequestro de sessão (Session Hijacking). Deve incluir expiração automática e revalidação periódica. Implementação via tokens seguros, como JWT com assinatura. Essencial para manter integridade e segurança no acesso. | C12: Aplicação - Web/Mobile | D12: {=IF(Tabela1[[#This Row],[STRIDE LM]]="Information Disclosure",Formatação!H$5,IF(Tabela1[[#This Row],[STRIDE LM]]="Repudiation",Formatação!H$4,IF(Tabela1[[#This Row],[STRIDE LM]]="Spoofing",Formatação!H$2,IF(Tabela1[[#This Row],[STRIDE LM]]="Tampering",Formatação!H$3, IF(Tabela1[[#This Row],[STRIDE LM]]="Denial of Service",Formatação!H$6,IF(Tabela1[[#This Row],[STRIDE LM]]="Elevation of Privilege",Formatação!H$7,IF(Tabela1[[#This Row],[STRIDE LM]]="Lateral Movement",Formatação!H$8,Errado)))))))} -> Autorização | E12: Elevation of Privilege | F12: {=IF(Tabela1[[#This Row],[STRIDE LM]]="Information Disclosure",Formatação!J$5,IF(Tabela1[[#This Row],[STRIDE LM]]="Repudiation",Formatação!J$4,IF(Tabela1[[#This Row],[STRIDE LM]]="Spoofing",Formatação!J$2,IF(Tabela1[[#This Row],[STRIDE LM]]="Tampering",Formatação!J$3, IF(Tabela1[[#This Row],[STRIDE LM]]="Denial of Service",Formatação!J$6,IF(Tabela1[[#This Row],[STRIDE LM]]="Elevation of Privilege",Formatação!J$7,IF(Tabela1[[#This Row],[STRIDE LM]]="Lateral Movement",Formatação!J$8,Errado)))))))} -> Danos financeiros/Vazamento de dados | G12: A05:2021-Security Misconfiguration | J12: Sim | K12: Sim | L12: Sim | M12: Sim | N12: Utilizar criptografia fim a fim com Mutual TLS | O12: Implementar certificados TLS entre microsserviços e aplicar segmentação de rede com políticas Zero Trust.
A13: Os Bancos de Dados utilizados pela aplicação devem possuir uma rotina de backup documentada, aplicada e testada periodicamente | B13: Backups regulares são cruciais para a recuperação em caso de falhas ou ataques. A falta de backups bem geridos pode resultar em perda irreparável de dados críticos. | C13: Banco de Dados | D13: {=IF(Tabela1[[#This Row],[STRIDE LM]]="Information Disclosure",Formatação!H$5,IF(Tabela1[[#This Row],[STRIDE LM]]="Repudiation",Formatação!H$4,IF(Tabela1[[#This Row],[STRIDE LM]]="Spoofing",Formatação!H$2,IF(Tabela1[[#This Row],[STRIDE LM]]="Tampering",Formatação!H$3, IF(Tabela1[[#This Row],[STRIDE LM]]="Denial of Service",Formatação!H$6,IF(Tabela1[[#This Row],[STRIDE LM]]="Elevation of Privilege",Formatação!H$7,IF(Tabela1[[#This Row],[STRIDE LM]]="Lateral Movement",Formatação!H$8,Errado)))))))} -> Confidencialidade | E13: Information Disclosure | F13: {=IF(Tabela1[[#This Row],[STRIDE LM]]="Information Disclosure",Formatação!J$5,IF(Tabela1[[#This Row],[STRIDE LM]]="Repudiation",Formatação!J$4,IF(Tabela1[[#This Row],[STRIDE LM]]="Spoofing",Formatação!J$2,IF(Tabela1[[#This Row],[STRIDE LM]]="Tampering",Formatação!J$3, IF(Tabela1[[#This Row],[STRIDE LM]]="Denial of Service",Formatação!J$6,IF(Tabela1[[#This Row],[STRIDE LM]]="Elevation of Privilege",Formatação!J$7,IF(Tabela1[[#This Row],[STRIDE LM]]="Lateral Movement",Formatação!J$8,Errado)))))))} -> Vazamento de dados | G13: A04:2021-Insecure Design | J13: Sim | K13: Sim | L13: Sim | M13: Sim
A14: Toda e qualquer Fuction deverá estar exposta atrás de um API Gateway, além disso só poderá aceitar requisições externas das soluções de WAF definidas pela Companhia (ex: Akamai e/ou CloudFlare) | B14: O API Gateway controla e monitora o acesso a funções críticas da aplicação, limitando o risco de exploração externa. Sem isso, a aplicação fica vulnerável a abusos e ataques. | C14: Banco de dados | D14: {=IF(Tabela1[[#This Row],[STRIDE LM]]="Information Disclosure",Formatação!H$5,IF(Tabela1[[#This Row],[STRIDE LM]]="Repudiation",Formatação!H$4,IF(Tabela1[[#This Row],[STRIDE LM]]="Spoofing",Formatação!H$2,IF(Tabela1[[#This Row],[STRIDE LM]]="Tampering",Formatação!H$3, IF(Tabela1[[#This Row],[STRIDE LM]]="Denial of Service",Formatação!H$6,IF(Tabela1[[#This Row],[STRIDE LM]]="Elevation of Privilege",Formatação!H$7,IF(Tabela1[[#This Row],[STRIDE LM]]="Lateral Movement",Formatação!H$8,Errado)))))))} -> Integridade | E14: Tampering | F14: {=IF(Tabela1[[#This Row],[STRIDE LM]]="Information Disclosure",Formatação!J$5,IF(Tabela1[[#This Row],[STRIDE LM]]="Repudiation",Formatação!J$4,IF(Tabela1[[#This Row],[STRIDE LM]]="Spoofing",Formatação!J$2,IF(Tabela1[[#This Row],[STRIDE LM]]="Tampering",Formatação!J$3, IF(Tabela1[[#This Row],[STRIDE LM]]="Denial of Service",Formatação!J$6,IF(Tabela1[[#This Row],[STRIDE LM]]="Elevation of Privilege",Formatação!J$7,IF(Tabela1[[#This Row],[STRIDE LM]]="Lateral Movement",Formatação!J$8,Errado)))))))} -> Danos a imagem | G14: A03:2021-Injection | J14: Sim | K14: Sim | L14: Sim | M14: Sim | N14: Uso de prepared statements, sanitização de entrada e implementação de políticas CSP (Content Security Policy). | O14: Atualizar ORM para usar consultas parametrizadas; Configurar firewall de aplicações web (WAF) para bloquear payloads maliciosos.
A15: Implementar mecanismos para bloqueio de ataques de “Brute Force” (exemplo: CAPTCH) | B15: Mecanismos como CAPTCHA impedem tentativas automatizadas de adivinhar senhas. Sem essas medidas, a aplicação fica vulnerável a ataques de força bruta. | C15: Identidade e Acesso | D15: {=IF(Tabela1[[#This Row],[STRIDE LM]]="Information Disclosure",Formatação!H$5,IF(Tabela1[[#This Row],[STRIDE LM]]="Repudiation",Formatação!H$4,IF(Tabela1[[#This Row],[STRIDE LM]]="Spoofing",Formatação!H$2,IF(Tabela1[[#This Row],[STRIDE LM]]="Tampering",Formatação!H$3, IF(Tabela1[[#This Row],[STRIDE LM]]="Denial of Service",Formatação!H$6,IF(Tabela1[[#This Row],[STRIDE LM]]="Elevation of Privilege",Formatação!H$7,IF(Tabela1[[#This Row],[STRIDE LM]]="Lateral Movement",Formatação!H$8,Errado)))))))} -> Autorização | E15: Elevation of Privilege | F15: {=IF(Tabela1[[#This Row],[STRIDE LM]]="Information Disclosure",Formatação!J$5,IF(Tabela1[[#This Row],[STRIDE LM]]="Repudiation",Formatação!J$4,IF(Tabela1[[#This Row],[STRIDE LM]]="Spoofing",Formatação!J$2,IF(Tabela1[[#This Row],[STRIDE LM]]="Tampering",Formatação!J$3, IF(Tabela1[[#This Row],[STRIDE LM]]="Denial of Service",Formatação!J$6,IF(Tabela1[[#This Row],[STRIDE LM]]="Elevation of Privilege",Formatação!J$7,IF(Tabela1[[#This Row],[STRIDE LM]]="Lateral Movement",Formatação!J$8,Errado)))))))} -> Danos financeiros/Vazamento de dados | G15: A07:2021-Identification and Authentication Failures | J15: Sim | K15: Sim | L15: Sim | M15: Sim
A16: Garantir que cada token OTP (One Time Password), se aplicável, só possa ser usado uma única vez | B16: A utilização de tokens OTP únicos reduz o risco de replay attacks, onde tokens antigos podem ser reutilizados por atacantes. A falha nesse controle pode resultar em comprometimento de contas. | C16: Identidade e Acesso | D16: {=IF(Tabela1[[#This Row],[STRIDE LM]]="Information Disclosure",Formatação!H$5,IF(Tabela1[[#This Row],[STRIDE LM]]="Repudiation",Formatação!H$4,IF(Tabela1[[#This Row],[STRIDE LM]]="Spoofing",Formatação!H$2,IF(Tabela1[[#This Row],[STRIDE LM]]="Tampering",Formatação!H$3, IF(Tabela1[[#This Row],[STRIDE LM]]="Denial of Service",Formatação!H$6,IF(Tabela1[[#This Row],[STRIDE LM]]="Elevation of Privilege",Formatação!H$7,IF(Tabela1[[#This Row],[STRIDE LM]]="Lateral Movement",Formatação!H$8,Errado)))))))} -> Autorização | E16: Elevation of Privilege | F16: {=IF(Tabela1[[#This Row],[STRIDE LM]]="Information Disclosure",Formatação!J$5,IF(Tabela1[[#This Row],[STRIDE LM]]="Repudiation",Formatação!J$4,IF(Tabela1[[#This Row],[STRIDE LM]]="Spoofing",Formatação!J$2,IF(Tabela1[[#This Row],[STRIDE LM]]="Tampering",Formatação!J$3, IF(Tabela1[[#This Row],[STRIDE LM]]="Denial of Service",Formatação!J$6,IF(Tabela1[[#This Row],[STRIDE LM]]="Elevation of Privilege",Formatação!J$7,IF(Tabela1[[#This Row],[STRIDE LM]]="Lateral Movement",Formatação!J$8,Errado)))))))} -> Danos financeiros/Vazamento de dados | G16: A07:2021-Identification and Authentication Failures | J16: Sim | K16: Sim | L16: Sim | M16: Sim
A17: Solução obrigatoriamente precisa se integrar com o Identity Provider definido pela Companhia para autenticação e autorização atraves de modelos de segurança seguros como OpenID, Oauth2 e SAML2.0 no fluxo 3-Legged Authentication; | B17: A integração com o Identity Provider garante que os processos de autenticação e autorização sejam seguros e centralizados. | C17: Identidade e Acesso | D17: {=IF(Tabela1[[#This Row],[STRIDE LM]]="Information Disclosure",Formatação!H$5,IF(Tabela1[[#This Row],[STRIDE LM]]="Repudiation",Formatação!H$4,IF(Tabela1[[#This Row],[STRIDE LM]]="Spoofing",Formatação!H$2,IF(Tabela1[[#This Row],[STRIDE LM]]="Tampering",Formatação!H$3, IF(Tabela1[[#This Row],[STRIDE LM]]="Denial of Service",Formatação!H$6,IF(Tabela1[[#This Row],[STRIDE LM]]="Elevation of Privilege",Formatação!H$7,IF(Tabela1[[#This Row],[STRIDE LM]]="Lateral Movement",Formatação!H$8,Errado)))))))} -> Autenticação | E17: Spoofing | F17: {=IF(Tabela1[[#This Row],[STRIDE LM]]="Information Disclosure",Formatação!J$5,IF(Tabela1[[#This Row],[STRIDE LM]]="Repudiation",Formatação!J$4,IF(Tabela1[[#This Row],[STRIDE LM]]="Spoofing",Formatação!J$2,IF(Tabela1[[#This Row],[STRIDE LM]]="Tampering",Formatação!J$3, IF(Tabela1[[#This Row],[STRIDE LM]]="Denial of Service",Formatação!J$6,IF(Tabela1[[#This Row],[STRIDE LM]]="Elevation of Privilege",Formatação!J$7,IF(Tabela1[[#This Row],[STRIDE LM]]="Lateral Movement",Formatação!J$8,Errado)))))))} -> Fraudes/Vazamento de dados | G17: A01:2021-Broken Access Control | J17: Não | K17: Sim | L17: Sim | M17: Sim | N17: Implementar OAuth 2.0/OpenID, MFA, bloqueio de login após tentativas falhas e rate limiting. | O17: Configurar OpenID Connect no IAM; Aplicar regras de rate limiting no API Gateway; Monitorar tentativas de login suspeitas no SIEM.
A18: É mandatório que a solução suporte e implemente o modelo de autorização baseado em perfis de acesso conforme o padrão RBAC (Role Based Access Control) | B18: RBAC assegura que usuários tenham apenas os privilégios necessários para suas funções. A falta dessa implementação pode resultar em usuários com acesso indevido a recursos sensíveis. | C18: Identidade e Acesso | D18: {=IF(Tabela1[[#This Row],[STRIDE LM]]="Information Disclosure",Formatação!H$5,IF(Tabela1[[#This Row],[STRIDE LM]]="Repudiation",Formatação!H$4,IF(Tabela1[[#This Row],[STRIDE LM]]="Spoofing",Formatação!H$2,IF(Tabela1[[#This Row],[STRIDE LM]]="Tampering",Formatação!H$3, IF(Tabela1[[#This Row],[STRIDE LM]]="Denial of Service",Formatação!H$6,IF(Tabela1[[#This Row],[STRIDE LM]]="Elevation of Privilege",Formatação!H$7,IF(Tabela1[[#This Row],[STRIDE LM]]="Lateral Movement",Formatação!H$8,Errado)))))))} -> Autorização | E18: Elevation of Privilege | F18: {=IF(Tabela1[[#This Row],[STRIDE LM]]="Information Disclosure",Formatação!J$5,IF(Tabela1[[#This Row],[STRIDE LM]]="Repudiation",Formatação!J$4,IF(Tabela1[[#This Row],[STRIDE LM]]="Spoofing",Formatação!J$2,IF(Tabela1[[#This Row],[STRIDE LM]]="Tampering",Formatação!J$3, IF(Tabela1[[#This Row],[STRIDE LM]]="Denial of Service",Formatação!J$6,IF(Tabela1[[#This Row],[STRIDE LM]]="Elevation of Privilege",Formatação!J$7,IF(Tabela1[[#This Row],[STRIDE LM]]="Lateral Movement",Formatação!J$8,Errado)))))))} -> Danos financeiros/Vazamento de dados | G18: A01:2021-Broken Access Control | J18: Sim | K18: Sim | L18: Sim | M18: Sim | N18: Implementar RBAC/ABAC, aplicar o princípio do menor privilégio e realizar auditoria de permissões periodicamente. | O18: "Configurar IAM para separar funções administrativas e operacionais; Implementar auditoria contínua de acessos."
A19: Utilize assinaturas digitais para garantir a autenticidade e a origem das mensagens, permitindo que a fonte seja verificada de forma irrefutável. | B19: As assinaturas digitais garantem que as mensagens ou transações sejam autênticas, vindas de uma fonte verificada, e não modificadas em trânsito. Isso é fundamental para evitar falsificação de dados e garantir a integridade das informações. A não utilização dessas assinaturas pode permitir ataques como spoofing e falsificação de identidade. | C19: Serverless & Functions | D19: {=IF(Tabela1[[#This Row],[STRIDE LM]]="Information Disclosure",Formatação!H$5,IF(Tabela1[[#This Row],[STRIDE LM]]="Repudiation",Formatação!H$4,IF(Tabela1[[#This Row],[STRIDE LM]]="Spoofing",Formatação!H$2,IF(Tabela1[[#This Row],[STRIDE LM]]="Tampering",Formatação!H$3, IF(Tabela1[[#This Row],[STRIDE LM]]="Denial of Service",Formatação!H$6,IF(Tabela1[[#This Row],[STRIDE LM]]="Elevation of Privilege",Formatação!H$7,IF(Tabela1[[#This Row],[STRIDE LM]]="Lateral Movement",Formatação!H$8,Errado)))))))} -> Contenção | E19: Lateral Movement | F19: {=IF(Tabela1[[#This Row],[STRIDE LM]]="Information Disclosure",Formatação!J$5,IF(Tabela1[[#This Row],[STRIDE LM]]="Repudiation",Formatação!J$4,IF(Tabela1[[#This Row],[STRIDE LM]]="Spoofing",Formatação!J$2,IF(Tabela1[[#This Row],[STRIDE LM]]="Tampering",Formatação!J$3, IF(Tabela1[[#This Row],[STRIDE LM]]="Denial of Service",Formatação!J$6,IF(Tabela1[[#This Row],[STRIDE LM]]="Elevation of Privilege",Formatação!J$7,IF(Tabela1[[#This Row],[STRIDE LM]]="Lateral Movement",Formatação!J$8,Errado)))))))} -> Vazamento de dados | G19: A08:2021-Software and Data Integrity Failures | J19: Sim | K19: Sim | L19: Sim | M19: Sim
A20: Provisionar soluções de antivírus e monitoramento de endpoints (EDR). Toda maquina de sistema operação | B20: A implementação de soluções de antivírus e EDR (Endpoint Detection and Response) em todas as máquinas de sistema operacional ajuda a detectar, bloquear e responder a ameaças em tempo real. Sem essas soluções, os endpoints ficam vulneráveis a malware, ransomware e outros tipos de ataques que podem comprometer a integridade do sistema. | C20: Workstation | D20: {=IF(Tabela1[[#This Row],[STRIDE LM]]="Information Disclosure",Formatação!H$5,IF(Tabela1[[#This Row],[STRIDE LM]]="Repudiation",Formatação!H$4,IF(Tabela1[[#This Row],[STRIDE LM]]="Spoofing",Formatação!H$2,IF(Tabela1[[#This Row],[STRIDE LM]]="Tampering",Formatação!H$3, IF(Tabela1[[#This Row],[STRIDE LM]]="Denial of Service",Formatação!H$6,IF(Tabela1[[#This Row],[STRIDE LM]]="Elevation of Privilege",Formatação!H$7,IF(Tabela1[[#This Row],[STRIDE LM]]="Lateral Movement",Formatação!H$8,Errado)))))))} -> Integridade | E20: Tampering | F20: {=IF(Tabela1[[#This Row],[STRIDE LM]]="Information Disclosure",Formatação!J$5,IF(Tabela1[[#This Row],[STRIDE LM]]="Repudiation",Formatação!J$4,IF(Tabela1[[#This Row],[STRIDE LM]]="Spoofing",Formatação!J$2,IF(Tabela1[[#This Row],[STRIDE LM]]="Tampering",Formatação!J$3, IF(Tabela1[[#This Row],[STRIDE LM]]="Denial of Service",Formatação!J$6,IF(Tabela1[[#This Row],[STRIDE LM]]="Elevation of Privilege",Formatação!J$7,IF(Tabela1[[#This Row],[STRIDE LM]]="Lateral Movement",Formatação!J$8,Errado)))))))} -> Danos a imagem | G20: A08:2021-Software and Data Integrity Failures | J20: Sim | K20: Sim | L20: Não | M20: Não
A21: É necessário manter o software e as dependências atualizados, aplicando correções de segurança regularmente para mitigar as vulnerabilidades conhecidas. | B21: Manter o software e suas dependências atualizados reduz a exposição a vulnerabilidades conhecidas. Aplicar patches de segurança de forma constante impede que falhas de segurança sejam exploradas. A não atualização pode resultar em sistemas obsoletos que são facilmente comprometidos por atacantes utilizando exploits já conhecidos. | C21: Workstation | D21: {=IF(Tabela1[[#This Row],[STRIDE LM]]="Information Disclosure",Formatação!H$5,IF(Tabela1[[#This Row],[STRIDE LM]]="Repudiation",Formatação!H$4,IF(Tabela1[[#This Row],[STRIDE LM]]="Spoofing",Formatação!H$2,IF(Tabela1[[#This Row],[STRIDE LM]]="Tampering",Formatação!H$3, IF(Tabela1[[#This Row],[STRIDE LM]]="Denial of Service",Formatação!H$6,IF(Tabela1[[#This Row],[STRIDE LM]]="Elevation of Privilege",Formatação!H$7,IF(Tabela1[[#This Row],[STRIDE LM]]="Lateral Movement",Formatação!H$8,Errado)))))))} -> Integridade | E21: Tampering | F21: {=IF(Tabela1[[#This Row],[STRIDE LM]]="Information Disclosure",Formatação!J$5,IF(Tabela1[[#This Row],[STRIDE LM]]="Repudiation",Formatação!J$4,IF(Tabela1[[#This Row],[STRIDE LM]]="Spoofing",Formatação!J$2,IF(Tabela1[[#This Row],[STRIDE LM]]="Tampering",Formatação!J$3, IF(Tabela1[[#This Row],[STRIDE LM]]="Denial of Service",Formatação!J$6,IF(Tabela1[[#This Row],[STRIDE LM]]="Elevation of Privilege",Formatação!J$7,IF(Tabela1[[#This Row],[STRIDE LM]]="Lateral Movement",Formatação!J$8,Errado)))))))} -> Danos a imagem | G21: A05:2021-Security Misconfiguration | J21: Sim | K21: Sim | L21: Sim | M21: Não
A22: Implementar mecanismos para bloqueio de ataques de “Brute Force” (exemplo: CAPTCH) | B22: Mecanismos como CAPTCHAs protegem contra ataques de força bruta, nos quais os atacantes tentam diversas combinações de senhas para acessar sistemas. A implementação de CAPTCHAs ou outras formas de bloqueio, como limites de tentativas, é crucial para garantir a segurança contra esse tipo de ataque. A falta dessa proteção pode permitir que atacantes consigam comprometer contas facilmente por meio de tentativa e erro. | C22: Workstation | D22: {=IF(Tabela1[[#This Row],[STRIDE LM]]="Information Disclosure",Formatação!H$5,IF(Tabela1[[#This Row],[STRIDE LM]]="Repudiation",Formatação!H$4,IF(Tabela1[[#This Row],[STRIDE LM]]="Spoofing",Formatação!H$2,IF(Tabela1[[#This Row],[STRIDE LM]]="Tampering",Formatação!H$3, IF(Tabela1[[#This Row],[STRIDE LM]]="Denial of Service",Formatação!H$6,IF(Tabela1[[#This Row],[STRIDE LM]]="Elevation of Privilege",Formatação!H$7,IF(Tabela1[[#This Row],[STRIDE LM]]="Lateral Movement",Formatação!H$8,Errado)))))))} -> Autorização | E22: Elevation of Privilege | F22: {=IF(Tabela1[[#This Row],[STRIDE LM]]="Information Disclosure",Formatação!J$5,IF(Tabela1[[#This Row],[STRIDE LM]]="Repudiation",Formatação!J$4,IF(Tabela1[[#This Row],[STRIDE LM]]="Spoofing",Formatação!J$2,IF(Tabela1[[#This Row],[STRIDE LM]]="Tampering",Formatação!J$3, IF(Tabela1[[#This Row],[STRIDE LM]]="Denial of Service",Formatação!J$6,IF(Tabela1[[#This Row],[STRIDE LM]]="Elevation of Privilege",Formatação!J$7,IF(Tabela1[[#This Row],[STRIDE LM]]="Lateral Movement",Formatação!J$8,Errado)))))))} -> Danos financeiros/Vazamento de dados | G22: A07:2021-Identification and Authentication Failures | J22: Sim | K22: Sim | L22: Sim | M22: Sim
A23: É necessário incorporar avaliações de segurança, desde a concepção até a manutenção, garantindo à segurança do Hardware. | B23: Avaliar a segurança desde o início do desenvolvimento e ao longo da manutenção é essencial para identificar e mitigar vulnerabilidades em sistemas de hardware. Isso inclui revisões de arquitetura, testes de segurança e validações contínuas. A falha em realizar essas avaliações pode levar a falhas de segurança no hardware, tornando-o um ponto vulnerável de ataque, comprometendo a segurança do sistema como um todo. | C23: Workstation | D23: {=IF(Tabela1[[#This Row],[STRIDE LM]]="Information Disclosure",Formatação!H$5,IF(Tabela1[[#This Row],[STRIDE LM]]="Repudiation",Formatação!H$4,IF(Tabela1[[#This Row],[STRIDE LM]]="Spoofing",Formatação!H$2,IF(Tabela1[[#This Row],[STRIDE LM]]="Tampering",Formatação!H$3, IF(Tabela1[[#This Row],[STRIDE LM]]="Denial of Service",Formatação!H$6,IF(Tabela1[[#This Row],[STRIDE LM]]="Elevation of Privilege",Formatação!H$7,IF(Tabela1[[#This Row],[STRIDE LM]]="Lateral Movement",Formatação!H$8,Errado)))))))} -> Integridade | E23: Tampering | F23: {=IF(Tabela1[[#This Row],[STRIDE LM]]="Information Disclosure",Formatação!J$5,IF(Tabela1[[#This Row],[STRIDE LM]]="Repudiation",Formatação!J$4,IF(Tabela1[[#This Row],[STRIDE LM]]="Spoofing",Formatação!J$2,IF(Tabela1[[#This Row],[STRIDE LM]]="Tampering",Formatação!J$3, IF(Tabela1[[#This Row],[STRIDE LM]]="Denial of Service",Formatação!J$6,IF(Tabela1[[#This Row],[STRIDE LM]]="Elevation of Privilege",Formatação!J$7,IF(Tabela1[[#This Row],[STRIDE LM]]="Lateral Movement",Formatação!J$8,Errado)))))))} -> Danos a imagem | G23: A07:2021-Identification and Authentication Failures | J23: Sim | K23: Sim | L23: Sim | M23: Sim
A24: Implementar DLP para monitorameto de dados e evitar vazamento de informação. | C24: Workstation | D24: {=IF(Tabela1[[#This Row],[STRIDE LM]]="Information Disclosure",Formatação!H$5,IF(Tabela1[[#This Row],[STRIDE LM]]="Repudiation",Formatação!H$4,IF(Tabela1[[#This Row],[STRIDE LM]]="Spoofing",Formatação!H$2,IF(Tabela1[[#This Row],[STRIDE LM]]="Tampering",Formatação!H$3, IF(Tabela1[[#This Row],[STRIDE LM]]="Denial of Service",Formatação!H$6,IF(Tabela1[[#This Row],[STRIDE LM]]="Elevation of Privilege",Formatação!H$7,IF(Tabela1[[#This Row],[STRIDE LM]]="Lateral Movement",Formatação!H$8,Errado)))))))} -> Confidencialidade | E24: Information Disclosure | F24: {=IF(Tabela1[[#This Row],[STRIDE LM]]="Information Disclosure",Formatação!J$5,IF(Tabela1[[#This Row],[STRIDE LM]]="Repudiation",Formatação!J$4,IF(Tabela1[[#This Row],[STRIDE LM]]="Spoofing",Formatação!J$2,IF(Tabela1[[#This Row],[STRIDE LM]]="Tampering",Formatação!J$3, IF(Tabela1[[#This Row],[STRIDE LM]]="Denial of Service",Formatação!J$6,IF(Tabela1[[#This Row],[STRIDE LM]]="Elevation of Privilege",Formatação!J$7,IF(Tabela1[[#This Row],[STRIDE LM]]="Lateral Movement",Formatação!J$8,Errado)))))))} -> Vazamento de dados | G24: A08:2021-Software and Data Integrity Failures | J24: Sim | K24: Sim | L24: Sim | M24: Sim
A25: Implemetar e Definir regras claras e bloquear softwares não autorizados. | C25: Workstation | D25: {=IF(Tabela1[[#This Row],[STRIDE LM]]="Information Disclosure",Formatação!H$5,IF(Tabela1[[#This Row],[STRIDE LM]]="Repudiation",Formatação!H$4,IF(Tabela1[[#This Row],[STRIDE LM]]="Spoofing",Formatação!H$2,IF(Tabela1[[#This Row],[STRIDE LM]]="Tampering",Formatação!H$3, IF(Tabela1[[#This Row],[STRIDE LM]]="Denial of Service",Formatação!H$6,IF(Tabela1[[#This Row],[STRIDE LM]]="Elevation of Privilege",Formatação!H$7,IF(Tabela1[[#This Row],[STRIDE LM]]="Lateral Movement",Formatação!H$8,Errado)))))))} -> Integridade | E25: Tampering | F25: {=IF(Tabela1[[#This Row],[STRIDE LM]]="Information Disclosure",Formatação!J$5,IF(Tabela1[[#This Row],[STRIDE LM]]="Repudiation",Formatação!J$4,IF(Tabela1[[#This Row],[STRIDE LM]]="Spoofing",Formatação!J$2,IF(Tabela1[[#This Row],[STRIDE LM]]="Tampering",Formatação!J$3, IF(Tabela1[[#This Row],[STRIDE LM]]="Denial of Service",Formatação!J$6,IF(Tabela1[[#This Row],[STRIDE LM]]="Elevation of Privilege",Formatação!J$7,IF(Tabela1[[#This Row],[STRIDE LM]]="Lateral Movement",Formatação!J$8,Errado)))))))} -> Danos a imagem | G25: A05:2021-Security Misconfiguration | J25: Sim | K25: Sim | L25: Sim | M25: Não
A26: Implementar a pinagem do Certificado Digital em soluções (Evitar MITM) | C26: Workstation | D26: {=IF(Tabela1[[#This Row],[STRIDE LM]]="Information Disclosure",Formatação!H$5,IF(Tabela1[[#This Row],[STRIDE LM]]="Repudiation",Formatação!H$4,IF(Tabela1[[#This Row],[STRIDE LM]]="Spoofing",Formatação!H$2,IF(Tabela1[[#This Row],[STRIDE LM]]="Tampering",Formatação!H$3, IF(Tabela1[[#This Row],[STRIDE LM]]="Denial of Service",Formatação!H$6,IF(Tabela1[[#This Row],[STRIDE LM]]="Elevation of Privilege",Formatação!H$7,IF(Tabela1[[#This Row],[STRIDE LM]]="Lateral Movement",Formatação!H$8,Errado)))))))} -> Autenticação | E26: Spoofing | F26: {=IF(Tabela1[[#This Row],[STRIDE LM]]="Information Disclosure",Formatação!J$5,IF(Tabela1[[#This Row],[STRIDE LM]]="Repudiation",Formatação!J$4,IF(Tabela1[[#This Row],[STRIDE LM]]="Spoofing",Formatação!J$2,IF(Tabela1[[#This Row],[STRIDE LM]]="Tampering",Formatação!J$3, IF(Tabela1[[#This Row],[STRIDE LM]]="Denial of Service",Formatação!J$6,IF(Tabela1[[#This Row],[STRIDE LM]]="Elevation of Privilege",Formatação!J$7,IF(Tabela1[[#This Row],[STRIDE LM]]="Lateral Movement",Formatação!J$8,Errado)))))))} -> Fraudes/Vazamento de dados | G26: A02:2021-Cryptographic Failures | J26: Sim | K26: Sim | L26: Sim | M26: Sim
A27: Desabilitar serviços não essenciais e usar configurações de segurança recomendadas (Ex.: Cis Benchmarks) | C27: Workstation | D27: {=IF(Tabela1[[#This Row],[STRIDE LM]]="Information Disclosure",Formatação!H$5,IF(Tabela1[[#This Row],[STRIDE LM]]="Repudiation",Formatação!H$4,IF(Tabela1[[#This Row],[STRIDE LM]]="Spoofing",Formatação!H$2,IF(Tabela1[[#This Row],[STRIDE LM]]="Tampering",Formatação!H$3, IF(Tabela1[[#This Row],[STRIDE LM]]="Denial of Service",Formatação!H$6,IF(Tabela1[[#This Row],[STRIDE LM]]="Elevation of Privilege",Formatação!H$7,IF(Tabela1[[#This Row],[STRIDE LM]]="Lateral Movement",Formatação!H$8,Errado)))))))} -> Autorização | E27: Elevation of Privilege | F27: {=IF(Tabela1[[#This Row],[STRIDE LM]]="Information Disclosure",Formatação!J$5,IF(Tabela1[[#This Row],[STRIDE LM]]="Repudiation",Formatação!J$4,IF(Tabela1[[#This Row],[STRIDE LM]]="Spoofing",Formatação!J$2,IF(Tabela1[[#This Row],[STRIDE LM]]="Tampering",Formatação!J$3, IF(Tabela1[[#This Row],[STRIDE LM]]="Denial of Service",Formatação!J$6,IF(Tabela1[[#This Row],[STRIDE LM]]="Elevation of Privilege",Formatação!J$7,IF(Tabela1[[#This Row],[STRIDE LM]]="Lateral Movement",Formatação!J$8,Errado)))))))} -> Danos financeiros/Vazamento de dados | G27: A05:2021-Security Misconfiguration | J27: Sim | K27: Sim | L27: Não | M27: Não
A28: O Banco de Dados deve utilizar validações de entrada para evitar ataques de injeção, como SQL injection, que podem comprometer a integridade dos dados | C28: Banco de dados | D28: {=IF(Tabela1[[#This Row],[STRIDE LM]]="Information Disclosure",Formatação!H$5,IF(Tabela1[[#This Row],[STRIDE LM]]="Repudiation",Formatação!H$4,IF(Tabela1[[#This Row],[STRIDE LM]]="Spoofing",Formatação!H$2,IF(Tabela1[[#This Row],[STRIDE LM]]="Tampering",Formatação!H$3, IF(Tabela1[[#This Row],[STRIDE LM]]="Denial of Service",Formatação!H$6,IF(Tabela1[[#This Row],[STRIDE LM]]="Elevation of Privilege",Formatação!H$7,IF(Tabela1[[#This Row],[STRIDE LM]]="Lateral Movement",Formatação!H$8,Errado)))))))} -> Integridade | E28: Tampering | F28: {=IF(Tabela1[[#This Row],[STRIDE LM]]="Information Disclosure",Formatação!J$5,IF(Tabela1[[#This Row],[STRIDE LM]]="Repudiation",Formatação!J$4,IF(Tabela1[[#This Row],[STRIDE LM]]="Spoofing",Formatação!J$2,IF(Tabela1[[#This Row],[STRIDE LM]]="Tampering",Formatação!J$3, IF(Tabela1[[#This Row],[STRIDE LM]]="Denial of Service",Formatação!J$6,IF(Tabela1[[#This Row],[STRIDE LM]]="Elevation of Privilege",Formatação!J$7,IF(Tabela1[[#This Row],[STRIDE LM]]="Lateral Movement",Formatação!J$8,Errado)))))))} -> Danos a imagem | G28: A03:2021-Injection | J28: Sim | K28: Não | L28: Não | M28: Não
A29: Realizar Periodicamente Auditorias de configurações e implementar ferramentas de monitoramento de conformidade, com automação na configuração. | C29: Banco de dados | D29: {=IF(Tabela1[[#This Row],[STRIDE LM]]="Information Disclosure",Formatação!H$5,IF(Tabela1[[#This Row],[STRIDE LM]]="Repudiation",Formatação!H$4,IF(Tabela1[[#This Row],[STRIDE LM]]="Spoofing",Formatação!H$2,IF(Tabela1[[#This Row],[STRIDE LM]]="Tampering",Formatação!H$3, IF(Tabela1[[#This Row],[STRIDE LM]]="Denial of Service",Formatação!H$6,IF(Tabela1[[#This Row],[STRIDE LM]]="Elevation of Privilege",Formatação!H$7,IF(Tabela1[[#This Row],[STRIDE LM]]="Lateral Movement",Formatação!H$8,Errado)))))))} -> Não repúdio | E29: Repudiation | F29: {=IF(Tabela1[[#This Row],[STRIDE LM]]="Information Disclosure",Formatação!J$5,IF(Tabela1[[#This Row],[STRIDE LM]]="Repudiation",Formatação!J$4,IF(Tabela1[[#This Row],[STRIDE LM]]="Spoofing",Formatação!J$2,IF(Tabela1[[#This Row],[STRIDE LM]]="Tampering",Formatação!J$3, IF(Tabela1[[#This Row],[STRIDE LM]]="Denial of Service",Formatação!J$6,IF(Tabela1[[#This Row],[STRIDE LM]]="Elevation of Privilege",Formatação!J$7,IF(Tabela1[[#This Row],[STRIDE LM]]="Lateral Movement",Formatação!J$8,Errado)))))))} -> Regulatório/Compliance | G29: A05:2021-Security Misconfiguration | J29: Sim | K29: Sim | L29: Não | M29: Não
A30: Implementar controles de acesso assim garantindo que só pessoas autorizadas possam acessar o ambiente e utilizar criptografia em repouso (AES-256) para proteger as informações sensiveis. | C30: Banco de dados | D30: {=IF(Tabela1[[#This Row],[STRIDE LM]]="Information Disclosure",Formatação!H$5,IF(Tabela1[[#This Row],[STRIDE LM]]="Repudiation",Formatação!H$4,IF(Tabela1[[#This Row],[STRIDE LM]]="Spoofing",Formatação!H$2,IF(Tabela1[[#This Row],[STRIDE LM]]="Tampering",Formatação!H$3, IF(Tabela1[[#This Row],[STRIDE LM]]="Denial of Service",Formatação!H$6,IF(Tabela1[[#This Row],[STRIDE LM]]="Elevation of Privilege",Formatação!H$7,IF(Tabela1[[#This Row],[STRIDE LM]]="Lateral Movement",Formatação!H$8,Errado)))))))} -> Confidencialidade | E30: Information Disclosure | F30: {=IF(Tabela1[[#This Row],[STRIDE LM]]="Information Disclosure",Formatação!J$5,IF(Tabela1[[#This Row],[STRIDE LM]]="Repudiation",Formatação!J$4,IF(Tabela1[[#This Row],[STRIDE LM]]="Spoofing",Formatação!J$2,IF(Tabela1[[#This Row],[STRIDE LM]]="Tampering",Formatação!J$3, IF(Tabela1[[#This Row],[STRIDE LM]]="Denial of Service",Formatação!J$6,IF(Tabela1[[#This Row],[STRIDE LM]]="Elevation of Privilege",Formatação!J$7,IF(Tabela1[[#This Row],[STRIDE LM]]="Lateral Movement",Formatação!J$8,Errado)))))))} -> Vazamento de dados | G30: A01:2021-Broken Access Control | J30: Sim | K30: Sim | L30: Não | M30: Não
A31: Implementação de rotinas de atualizações rápidas de patches de segurança e monitoramento continuo de ameaças, impedindo a exploração de vulnerabilidades | C31: Banco de dados | D31: {=IF(Tabela1[[#This Row],[STRIDE LM]]="Information Disclosure",Formatação!H$5,IF(Tabela1[[#This Row],[STRIDE LM]]="Repudiation",Formatação!H$4,IF(Tabela1[[#This Row],[STRIDE LM]]="Spoofing",Formatação!H$2,IF(Tabela1[[#This Row],[STRIDE LM]]="Tampering",Formatação!H$3, IF(Tabela1[[#This Row],[STRIDE LM]]="Denial of Service",Formatação!H$6,IF(Tabela1[[#This Row],[STRIDE LM]]="Elevation of Privilege",Formatação!H$7,IF(Tabela1[[#This Row],[STRIDE LM]]="Lateral Movement",Formatação!H$8,Errado)))))))} -> Integridade | E31: Tampering | F31: {=IF(Tabela1[[#This Row],[STRIDE LM]]="Information Disclosure",Formatação!J$5,IF(Tabela1[[#This Row],[STRIDE LM]]="Repudiation",Formatação!J$4,IF(Tabela1[[#This Row],[STRIDE LM]]="Spoofing",Formatação!J$2,IF(Tabela1[[#This Row],[STRIDE LM]]="Tampering",Formatação!J$3, IF(Tabela1[[#This Row],[STRIDE LM]]="Denial of Service",Formatação!J$6,IF(Tabela1[[#This Row],[STRIDE LM]]="Elevation of Privilege",Formatação!J$7,IF(Tabela1[[#This Row],[STRIDE LM]]="Lateral Movement",Formatação!J$8,Errado)))))))} -> Danos a imagem | G31: A06:2021-Vulnerable and Outdated Components | J31: Sim | K31: Sim | L31: Não | M31: Não
A32: O Banco de Dados deve utilizar validações de entrada para evitar ataques de injeção, como SQL injection, que podem comprometer a integridade dos dados | C32: Banco de dados | D32: {=IF(Tabela1[[#This Row],[STRIDE LM]]="Information Disclosure",Formatação!H$5,IF(Tabela1[[#This Row],[STRIDE LM]]="Repudiation",Formatação!H$4,IF(Tabela1[[#This Row],[STRIDE LM]]="Spoofing",Formatação!H$2,IF(Tabela1[[#This Row],[STRIDE LM]]="Tampering",Formatação!H$3, IF(Tabela1[[#This Row],[STRIDE LM]]="Denial of Service",Formatação!H$6,IF(Tabela1[[#This Row],[STRIDE LM]]="Elevation of Privilege",Formatação!H$7,IF(Tabela1[[#This Row],[STRIDE LM]]="Lateral Movement",Formatação!H$8,Errado)))))))} -> Integridade | E32: Tampering | F32: {=IF(Tabela1[[#This Row],[STRIDE LM]]="Information Disclosure",Formatação!J$5,IF(Tabela1[[#This Row],[STRIDE LM]]="Repudiation",Formatação!J$4,IF(Tabela1[[#This Row],[STRIDE LM]]="Spoofing",Formatação!J$2,IF(Tabela1[[#This Row],[STRIDE LM]]="Tampering",Formatação!J$3, IF(Tabela1[[#This Row],[STRIDE LM]]="Denial of Service",Formatação!J$6,IF(Tabela1[[#This Row],[STRIDE LM]]="Elevation of Privilege",Formatação!J$7,IF(Tabela1[[#This Row],[STRIDE LM]]="Lateral Movement",Formatação!J$8,Errado)))))))} -> Danos a imagem | G32: A03:2021-Injection | J32: Sim | K32: Não | L32: Não | M32: Não
A33: Realizar Periodicamente Auditorias de configurações e implementar ferramentas de monitoramento de conformidade, com automação na configuração. | C33: Banco de dados | D33: {=IF(Tabela1[[#This Row],[STRIDE LM]]="Information Disclosure",Formatação!H$5,IF(Tabela1[[#This Row],[STRIDE LM]]="Repudiation",Formatação!H$4,IF(Tabela1[[#This Row],[STRIDE LM]]="Spoofing",Formatação!H$2,IF(Tabela1[[#This Row],[STRIDE LM]]="Tampering",Formatação!H$3, IF(Tabela1[[#This Row],[STRIDE LM]]="Denial of Service",Formatação!H$6,IF(Tabela1[[#This Row],[STRIDE LM]]="Elevation of Privilege",Formatação!H$7,IF(Tabela1[[#This Row],[STRIDE LM]]="Lateral Movement",Formatação!H$8,Errado)))))))} -> Não repúdio | E33: Repudiation | F33: {=IF(Tabela1[[#This Row],[STRIDE LM]]="Information Disclosure",Formatação!J$5,IF(Tabela1[[#This Row],[STRIDE LM]]="Repudiation",Formatação!J$4,IF(Tabela1[[#This Row],[STRIDE LM]]="Spoofing",Formatação!J$2,IF(Tabela1[[#This Row],[STRIDE LM]]="Tampering",Formatação!J$3, IF(Tabela1[[#This Row],[STRIDE LM]]="Denial of Service",Formatação!J$6,IF(Tabela1[[#This Row],[STRIDE LM]]="Elevation of Privilege",Formatação!J$7,IF(Tabela1[[#This Row],[STRIDE LM]]="Lateral Movement",Formatação!J$8,Errado)))))))} -> Regulatório/Compliance | G33: A05:2021-Security Misconfiguration | J33: Sim | K33: Sim | L33: Não | M33: Não
A34: Implementar controles de acesso assim garantindo que só pessoas autorizadas possam acessar o ambiente e utilizar criptografia em repouso (AES-256) para proteger as informações sensiveis. | C34: Banco de dados | D34: {=IF(Tabela1[[#This Row],[STRIDE LM]]="Information Disclosure",Formatação!H$5,IF(Tabela1[[#This Row],[STRIDE LM]]="Repudiation",Formatação!H$4,IF(Tabela1[[#This Row],[STRIDE LM]]="Spoofing",Formatação!H$2,IF(Tabela1[[#This Row],[STRIDE LM]]="Tampering",Formatação!H$3, IF(Tabela1[[#This Row],[STRIDE LM]]="Denial of Service",Formatação!H$6,IF(Tabela1[[#This Row],[STRIDE LM]]="Elevation of Privilege",Formatação!H$7,IF(Tabela1[[#This Row],[STRIDE LM]]="Lateral Movement",Formatação!H$8,Errado)))))))} -> Confidencialidade | E34: Information Disclosure | F34: {=IF(Tabela1[[#This Row],[STRIDE LM]]="Information Disclosure",Formatação!J$5,IF(Tabela1[[#This Row],[STRIDE LM]]="Repudiation",Formatação!J$4,IF(Tabela1[[#This Row],[STRIDE LM]]="Spoofing",Formatação!J$2,IF(Tabela1[[#This Row],[STRIDE LM]]="Tampering",Formatação!J$3, IF(Tabela1[[#This Row],[STRIDE LM]]="Denial of Service",Formatação!J$6,IF(Tabela1[[#This Row],[STRIDE LM]]="Elevation of Privilege",Formatação!J$7,IF(Tabela1[[#This Row],[STRIDE LM]]="Lateral Movement",Formatação!J$8,Errado)))))))} -> Vazamento de dados | G34: A01:2021-Broken Access Control | J34: Sim | K34: Sim | L34: Não | M34: Não
A35: Implementação de rotinas de atualizações rápidas de patches de segurança e monitoramento continuo de ameaças, impedindo a exploração de vulnerabilidades | C35: Banco de dados | D35: {=IF(Tabela1[[#This Row],[STRIDE LM]]="Information Disclosure",Formatação!H$5,IF(Tabela1[[#This Row],[STRIDE LM]]="Repudiation",Formatação!H$4,IF(Tabela1[[#This Row],[STRIDE LM]]="Spoofing",Formatação!H$2,IF(Tabela1[[#This Row],[STRIDE LM]]="Tampering",Formatação!H$3, IF(Tabela1[[#This Row],[STRIDE LM]]="Denial of Service",Formatação!H$6,IF(Tabela1[[#This Row],[STRIDE LM]]="Elevation of Privilege",Formatação!H$7,IF(Tabela1[[#This Row],[STRIDE LM]]="Lateral Movement",Formatação!H$8,Errado)))))))} -> Integridade | E35: Tampering | F35: {=IF(Tabela1[[#This Row],[STRIDE LM]]="Information Disclosure",Formatação!J$5,IF(Tabela1[[#This Row],[STRIDE LM]]="Repudiation",Formatação!J$4,IF(Tabela1[[#This Row],[STRIDE LM]]="Spoofing",Formatação!J$2,IF(Tabela1[[#This Row],[STRIDE LM]]="Tampering",Formatação!J$3, IF(Tabela1[[#This Row],[STRIDE LM]]="Denial of Service",Formatação!J$6,IF(Tabela1[[#This Row],[STRIDE LM]]="Elevation of Privilege",Formatação!J$7,IF(Tabela1[[#This Row],[STRIDE LM]]="Lateral Movement",Formatação!J$8,Errado)))))))} -> Danos a imagem | G35: A06:2021-Vulnerable and Outdated Components | J35: Sim | K35: Sim | L35: Não | M35: Não
A36: A aplicação precisa estar protegida com um Web Application Firewall (WAF) na regra "deny high" | C36: Desenvolvimento Seguro | D36: {=IF(Tabela1[[#This Row],[STRIDE LM]]="Information Disclosure",Formatação!H$5,IF(Tabela1[[#This Row],[STRIDE LM]]="Repudiation",Formatação!H$4,IF(Tabela1[[#This Row],[STRIDE LM]]="Spoofing",Formatação!H$2,IF(Tabela1[[#This Row],[STRIDE LM]]="Tampering",Formatação!H$3, IF(Tabela1[[#This Row],[STRIDE LM]]="Denial of Service",Formatação!H$6,IF(Tabela1[[#This Row],[STRIDE LM]]="Elevation of Privilege",Formatação!H$7,IF(Tabela1[[#This Row],[STRIDE LM]]="Lateral Movement",Formatação!H$8,Errado)))))))} -> Integridade | E36: Tampering | F36: {=IF(Tabela1[[#This Row],[STRIDE LM]]="Information Disclosure",Formatação!J$5,IF(Tabela1[[#This Row],[STRIDE LM]]="Repudiation",Formatação!J$4,IF(Tabela1[[#This Row],[STRIDE LM]]="Spoofing",Formatação!J$2,IF(Tabela1[[#This Row],[STRIDE LM]]="Tampering",Formatação!J$3, IF(Tabela1[[#This Row],[STRIDE LM]]="Denial of Service",Formatação!J$6,IF(Tabela1[[#This Row],[STRIDE LM]]="Elevation of Privilege",Formatação!J$7,IF(Tabela1[[#This Row],[STRIDE LM]]="Lateral Movement",Formatação!J$8,Errado)))))))} -> Danos a imagem | G36: A03:2021-Injection | J36: Não | K36: Sim | L36: Sim | M36: Sim | N36: ModSecurity | O36: Utilizar bibliotecas seguras como OWASP ESAPI e implementar um WAF (Web Application Firewall).
A37: É mandatório que a solução suporte e implemente o modelo de autorização baseado em perfis de acesso conforme o padrão RBAC (Role Based Access Control) | C37: Identidade e Acesso | D37: {=IF(Tabela1[[#This Row],[STRIDE LM]]="Information Disclosure",Formatação!H$5,IF(Tabela1[[#This Row],[STRIDE LM]]="Repudiation",Formatação!H$4,IF(Tabela1[[#This Row],[STRIDE LM]]="Spoofing",Formatação!H$2,IF(Tabela1[[#This Row],[STRIDE LM]]="Tampering",Formatação!H$3, IF(Tabela1[[#This Row],[STRIDE LM]]="Denial of Service",Formatação!H$6,IF(Tabela1[[#This Row],[STRIDE LM]]="Elevation of Privilege",Formatação!H$7,IF(Tabela1[[#This Row],[STRIDE LM]]="Lateral Movement",Formatação!H$8,Errado)))))))} -> Não repúdio | E37: Repudiation | F37: {=IF(Tabela1[[#This Row],[STRIDE LM]]="Information Disclosure",Formatação!J$5,IF(Tabela1[[#This Row],[STRIDE LM]]="Repudiation",Formatação!J$4,IF(Tabela1[[#This Row],[STRIDE LM]]="Spoofing",Formatação!J$2,IF(Tabela1[[#This Row],[STRIDE LM]]="Tampering",Formatação!J$3, IF(Tabela1[[#This Row],[STRIDE LM]]="Denial of Service",Formatação!J$6,IF(Tabela1[[#This Row],[STRIDE LM]]="Elevation of Privilege",Formatação!J$7,IF(Tabela1[[#This Row],[STRIDE LM]]="Lateral Movement",Formatação!J$8,Errado)))))))} -> Regulatório/Compliance | G37: A01:2021-Broken Access Control | J37: Sim | K37: Sim | L37: Sim | M37: Sim | N37: Open Policy, Implementação de RBAC/ABAC | O37: Definir roles claras, implementar políticas IAM (Identity and Access Management) e armazenar logs imutáveis.
A38: Todo e qualquer consumo ao banco de dados deve passar por uma camada de orquestração (API Gateway ou barramento, por exemplo) | C38: Banco de dados | D38: {=IF(Tabela1[[#This Row],[STRIDE LM]]="Information Disclosure",Formatação!H$5,IF(Tabela1[[#This Row],[STRIDE LM]]="Repudiation",Formatação!H$4,IF(Tabela1[[#This Row],[STRIDE LM]]="Spoofing",Formatação!H$2,IF(Tabela1[[#This Row],[STRIDE LM]]="Tampering",Formatação!H$3, IF(Tabela1[[#This Row],[STRIDE LM]]="Denial of Service",Formatação!H$6,IF(Tabela1[[#This Row],[STRIDE LM]]="Elevation of Privilege",Formatação!H$7,IF(Tabela1[[#This Row],[STRIDE LM]]="Lateral Movement",Formatação!H$8,Errado)))))))} -> Confidencialidade | E38: Information Disclosure | F38: {=IF(Tabela1[[#This Row],[STRIDE LM]]="Information Disclosure",Formatação!J$5,IF(Tabela1[[#This Row],[STRIDE LM]]="Repudiation",Formatação!J$4,IF(Tabela1[[#This Row],[STRIDE LM]]="Spoofing",Formatação!J$2,IF(Tabela1[[#This Row],[STRIDE LM]]="Tampering",Formatação!J$3, IF(Tabela1[[#This Row],[STRIDE LM]]="Denial of Service",Formatação!J$6,IF(Tabela1[[#This Row],[STRIDE LM]]="Elevation of Privilege",Formatação!J$7,IF(Tabela1[[#This Row],[STRIDE LM]]="Lateral Movement",Formatação!J$8,Errado)))))))} -> Vazamento de dados | G38: A08:2021-Software and Data Integrity Failures | J38: Sim | K38: Sim | L38: Sim | M38: Sim | N38: Oracle Service Bus / Microserviço | O38: Configurar rate limiting via API Gateway e utilizar Hystrix para gerenciamento de falhas.
A39: Utilize assinaturas digitais para garantir a autenticidade e a origem das mensagens, permitindo que a fonte seja verificada de forma irrefutável. | C39: Desenvolvimento Seguro | D39: {=IF(Tabela1[[#This Row],[STRIDE LM]]="Information Disclosure",Formatação!H$5,IF(Tabela1[[#This Row],[STRIDE LM]]="Repudiation",Formatação!H$4,IF(Tabela1[[#This Row],[STRIDE LM]]="Spoofing",Formatação!H$2,IF(Tabela1[[#This Row],[STRIDE LM]]="Tampering",Formatação!H$3, IF(Tabela1[[#This Row],[STRIDE LM]]="Denial of Service",Formatação!H$6,IF(Tabela1[[#This Row],[STRIDE LM]]="Elevation of Privilege",Formatação!H$7,IF(Tabela1[[#This Row],[STRIDE LM]]="Lateral Movement",Formatação!H$8,Errado)))))))} -> Contenção | E39: Lateral Movement | F39: {=IF(Tabela1[[#This Row],[STRIDE LM]]="Information Disclosure",Formatação!J$5,IF(Tabela1[[#This Row],[STRIDE LM]]="Repudiation",Formatação!J$4,IF(Tabela1[[#This Row],[STRIDE LM]]="Spoofing",Formatação!J$2,IF(Tabela1[[#This Row],[STRIDE LM]]="Tampering",Formatação!J$3, IF(Tabela1[[#This Row],[STRIDE LM]]="Denial of Service",Formatação!J$6,IF(Tabela1[[#This Row],[STRIDE LM]]="Elevation of Privilege",Formatação!J$7,IF(Tabela1[[#This Row],[STRIDE LM]]="Lateral Movement",Formatação!J$8,Errado)))))))} -> Vazamento de dados | G39: A08:2021 - Software and Data Integrity Failures | J39: Sim | K39: Sim | L39: Sim | M39: Sim | N39: Monitoramento de dependências e aplicação de patching automático. | O39: Utilizar ferramentas como OWASP Dependency-Check e SBOM (Software Bill of Materials).
A40: O serviço precisa disponibilizar um dash de Healthcheck que mostre itens de compliance de configuração dos itens de MFA, criptografia entre outros controles de segurança | C40: Banco de dados | D40: {=IF(Tabela1[[#This Row],[STRIDE LM]]="Information Disclosure",Formatação!H$5,IF(Tabela1[[#This Row],[STRIDE LM]]="Repudiation",Formatação!H$4,IF(Tabela1[[#This Row],[STRIDE LM]]="Spoofing",Formatação!H$2,IF(Tabela1[[#This Row],[STRIDE LM]]="Tampering",Formatação!H$3, IF(Tabela1[[#This Row],[STRIDE LM]]="Denial of Service",Formatação!H$6,IF(Tabela1[[#This Row],[STRIDE LM]]="Elevation of Privilege",Formatação!H$7,IF(Tabela1[[#This Row],[STRIDE LM]]="Lateral Movement",Formatação!H$8,Errado)))))))} -> Confidencialidade | E40: Information Disclosure | F40: {=IF(Tabela1[[#This Row],[STRIDE LM]]="Information Disclosure",Formatação!J$5,IF(Tabela1[[#This Row],[STRIDE LM]]="Repudiation",Formatação!J$4,IF(Tabela1[[#This Row],[STRIDE LM]]="Spoofing",Formatação!J$2,IF(Tabela1[[#This Row],[STRIDE LM]]="Tampering",Formatação!J$3, IF(Tabela1[[#This Row],[STRIDE LM]]="Denial of Service",Formatação!J$6,IF(Tabela1[[#This Row],[STRIDE LM]]="Elevation of Privilege",Formatação!J$7,IF(Tabela1[[#This Row],[STRIDE LM]]="Lateral Movement",Formatação!J$8,Errado)))))))} -> Vazamento de dados | G40: A04:2021-Insecure Design | J40: Não | K40: Sim | L40: Sim | M40: Sim | N40: Implementação de isolamento de dados por tenant. | O40: Configurar bancos de dados multi-tenant, garantindo encriptação per-tenant e aplicação de access control policies.
A41: É necessário garantir que os hosts utilizados nos projetos estejam com os SO adequados (não é permitido a subida de SO obsoleto) | C41: Hosts | D41: {=IF(Tabela1[[#This Row],[STRIDE LM]]="Information Disclosure",Formatação!H$5,IF(Tabela1[[#This Row],[STRIDE LM]]="Repudiation",Formatação!H$4,IF(Tabela1[[#This Row],[STRIDE LM]]="Spoofing",Formatação!H$2,IF(Tabela1[[#This Row],[STRIDE LM]]="Tampering",Formatação!H$3, IF(Tabela1[[#This Row],[STRIDE LM]]="Denial of Service",Formatação!H$6,IF(Tabela1[[#This Row],[STRIDE LM]]="Elevation of Privilege",Formatação!H$7,IF(Tabela1[[#This Row],[STRIDE LM]]="Lateral Movement",Formatação!H$8,Errado)))))))} -> Integridade | E41: Tampering | F41: {=IF(Tabela1[[#This Row],[STRIDE LM]]="Information Disclosure",Formatação!J$5,IF(Tabela1[[#This Row],[STRIDE LM]]="Repudiation",Formatação!J$4,IF(Tabela1[[#This Row],[STRIDE LM]]="Spoofing",Formatação!J$2,IF(Tabela1[[#This Row],[STRIDE LM]]="Tampering",Formatação!J$3, IF(Tabela1[[#This Row],[STRIDE LM]]="Denial of Service",Formatação!J$6,IF(Tabela1[[#This Row],[STRIDE LM]]="Elevation of Privilege",Formatação!J$7,IF(Tabela1[[#This Row],[STRIDE LM]]="Lateral Movement",Formatação!J$8,Errado)))))))} -> Danos a imagem | G41: A06:2021-Vulnerable and Outdated Components | J41: Sim | K41: Sim | L41: Não | M41: Não | N41: Hardenização do SO | O41: Garantir que o Host seja provisionado pelo Plataform Code, em caso de provisionamento manual o mesmo deve ser validado que foi usado a imagem homologada.
A42: Implementar autenticação multifatorial (MFA) para todas as contas | C42: Hosts | D42: {=IF(Tabela1[[#This Row],[STRIDE LM]]="Information Disclosure",Formatação!H$5,IF(Tabela1[[#This Row],[STRIDE LM]]="Repudiation",Formatação!H$4,IF(Tabela1[[#This Row],[STRIDE LM]]="Spoofing",Formatação!H$2,IF(Tabela1[[#This Row],[STRIDE LM]]="Tampering",Formatação!H$3, IF(Tabela1[[#This Row],[STRIDE LM]]="Denial of Service",Formatação!H$6,IF(Tabela1[[#This Row],[STRIDE LM]]="Elevation of Privilege",Formatação!H$7,IF(Tabela1[[#This Row],[STRIDE LM]]="Lateral Movement",Formatação!H$8,Errado)))))))} -> Autenticação | E42: Spoofing | F42: {=IF(Tabela1[[#This Row],[STRIDE LM]]="Information Disclosure",Formatação!J$5,IF(Tabela1[[#This Row],[STRIDE LM]]="Repudiation",Formatação!J$4,IF(Tabela1[[#This Row],[STRIDE LM]]="Spoofing",Formatação!J$2,IF(Tabela1[[#This Row],[STRIDE LM]]="Tampering",Formatação!J$3, IF(Tabela1[[#This Row],[STRIDE LM]]="Denial of Service",Formatação!J$6,IF(Tabela1[[#This Row],[STRIDE LM]]="Elevation of Privilege",Formatação!J$7,IF(Tabela1[[#This Row],[STRIDE LM]]="Lateral Movement",Formatação!J$8,Errado)))))))} -> Fraudes/Vazamento de dados | G42: A07:2021-Identification and Authentication Failures | J42: Sim | K42: Sim | L42: Não | M42: Não | N42: Authenticator
A43: Implementar criptografia para dados em repouso e em trânsito, protegendo informações sensíveis de acesso não autorizado. | C43: Hosts | D43: {=IF(Tabela1[[#This Row],[STRIDE LM]]="Information Disclosure",Formatação!H$5,IF(Tabela1[[#This Row],[STRIDE LM]]="Repudiation",Formatação!H$4,IF(Tabela1[[#This Row],[STRIDE LM]]="Spoofing",Formatação!H$2,IF(Tabela1[[#This Row],[STRIDE LM]]="Tampering",Formatação!H$3, IF(Tabela1[[#This Row],[STRIDE LM]]="Denial of Service",Formatação!H$6,IF(Tabela1[[#This Row],[STRIDE LM]]="Elevation of Privilege",Formatação!H$7,IF(Tabela1[[#This Row],[STRIDE LM]]="Lateral Movement",Formatação!H$8,Errado)))))))} -> Confidencialidade | E43: Information Disclosure | F43: {=IF(Tabela1[[#This Row],[STRIDE LM]]="Information Disclosure",Formatação!J$5,IF(Tabela1[[#This Row],[STRIDE LM]]="Repudiation",Formatação!J$4,IF(Tabela1[[#This Row],[STRIDE LM]]="Spoofing",Formatação!J$2,IF(Tabela1[[#This Row],[STRIDE LM]]="Tampering",Formatação!J$3, IF(Tabela1[[#This Row],[STRIDE LM]]="Denial of Service",Formatação!J$6,IF(Tabela1[[#This Row],[STRIDE LM]]="Elevation of Privilege",Formatação!J$7,IF(Tabela1[[#This Row],[STRIDE LM]]="Lateral Movement",Formatação!J$8,Errado)))))))} -> Vazamento de dados | G43: A02:2021-Cryptographic Failures | J43: Sim | K43: Sim | L43: Não | M43: Não | N43: Bitlocker (Windows), dm-crypt (Linux), TLS
A44: Implementar políticas que garantam a retenção adequada de logs para auditoria e investigação. | C44: Hosts | D44: {=IF(Tabela1[[#This Row],[STRIDE LM]]="Information Disclosure",Formatação!H$5,IF(Tabela1[[#This Row],[STRIDE LM]]="Repudiation",Formatação!H$4,IF(Tabela1[[#This Row],[STRIDE LM]]="Spoofing",Formatação!H$2,IF(Tabela1[[#This Row],[STRIDE LM]]="Tampering",Formatação!H$3, IF(Tabela1[[#This Row],[STRIDE LM]]="Denial of Service",Formatação!H$6,IF(Tabela1[[#This Row],[STRIDE LM]]="Elevation of Privilege",Formatação!H$7,IF(Tabela1[[#This Row],[STRIDE LM]]="Lateral Movement",Formatação!H$8,Errado)))))))} -> Não repúdio | E44: Repudiation | F44: {=IF(Tabela1[[#This Row],[STRIDE LM]]="Information Disclosure",Formatação!J$5,IF(Tabela1[[#This Row],[STRIDE LM]]="Repudiation",Formatação!J$4,IF(Tabela1[[#This Row],[STRIDE LM]]="Spoofing",Formatação!J$2,IF(Tabela1[[#This Row],[STRIDE LM]]="Tampering",Formatação!J$3, IF(Tabela1[[#This Row],[STRIDE LM]]="Denial of Service",Formatação!J$6,IF(Tabela1[[#This Row],[STRIDE LM]]="Elevation of Privilege",Formatação!J$7,IF(Tabela1[[#This Row],[STRIDE LM]]="Lateral Movement",Formatação!J$8,Errado)))))))} -> Regulatório/Compliance | G44: A09:2021-Security Logging and Monitoring Failures | J44: Sim | K44: Sim | L44: Não | M44: Não | N44: SIEM
A45: Implementar RBAC para gerenciar acesso a nivel infra | C45: Hosts | D45: {=IF(Tabela1[[#This Row],[STRIDE LM]]="Information Disclosure",Formatação!H$5,IF(Tabela1[[#This Row],[STRIDE LM]]="Repudiation",Formatação!H$4,IF(Tabela1[[#This Row],[STRIDE LM]]="Spoofing",Formatação!H$2,IF(Tabela1[[#This Row],[STRIDE LM]]="Tampering",Formatação!H$3, IF(Tabela1[[#This Row],[STRIDE LM]]="Denial of Service",Formatação!H$6,IF(Tabela1[[#This Row],[STRIDE LM]]="Elevation of Privilege",Formatação!H$7,IF(Tabela1[[#This Row],[STRIDE LM]]="Lateral Movement",Formatação!H$8,Errado)))))))} -> Autenticação | E45: Spoofing | F45: {=IF(Tabela1[[#This Row],[STRIDE LM]]="Information Disclosure",Formatação!J$5,IF(Tabela1[[#This Row],[STRIDE LM]]="Repudiation",Formatação!J$4,IF(Tabela1[[#This Row],[STRIDE LM]]="Spoofing",Formatação!J$2,IF(Tabela1[[#This Row],[STRIDE LM]]="Tampering",Formatação!J$3, IF(Tabela1[[#This Row],[STRIDE LM]]="Denial of Service",Formatação!J$6,IF(Tabela1[[#This Row],[STRIDE LM]]="Elevation of Privilege",Formatação!J$7,IF(Tabela1[[#This Row],[STRIDE LM]]="Lateral Movement",Formatação!J$8,Errado)))))))} -> Fraudes/Vazamento de dados | G45: A01:2021-Broken Access Control | J45: Sim | K45: Sim | L45: Não | M45: Não | N45: Analise de perfil / IDP
A46: Implementar segmentação de rede para limitar o movimento lateral | C46: Hosts | D46: {=IF(Tabela1[[#This Row],[STRIDE LM]]="Information Disclosure",Formatação!H$5,IF(Tabela1[[#This Row],[STRIDE LM]]="Repudiation",Formatação!H$4,IF(Tabela1[[#This Row],[STRIDE LM]]="Spoofing",Formatação!H$2,IF(Tabela1[[#This Row],[STRIDE LM]]="Tampering",Formatação!H$3, IF(Tabela1[[#This Row],[STRIDE LM]]="Denial of Service",Formatação!H$6,IF(Tabela1[[#This Row],[STRIDE LM]]="Elevation of Privilege",Formatação!H$7,IF(Tabela1[[#This Row],[STRIDE LM]]="Lateral Movement",Formatação!H$8,Errado)))))))} -> Contenção | E46: Lateral Movement | F46: {=IF(Tabela1[[#This Row],[STRIDE LM]]="Information Disclosure",Formatação!J$5,IF(Tabela1[[#This Row],[STRIDE LM]]="Repudiation",Formatação!J$4,IF(Tabela1[[#This Row],[STRIDE LM]]="Spoofing",Formatação!J$2,IF(Tabela1[[#This Row],[STRIDE LM]]="Tampering",Formatação!J$3, IF(Tabela1[[#This Row],[STRIDE LM]]="Denial of Service",Formatação!J$6,IF(Tabela1[[#This Row],[STRIDE LM]]="Elevation of Privilege",Formatação!J$7,IF(Tabela1[[#This Row],[STRIDE LM]]="Lateral Movement",Formatação!J$8,Errado)))))))} -> Vazamento de dados | G46: A04:2021-Insecure Design | J46: Sim | K46: Sim | L46: Não | M46: Não | N46: Microsegmentação
A47: O ativo precisa estar integrado ao CMDB, garantindo a centralização dos ativos no inventário oficial | C47: Hosts | D47: {=IF(Tabela1[[#This Row],[STRIDE LM]]="Information Disclosure",Formatação!H$5,IF(Tabela1[[#This Row],[STRIDE LM]]="Repudiation",Formatação!H$4,IF(Tabela1[[#This Row],[STRIDE LM]]="Spoofing",Formatação!H$2,IF(Tabela1[[#This Row],[STRIDE LM]]="Tampering",Formatação!H$3, IF(Tabela1[[#This Row],[STRIDE LM]]="Denial of Service",Formatação!H$6,IF(Tabela1[[#This Row],[STRIDE LM]]="Elevation of Privilege",Formatação!H$7,IF(Tabela1[[#This Row],[STRIDE LM]]="Lateral Movement",Formatação!H$8,Errado)))))))} -> Autenticação | E47: Spoofing | F47: {=IF(Tabela1[[#This Row],[STRIDE LM]]="Information Disclosure",Formatação!J$5,IF(Tabela1[[#This Row],[STRIDE LM]]="Repudiation",Formatação!J$4,IF(Tabela1[[#This Row],[STRIDE LM]]="Spoofing",Formatação!J$2,IF(Tabela1[[#This Row],[STRIDE LM]]="Tampering",Formatação!J$3, IF(Tabela1[[#This Row],[STRIDE LM]]="Denial of Service",Formatação!J$6,IF(Tabela1[[#This Row],[STRIDE LM]]="Elevation of Privilege",Formatação!J$7,IF(Tabela1[[#This Row],[STRIDE LM]]="Lateral Movement",Formatação!J$8,Errado)))))))} -> Fraudes/Vazamento de dados | G47: A00: No Application | J47: Sim | K47: Sim | L47: Não | M47: Não | N47: CMDB
A48: O servidor deverá estar integrado a uma solução de PAM | C48: Hosts | D48: {=IF(Tabela1[[#This Row],[STRIDE LM]]="Information Disclosure",Formatação!H$5,IF(Tabela1[[#This Row],[STRIDE LM]]="Repudiation",Formatação!H$4,IF(Tabela1[[#This Row],[STRIDE LM]]="Spoofing",Formatação!H$2,IF(Tabela1[[#This Row],[STRIDE LM]]="Tampering",Formatação!H$3, IF(Tabela1[[#This Row],[STRIDE LM]]="Denial of Service",Formatação!H$6,IF(Tabela1[[#This Row],[STRIDE LM]]="Elevation of Privilege",Formatação!H$7,IF(Tabela1[[#This Row],[STRIDE LM]]="Lateral Movement",Formatação!H$8,Errado)))))))} -> Autorização | E48: Elevation of Privilege | F48: {=IF(Tabela1[[#This Row],[STRIDE LM]]="Information Disclosure",Formatação!J$5,IF(Tabela1[[#This Row],[STRIDE LM]]="Repudiation",Formatação!J$4,IF(Tabela1[[#This Row],[STRIDE LM]]="Spoofing",Formatação!J$2,IF(Tabela1[[#This Row],[STRIDE LM]]="Tampering",Formatação!J$3, IF(Tabela1[[#This Row],[STRIDE LM]]="Denial of Service",Formatação!J$6,IF(Tabela1[[#This Row],[STRIDE LM]]="Elevation of Privilege",Formatação!J$7,IF(Tabela1[[#This Row],[STRIDE LM]]="Lateral Movement",Formatação!J$8,Errado)))))))} -> Danos financeiros/Vazamento de dados | G48: A01:2021-Broken Access Control | J48: Sim | K48: Sim | L48: Não | M48: Não | N48: Caso o servidor esteja sendo provisionado via Plataform Code o mesmo é automatica adicionado a solução PAM homologada da empresa, bastando abrir chamado para solicitação de login de acesso. | O48: Abrir chamado para solicitação de login de acesso para o host
A49: Todos os servidores devem possuir imagem de SO e BD padrão da Vivo (com EDR, Antivírus, conector de SIEM e agente de Scan de Infra) | C49: Hosts | D49: {=IF(Tabela1[[#This Row],[STRIDE LM]]="Information Disclosure",Formatação!H$5,IF(Tabela1[[#This Row],[STRIDE LM]]="Repudiation",Formatação!H$4,IF(Tabela1[[#This Row],[STRIDE LM]]="Spoofing",Formatação!H$2,IF(Tabela1[[#This Row],[STRIDE LM]]="Tampering",Formatação!H$3, IF(Tabela1[[#This Row],[STRIDE LM]]="Denial of Service",Formatação!H$6,IF(Tabela1[[#This Row],[STRIDE LM]]="Elevation of Privilege",Formatação!H$7,IF(Tabela1[[#This Row],[STRIDE LM]]="Lateral Movement",Formatação!H$8,Errado)))))))} -> Confidencialidade | E49: Information Disclosure | F49: {=IF(Tabela1[[#This Row],[STRIDE LM]]="Information Disclosure",Formatação!J$5,IF(Tabela1[[#This Row],[STRIDE LM]]="Repudiation",Formatação!J$4,IF(Tabela1[[#This Row],[STRIDE LM]]="Spoofing",Formatação!J$2,IF(Tabela1[[#This Row],[STRIDE LM]]="Tampering",Formatação!J$3, IF(Tabela1[[#This Row],[STRIDE LM]]="Denial of Service",Formatação!J$6,IF(Tabela1[[#This Row],[STRIDE LM]]="Elevation of Privilege",Formatação!J$7,IF(Tabela1[[#This Row],[STRIDE LM]]="Lateral Movement",Formatação!J$8,Errado)))))))} -> Vazamento de dados | G49: A05:2021-Security Misconfiguration | J49: Sim | K49: Sim | L49: Não | M49: Não | N49: Hardenização do SO | O49: Recursos criados pelo Plataform Code já utilizam a golden image da Vivo, para Recursos criados de forma manual deverá procura time de SO
A50: Utilizar soluções de prevenção de perda de dados para monitorar e proteger dados sensíveis. | C50: Hosts | D50: {=IF(Tabela1[[#This Row],[STRIDE LM]]="Information Disclosure",Formatação!H$5,IF(Tabela1[[#This Row],[STRIDE LM]]="Repudiation",Formatação!H$4,IF(Tabela1[[#This Row],[STRIDE LM]]="Spoofing",Formatação!H$2,IF(Tabela1[[#This Row],[STRIDE LM]]="Tampering",Formatação!H$3, IF(Tabela1[[#This Row],[STRIDE LM]]="Denial of Service",Formatação!H$6,IF(Tabela1[[#This Row],[STRIDE LM]]="Elevation of Privilege",Formatação!H$7,IF(Tabela1[[#This Row],[STRIDE LM]]="Lateral Movement",Formatação!H$8,Errado)))))))} -> Confidencialidade | E50: Information Disclosure | F50: {=IF(Tabela1[[#This Row],[STRIDE LM]]="Information Disclosure",Formatação!J$5,IF(Tabela1[[#This Row],[STRIDE LM]]="Repudiation",Formatação!J$4,IF(Tabela1[[#This Row],[STRIDE LM]]="Spoofing",Formatação!J$2,IF(Tabela1[[#This Row],[STRIDE LM]]="Tampering",Formatação!J$3, IF(Tabela1[[#This Row],[STRIDE LM]]="Denial of Service",Formatação!J$6,IF(Tabela1[[#This Row],[STRIDE LM]]="Elevation of Privilege",Formatação!J$7,IF(Tabela1[[#This Row],[STRIDE LM]]="Lateral Movement",Formatação!J$8,Errado)))))))} -> Vazamento de dados | G50: A03:2021-Injection | J50: Sim | K50: Sim | L50: Não | M50: Não | N50: DLP
A51: A aplicação precisa estar protegida com um Web Application Firewall (WAF) | C51: Infraestrutura | D51: {=IF(Tabela1[[#This Row],[STRIDE LM]]="Information Disclosure",Formatação!H$5,IF(Tabela1[[#This Row],[STRIDE LM]]="Repudiation",Formatação!H$4,IF(Tabela1[[#This Row],[STRIDE LM]]="Spoofing",Formatação!H$2,IF(Tabela1[[#This Row],[STRIDE LM]]="Tampering",Formatação!H$3, IF(Tabela1[[#This Row],[STRIDE LM]]="Denial of Service",Formatação!H$6,IF(Tabela1[[#This Row],[STRIDE LM]]="Elevation of Privilege",Formatação!H$7,IF(Tabela1[[#This Row],[STRIDE LM]]="Lateral Movement",Formatação!H$8,Errado)))))))} -> Integridade | E51: Tampering | F51: {=IF(Tabela1[[#This Row],[STRIDE LM]]="Information Disclosure",Formatação!J$5,IF(Tabela1[[#This Row],[STRIDE LM]]="Repudiation",Formatação!J$4,IF(Tabela1[[#This Row],[STRIDE LM]]="Spoofing",Formatação!J$2,IF(Tabela1[[#This Row],[STRIDE LM]]="Tampering",Formatação!J$3, IF(Tabela1[[#This Row],[STRIDE LM]]="Denial of Service",Formatação!J$6,IF(Tabela1[[#This Row],[STRIDE LM]]="Elevation of Privilege",Formatação!J$7,IF(Tabela1[[#This Row],[STRIDE LM]]="Lateral Movement",Formatação!J$8,Errado)))))))} -> Danos a imagem | G51: A05:2021-Security Misconfiguration | J51: Sim | K51: Sim | L51: Sim | M51: Sim
A52: Antes da subida em produção é necessário executar um EHT (Pentest) e corrigir todos os riscos e vulnerabilidades encontradas | C52: Infraestrutura | D52: {=IF(Tabela1[[#This Row],[STRIDE LM]]="Information Disclosure",Formatação!H$5,IF(Tabela1[[#This Row],[STRIDE LM]]="Repudiation",Formatação!H$4,IF(Tabela1[[#This Row],[STRIDE LM]]="Spoofing",Formatação!H$2,IF(Tabela1[[#This Row],[STRIDE LM]]="Tampering",Formatação!H$3, IF(Tabela1[[#This Row],[STRIDE LM]]="Denial of Service",Formatação!H$6,IF(Tabela1[[#This Row],[STRIDE LM]]="Elevation of Privilege",Formatação!H$7,IF(Tabela1[[#This Row],[STRIDE LM]]="Lateral Movement",Formatação!H$8,Errado)))))))} -> Autorização | E52: Elevation of Privilege | F52: {=IF(Tabela1[[#This Row],[STRIDE LM]]="Information Disclosure",Formatação!J$5,IF(Tabela1[[#This Row],[STRIDE LM]]="Repudiation",Formatação!J$4,IF(Tabela1[[#This Row],[STRIDE LM]]="Spoofing",Formatação!J$2,IF(Tabela1[[#This Row],[STRIDE LM]]="Tampering",Formatação!J$3, IF(Tabela1[[#This Row],[STRIDE LM]]="Denial of Service",Formatação!J$6,IF(Tabela1[[#This Row],[STRIDE LM]]="Elevation of Privilege",Formatação!J$7,IF(Tabela1[[#This Row],[STRIDE LM]]="Lateral Movement",Formatação!J$8,Errado)))))))} -> Danos financeiros/Vazamento de dados | G52: A01:2021-Broken Access Control | J52: Sim | K52: Sim | L52: Sim | M52: Sim
A53: Ambientes de Desenvolvimento, Homologação e Teste precisam estar segregados do ambiente de produção | C53: Infraestrutura | D53: {=IF(Tabela1[[#This Row],[STRIDE LM]]="Information Disclosure",Formatação!H$5,IF(Tabela1[[#This Row],[STRIDE LM]]="Repudiation",Formatação!H$4,IF(Tabela1[[#This Row],[STRIDE LM]]="Spoofing",Formatação!H$2,IF(Tabela1[[#This Row],[STRIDE LM]]="Tampering",Formatação!H$3, IF(Tabela1[[#This Row],[STRIDE LM]]="Denial of Service",Formatação!H$6,IF(Tabela1[[#This Row],[STRIDE LM]]="Elevation of Privilege",Formatação!H$7,IF(Tabela1[[#This Row],[STRIDE LM]]="Lateral Movement",Formatação!H$8,Errado)))))))} -> Confidencialidade | E53: Information Disclosure | F53: {=IF(Tabela1[[#This Row],[STRIDE LM]]="Information Disclosure",Formatação!J$5,IF(Tabela1[[#This Row],[STRIDE LM]]="Repudiation",Formatação!J$4,IF(Tabela1[[#This Row],[STRIDE LM]]="Spoofing",Formatação!J$2,IF(Tabela1[[#This Row],[STRIDE LM]]="Tampering",Formatação!J$3, IF(Tabela1[[#This Row],[STRIDE LM]]="Denial of Service",Formatação!J$6,IF(Tabela1[[#This Row],[STRIDE LM]]="Elevation of Privilege",Formatação!J$7,IF(Tabela1[[#This Row],[STRIDE LM]]="Lateral Movement",Formatação!J$8,Errado)))))))} -> Vazamento de dados | G53: A01:2021-Broken Access Control | J53: Sim | K53: Sim | L53: Sim | M53: Sim
A54: Apenas ambientes de produção devem conter dados reais. Ambientes de desenvolvimento, testes, homologação e outros devem possuir dados fictícios | C54: Infraestrutura | D54: {=IF(Tabela1[[#This Row],[STRIDE LM]]="Information Disclosure",Formatação!H$5,IF(Tabela1[[#This Row],[STRIDE LM]]="Repudiation",Formatação!H$4,IF(Tabela1[[#This Row],[STRIDE LM]]="Spoofing",Formatação!H$2,IF(Tabela1[[#This Row],[STRIDE LM]]="Tampering",Formatação!H$3, IF(Tabela1[[#This Row],[STRIDE LM]]="Denial of Service",Formatação!H$6,IF(Tabela1[[#This Row],[STRIDE LM]]="Elevation of Privilege",Formatação!H$7,IF(Tabela1[[#This Row],[STRIDE LM]]="Lateral Movement",Formatação!H$8,Errado)))))))} -> Confidencialidade | E54: Information Disclosure | F54: {=IF(Tabela1[[#This Row],[STRIDE LM]]="Information Disclosure",Formatação!J$5,IF(Tabela1[[#This Row],[STRIDE LM]]="Repudiation",Formatação!J$4,IF(Tabela1[[#This Row],[STRIDE LM]]="Spoofing",Formatação!J$2,IF(Tabela1[[#This Row],[STRIDE LM]]="Tampering",Formatação!J$3, IF(Tabela1[[#This Row],[STRIDE LM]]="Denial of Service",Formatação!J$6,IF(Tabela1[[#This Row],[STRIDE LM]]="Elevation of Privilege",Formatação!J$7,IF(Tabela1[[#This Row],[STRIDE LM]]="Lateral Movement",Formatação!J$8,Errado)))))))} -> Vazamento de dados | G54: A09:2021-Security Logging and Monitoring Failures | J54: Sim | K54: Sim | L54: Sim | M54: Sim
A55: É necessário garantir que os projetos estejam com os SO adequados (não é permitido a subida de SO obsoleto) | C55: Infraestrutura | D55: {=IF(Tabela1[[#This Row],[STRIDE LM]]="Information Disclosure",Formatação!H$5,IF(Tabela1[[#This Row],[STRIDE LM]]="Repudiation",Formatação!H$4,IF(Tabela1[[#This Row],[STRIDE LM]]="Spoofing",Formatação!H$2,IF(Tabela1[[#This Row],[STRIDE LM]]="Tampering",Formatação!H$3, IF(Tabela1[[#This Row],[STRIDE LM]]="Denial of Service",Formatação!H$6,IF(Tabela1[[#This Row],[STRIDE LM]]="Elevation of Privilege",Formatação!H$7,IF(Tabela1[[#This Row],[STRIDE LM]]="Lateral Movement",Formatação!H$8,Errado)))))))} -> Integridade | E55: Tampering | F55: {=IF(Tabela1[[#This Row],[STRIDE LM]]="Information Disclosure",Formatação!J$5,IF(Tabela1[[#This Row],[STRIDE LM]]="Repudiation",Formatação!J$4,IF(Tabela1[[#This Row],[STRIDE LM]]="Spoofing",Formatação!J$2,IF(Tabela1[[#This Row],[STRIDE LM]]="Tampering",Formatação!J$3, IF(Tabela1[[#This Row],[STRIDE LM]]="Denial of Service",Formatação!J$6,IF(Tabela1[[#This Row],[STRIDE LM]]="Elevation of Privilege",Formatação!J$7,IF(Tabela1[[#This Row],[STRIDE LM]]="Lateral Movement",Formatação!J$8,Errado)))))))} -> Danos a imagem | G55: A06:2021-Vulnerable and Outdated Components | J55: Sim | K55: Sim | L55: Sim | M55: Sim
A56: O sistema/aplicação/ ativo precisa estar integrado ao nosso CMDB, garantindo a centralização dos ativos no inventário oficial | C56: Infraestrutura | D56: {=IF(Tabela1[[#This Row],[STRIDE LM]]="Information Disclosure",Formatação!H$5,IF(Tabela1[[#This Row],[STRIDE LM]]="Repudiation",Formatação!H$4,IF(Tabela1[[#This Row],[STRIDE LM]]="Spoofing",Formatação!H$2,IF(Tabela1[[#This Row],[STRIDE LM]]="Tampering",Formatação!H$3, IF(Tabela1[[#This Row],[STRIDE LM]]="Denial of Service",Formatação!H$6,IF(Tabela1[[#This Row],[STRIDE LM]]="Elevation of Privilege",Formatação!H$7,IF(Tabela1[[#This Row],[STRIDE LM]]="Lateral Movement",Formatação!H$8,Errado)))))))} -> Não repúdio | E56: Repudiation | F56: {=IF(Tabela1[[#This Row],[STRIDE LM]]="Information Disclosure",Formatação!J$5,IF(Tabela1[[#This Row],[STRIDE LM]]="Repudiation",Formatação!J$4,IF(Tabela1[[#This Row],[STRIDE LM]]="Spoofing",Formatação!J$2,IF(Tabela1[[#This Row],[STRIDE LM]]="Tampering",Formatação!J$3, IF(Tabela1[[#This Row],[STRIDE LM]]="Denial of Service",Formatação!J$6,IF(Tabela1[[#This Row],[STRIDE LM]]="Elevation of Privilege",Formatação!J$7,IF(Tabela1[[#This Row],[STRIDE LM]]="Lateral Movement",Formatação!J$8,Errado)))))))} -> Regulatório/Compliance | G56: A09:2021-Security Logging and Monitoring Failures | J56: Sim | K56: Sim | L56: Sim | M56: Sim
A57: Aplicação deve ter implementado controles de microssegmentação, garantindo acesso somente entre contextos de serviços e operações da aplicação específica | C57: Infraestrutura | D57: {=IF(Tabela1[[#This Row],[STRIDE LM]]="Information Disclosure",Formatação!H$5,IF(Tabela1[[#This Row],[STRIDE LM]]="Repudiation",Formatação!H$4,IF(Tabela1[[#This Row],[STRIDE LM]]="Spoofing",Formatação!H$2,IF(Tabela1[[#This Row],[STRIDE LM]]="Tampering",Formatação!H$3, IF(Tabela1[[#This Row],[STRIDE LM]]="Denial of Service",Formatação!H$6,IF(Tabela1[[#This Row],[STRIDE LM]]="Elevation of Privilege",Formatação!H$7,IF(Tabela1[[#This Row],[STRIDE LM]]="Lateral Movement",Formatação!H$8,Errado)))))))} -> Integridade | E57: Tampering | F57: {=IF(Tabela1[[#This Row],[STRIDE LM]]="Information Disclosure",Formatação!J$5,IF(Tabela1[[#This Row],[STRIDE LM]]="Repudiation",Formatação!J$4,IF(Tabela1[[#This Row],[STRIDE LM]]="Spoofing",Formatação!J$2,IF(Tabela1[[#This Row],[STRIDE LM]]="Tampering",Formatação!J$3, IF(Tabela1[[#This Row],[STRIDE LM]]="Denial of Service",Formatação!J$6,IF(Tabela1[[#This Row],[STRIDE LM]]="Elevation of Privilege",Formatação!J$7,IF(Tabela1[[#This Row],[STRIDE LM]]="Lateral Movement",Formatação!J$8,Errado)))))))} -> Danos a imagem | G57: A01:2021-Broken Access Control | J57: Sim | K57: Sim | L57: Sim | M57: Sim
A58: O ambiente precisa possuir plano de contingência ou recursos que garantam a disponibilidade em casos de falhas ou desastres | C58: Infraestrutura | D58: {=IF(Tabela1[[#This Row],[STRIDE LM]]="Information Disclosure",Formatação!H$5,IF(Tabela1[[#This Row],[STRIDE LM]]="Repudiation",Formatação!H$4,IF(Tabela1[[#This Row],[STRIDE LM]]="Spoofing",Formatação!H$2,IF(Tabela1[[#This Row],[STRIDE LM]]="Tampering",Formatação!H$3, IF(Tabela1[[#This Row],[STRIDE LM]]="Denial of Service",Formatação!H$6,IF(Tabela1[[#This Row],[STRIDE LM]]="Elevation of Privilege",Formatação!H$7,IF(Tabela1[[#This Row],[STRIDE LM]]="Lateral Movement",Formatação!H$8,Errado)))))))} -> Disponibilidade | E58: Denial of Service | F58: {=IF(Tabela1[[#This Row],[STRIDE LM]]="Information Disclosure",Formatação!J$5,IF(Tabela1[[#This Row],[STRIDE LM]]="Repudiation",Formatação!J$4,IF(Tabela1[[#This Row],[STRIDE LM]]="Spoofing",Formatação!J$2,IF(Tabela1[[#This Row],[STRIDE LM]]="Tampering",Formatação!J$3, IF(Tabela1[[#This Row],[STRIDE LM]]="Denial of Service",Formatação!J$6,IF(Tabela1[[#This Row],[STRIDE LM]]="Elevation of Privilege",Formatação!J$7,IF(Tabela1[[#This Row],[STRIDE LM]]="Lateral Movement",Formatação!J$8,Errado)))))))} -> Indisponibilidade | G58: A05:2021-Security Misconfiguration | J58: Sim | K58: Sim | L58: Sim | M58: Sim
A59: Todos os servidores devem possuir imagem de SO e BD padrão da Companhia (com EDR, Antivírus, agente do SIEM e agente de Scan de Infra) | C59: Infraestrutura | D59: {=IF(Tabela1[[#This Row],[STRIDE LM]]="Information Disclosure",Formatação!H$5,IF(Tabela1[[#This Row],[STRIDE LM]]="Repudiation",Formatação!H$4,IF(Tabela1[[#This Row],[STRIDE LM]]="Spoofing",Formatação!H$2,IF(Tabela1[[#This Row],[STRIDE LM]]="Tampering",Formatação!H$3, IF(Tabela1[[#This Row],[STRIDE LM]]="Denial of Service",Formatação!H$6,IF(Tabela1[[#This Row],[STRIDE LM]]="Elevation of Privilege",Formatação!H$7,IF(Tabela1[[#This Row],[STRIDE LM]]="Lateral Movement",Formatação!H$8,Errado)))))))} -> Integridade | E59: Tampering | F59: {=IF(Tabela1[[#This Row],[STRIDE LM]]="Information Disclosure",Formatação!J$5,IF(Tabela1[[#This Row],[STRIDE LM]]="Repudiation",Formatação!J$4,IF(Tabela1[[#This Row],[STRIDE LM]]="Spoofing",Formatação!J$2,IF(Tabela1[[#This Row],[STRIDE LM]]="Tampering",Formatação!J$3, IF(Tabela1[[#This Row],[STRIDE LM]]="Denial of Service",Formatação!J$6,IF(Tabela1[[#This Row],[STRIDE LM]]="Elevation of Privilege",Formatação!J$7,IF(Tabela1[[#This Row],[STRIDE LM]]="Lateral Movement",Formatação!J$8,Errado)))))))} -> Danos a imagem | G59: A06:2021-Vulnerable and Outdated Components | J59: Sim | K59: Sim | L59: Sim | M59: Não
A60: A aplicação precisa utilizar certificados digitais emitidos por autoridades confiáveis (definidas pela Companhia) para validar a identidade das partes envolvidas em uma comunicação, fortalecendo a não repúdio. | C60: Infraestrutura | D60: {=IF(Tabela1[[#This Row],[STRIDE LM]]="Information Disclosure",Formatação!H$5,IF(Tabela1[[#This Row],[STRIDE LM]]="Repudiation",Formatação!H$4,IF(Tabela1[[#This Row],[STRIDE LM]]="Spoofing",Formatação!H$2,IF(Tabela1[[#This Row],[STRIDE LM]]="Tampering",Formatação!H$3, IF(Tabela1[[#This Row],[STRIDE LM]]="Denial of Service",Formatação!H$6,IF(Tabela1[[#This Row],[STRIDE LM]]="Elevation of Privilege",Formatação!H$7,IF(Tabela1[[#This Row],[STRIDE LM]]="Lateral Movement",Formatação!H$8,Errado)))))))} -> Autenticação | E60: Spoofing | F60: {=IF(Tabela1[[#This Row],[STRIDE LM]]="Information Disclosure",Formatação!J$5,IF(Tabela1[[#This Row],[STRIDE LM]]="Repudiation",Formatação!J$4,IF(Tabela1[[#This Row],[STRIDE LM]]="Spoofing",Formatação!J$2,IF(Tabela1[[#This Row],[STRIDE LM]]="Tampering",Formatação!J$3, IF(Tabela1[[#This Row],[STRIDE LM]]="Denial of Service",Formatação!J$6,IF(Tabela1[[#This Row],[STRIDE LM]]="Elevation of Privilege",Formatação!J$7,IF(Tabela1[[#This Row],[STRIDE LM]]="Lateral Movement",Formatação!J$8,Errado)))))))} -> Fraudes/Vazamento de dados | J60: Sim | K60: Sim | L60: Sim | M60: Sim
A61: É necessário garantir que os certificados SSL/TLS estejam atualizados, utilizando algoritmos robustos e renovando certificados antes do vencimento para manter a segurança da comunicação. | C61: Infraestrutura | D61: {=IF(Tabela1[[#This Row],[STRIDE LM]]="Information Disclosure",Formatação!H$5,IF(Tabela1[[#This Row],[STRIDE LM]]="Repudiation",Formatação!H$4,IF(Tabela1[[#This Row],[STRIDE LM]]="Spoofing",Formatação!H$2,IF(Tabela1[[#This Row],[STRIDE LM]]="Tampering",Formatação!H$3, IF(Tabela1[[#This Row],[STRIDE LM]]="Denial of Service",Formatação!H$6,IF(Tabela1[[#This Row],[STRIDE LM]]="Elevation of Privilege",Formatação!H$7,IF(Tabela1[[#This Row],[STRIDE LM]]="Lateral Movement",Formatação!H$8,Errado)))))))} -> Autenticação | E61: Spoofing | F61: {=IF(Tabela1[[#This Row],[STRIDE LM]]="Information Disclosure",Formatação!J$5,IF(Tabela1[[#This Row],[STRIDE LM]]="Repudiation",Formatação!J$4,IF(Tabela1[[#This Row],[STRIDE LM]]="Spoofing",Formatação!J$2,IF(Tabela1[[#This Row],[STRIDE LM]]="Tampering",Formatação!J$3, IF(Tabela1[[#This Row],[STRIDE LM]]="Denial of Service",Formatação!J$6,IF(Tabela1[[#This Row],[STRIDE LM]]="Elevation of Privilege",Formatação!J$7,IF(Tabela1[[#This Row],[STRIDE LM]]="Lateral Movement",Formatação!J$8,Errado)))))))} -> Fraudes/Vazamento de dados | G61: A02:2021-Cryptographic Failures | J61: Sim | K61: Sim | L61: Sim | M61: Sim
A62: Caso o projeto utilize contêineres, é necessário garantir que eles sejam configurados de forma segura, seguindo as práticas recomendadas de hardening de Segurança | C62: Infraestrutura | D62: {=IF(Tabela1[[#This Row],[STRIDE LM]]="Information Disclosure",Formatação!H$5,IF(Tabela1[[#This Row],[STRIDE LM]]="Repudiation",Formatação!H$4,IF(Tabela1[[#This Row],[STRIDE LM]]="Spoofing",Formatação!H$2,IF(Tabela1[[#This Row],[STRIDE LM]]="Tampering",Formatação!H$3, IF(Tabela1[[#This Row],[STRIDE LM]]="Denial of Service",Formatação!H$6,IF(Tabela1[[#This Row],[STRIDE LM]]="Elevation of Privilege",Formatação!H$7,IF(Tabela1[[#This Row],[STRIDE LM]]="Lateral Movement",Formatação!H$8,Errado)))))))} -> Integridade | E62: Tampering | F62: {=IF(Tabela1[[#This Row],[STRIDE LM]]="Information Disclosure",Formatação!J$5,IF(Tabela1[[#This Row],[STRIDE LM]]="Repudiation",Formatação!J$4,IF(Tabela1[[#This Row],[STRIDE LM]]="Spoofing",Formatação!J$2,IF(Tabela1[[#This Row],[STRIDE LM]]="Tampering",Formatação!J$3, IF(Tabela1[[#This Row],[STRIDE LM]]="Denial of Service",Formatação!J$6,IF(Tabela1[[#This Row],[STRIDE LM]]="Elevation of Privilege",Formatação!J$7,IF(Tabela1[[#This Row],[STRIDE LM]]="Lateral Movement",Formatação!J$8,Errado)))))))} -> Danos a imagem | G62: A05:2021-Security Misconfiguration | J62: Sim | K62: Sim | L62: Sim | M62: Sim
A63: As informações de Data e Hora, obrigatoriamente precisam estar no modelo UTC (Coordinated Universal Time) | B63: O uso do formato UTC padroniza os registros de eventos, evitando inconsistências de fusos horários que podem dificultar investigações e auditorias. Sem essa padronização, corre-se o risco de falhas na correlação de eventos e dificuldades na detecção de incidentes. | C63: Rastreabilidade | D63: {=IF(Tabela1[[#This Row],[STRIDE LM]]="Information Disclosure",Formatação!H$5,IF(Tabela1[[#This Row],[STRIDE LM]]="Repudiation",Formatação!H$4,IF(Tabela1[[#This Row],[STRIDE LM]]="Spoofing",Formatação!H$2,IF(Tabela1[[#This Row],[STRIDE LM]]="Tampering",Formatação!H$3, IF(Tabela1[[#This Row],[STRIDE LM]]="Denial of Service",Formatação!H$6,IF(Tabela1[[#This Row],[STRIDE LM]]="Elevation of Privilege",Formatação!H$7,IF(Tabela1[[#This Row],[STRIDE LM]]="Lateral Movement",Formatação!H$8,Errado)))))))} -> Não repúdio | E63: Repudiation | F63: {=IF(Tabela1[[#This Row],[STRIDE LM]]="Information Disclosure",Formatação!J$5,IF(Tabela1[[#This Row],[STRIDE LM]]="Repudiation",Formatação!J$4,IF(Tabela1[[#This Row],[STRIDE LM]]="Spoofing",Formatação!J$2,IF(Tabela1[[#This Row],[STRIDE LM]]="Tampering",Formatação!J$3, IF(Tabela1[[#This Row],[STRIDE LM]]="Denial of Service",Formatação!J$6,IF(Tabela1[[#This Row],[STRIDE LM]]="Elevation of Privilege",Formatação!J$7,IF(Tabela1[[#This Row],[STRIDE LM]]="Lateral Movement",Formatação!J$8,Errado)))))))} -> Regulatório/Compliance | G63: A09:2021-Security Logging and Monitoring Failures | H63: Processamento | I63: Threat Detection & Response | J63: Sim | K63: Sim | L63: Sim | M63: Sim
A64: Todo e qualquer custo de ingestão/armazenamento de logs é de responsabilidade do owner do projeto. | B64: Os custos associados ao armazenamento e processamento de logs precisam ser previstos no orçamento do projeto. Se não forem considerados, pode haver restrições de retenção ou cortes que impactam a visibilidade de segurança. | C64: Rastreabilidade | D64: {=IF(Tabela1[[#This Row],[STRIDE LM]]="Information Disclosure",Formatação!H$5,IF(Tabela1[[#This Row],[STRIDE LM]]="Repudiation",Formatação!H$4,IF(Tabela1[[#This Row],[STRIDE LM]]="Spoofing",Formatação!H$2,IF(Tabela1[[#This Row],[STRIDE LM]]="Tampering",Formatação!H$3, IF(Tabela1[[#This Row],[STRIDE LM]]="Denial of Service",Formatação!H$6,IF(Tabela1[[#This Row],[STRIDE LM]]="Elevation of Privilege",Formatação!H$7,IF(Tabela1[[#This Row],[STRIDE LM]]="Lateral Movement",Formatação!H$8,Errado)))))))} -> Não repúdio | E64: Repudiation | F64: {=IF(Tabela1[[#This Row],[STRIDE LM]]="Information Disclosure",Formatação!J$5,IF(Tabela1[[#This Row],[STRIDE LM]]="Repudiation",Formatação!J$4,IF(Tabela1[[#This Row],[STRIDE LM]]="Spoofing",Formatação!J$2,IF(Tabela1[[#This Row],[STRIDE LM]]="Tampering",Formatação!J$3, IF(Tabela1[[#This Row],[STRIDE LM]]="Denial of Service",Formatação!J$6,IF(Tabela1[[#This Row],[STRIDE LM]]="Elevation of Privilege",Formatação!J$7,IF(Tabela1[[#This Row],[STRIDE LM]]="Lateral Movement",Formatação!J$8,Errado)))))))} -> Regulatório/Compliance | G64: A09:2021-Security Logging and Monitoring Failures | H64: Processamento | I64: Threat Detection & Response | J64: Sim | K64: Sim | L64: Sim | M64: Sim
A65: É obrigatório que os logs de aplicações SoX não passem por nenhum tratamento/modificação antes de chegarem ao SIEM | B65: Para garantir conformidade com regulamentos como SOX, os logs devem ser armazenados em seu formato original, garantindo integridade e evitando adulterações. Modificações podem comprometer a confiabilidade das trilhas de auditoria. | C65: Rastreabilidade | D65: {=IF(Tabela1[[#This Row],[STRIDE LM]]="Information Disclosure",Formatação!H$5,IF(Tabela1[[#This Row],[STRIDE LM]]="Repudiation",Formatação!H$4,IF(Tabela1[[#This Row],[STRIDE LM]]="Spoofing",Formatação!H$2,IF(Tabela1[[#This Row],[STRIDE LM]]="Tampering",Formatação!H$3, IF(Tabela1[[#This Row],[STRIDE LM]]="Denial of Service",Formatação!H$6,IF(Tabela1[[#This Row],[STRIDE LM]]="Elevation of Privilege",Formatação!H$7,IF(Tabela1[[#This Row],[STRIDE LM]]="Lateral Movement",Formatação!H$8,Errado)))))))} -> Não repúdio | E65: Repudiation | F65: {=IF(Tabela1[[#This Row],[STRIDE LM]]="Information Disclosure",Formatação!J$5,IF(Tabela1[[#This Row],[STRIDE LM]]="Repudiation",Formatação!J$4,IF(Tabela1[[#This Row],[STRIDE LM]]="Spoofing",Formatação!J$2,IF(Tabela1[[#This Row],[STRIDE LM]]="Tampering",Formatação!J$3, IF(Tabela1[[#This Row],[STRIDE LM]]="Denial of Service",Formatação!J$6,IF(Tabela1[[#This Row],[STRIDE LM]]="Elevation of Privilege",Formatação!J$7,IF(Tabela1[[#This Row],[STRIDE LM]]="Lateral Movement",Formatação!J$8,Errado)))))))} -> Regulatório/Compliance | G65: A09:2021-Security Logging and Monitoring Failures | H65: Processamento | I65: Threat Detection & Response | J65: Sim | K65: Sim | L65: Sim | M65: Sim
A66: Logs com dados sensíveis gerados por aplicações devem ser mascaramento pela aplicação. Coleta de logs em outros recursos, é necessário que haja o mascaramento de dados sensíveis. | B66: O mascaramento impede a exposição de dados confidenciais, protegendo informações de clientes e credenciais de acesso. Sem essa proteção, logs podem se tornar um vetor de vazamento de dados. | C66: Rastreabilidade | D66: {=IF(Tabela1[[#This Row],[STRIDE LM]]="Information Disclosure",Formatação!H$5,IF(Tabela1[[#This Row],[STRIDE LM]]="Repudiation",Formatação!H$4,IF(Tabela1[[#This Row],[STRIDE LM]]="Spoofing",Formatação!H$2,IF(Tabela1[[#This Row],[STRIDE LM]]="Tampering",Formatação!H$3, IF(Tabela1[[#This Row],[STRIDE LM]]="Denial of Service",Formatação!H$6,IF(Tabela1[[#This Row],[STRIDE LM]]="Elevation of Privilege",Formatação!H$7,IF(Tabela1[[#This Row],[STRIDE LM]]="Lateral Movement",Formatação!H$8,Errado)))))))} -> Não repúdio | E66: Repudiation | F66: {=IF(Tabela1[[#This Row],[STRIDE LM]]="Information Disclosure",Formatação!J$5,IF(Tabela1[[#This Row],[STRIDE LM]]="Repudiation",Formatação!J$4,IF(Tabela1[[#This Row],[STRIDE LM]]="Spoofing",Formatação!J$2,IF(Tabela1[[#This Row],[STRIDE LM]]="Tampering",Formatação!J$3, IF(Tabela1[[#This Row],[STRIDE LM]]="Denial of Service",Formatação!J$6,IF(Tabela1[[#This Row],[STRIDE LM]]="Elevation of Privilege",Formatação!J$7,IF(Tabela1[[#This Row],[STRIDE LM]]="Lateral Movement",Formatação!J$8,Errado)))))))} -> Regulatório/Compliance | G66: A02:2021-Cryptographic Failures | H66: Processamento | I66: Threat Detection & Response | J66: Sim | K66: Sim | L66: Sim | M66: Sim | N66: TLS 1.3
A67: A aplicação, seja desenvolvida internamente, seja um serviço (como GTW, por exemplo) ou considerada software de prateleira, deve ser capaz de fazer a ingestão adequada dos logs de Segurança e de SoX. | B67: Garantir que todos os sistemas e serviços gerem logs estruturados e consumíveis por ferramentas de monitoramento de segurança. Sem isso, a rastreabilidade e a capacidade de resposta a incidentes podem ser comprometidas. | C67: Rastreabilidade | D67: {=IF(Tabela1[[#This Row],[STRIDE LM]]="Information Disclosure",Formatação!H$5,IF(Tabela1[[#This Row],[STRIDE LM]]="Repudiation",Formatação!H$4,IF(Tabela1[[#This Row],[STRIDE LM]]="Spoofing",Formatação!H$2,IF(Tabela1[[#This Row],[STRIDE LM]]="Tampering",Formatação!H$3, IF(Tabela1[[#This Row],[STRIDE LM]]="Denial of Service",Formatação!H$6,IF(Tabela1[[#This Row],[STRIDE LM]]="Elevation of Privilege",Formatação!H$7,IF(Tabela1[[#This Row],[STRIDE LM]]="Lateral Movement",Formatação!H$8,Errado)))))))} -> Não repúdio | E67: Repudiation | F67: {=IF(Tabela1[[#This Row],[STRIDE LM]]="Information Disclosure",Formatação!J$5,IF(Tabela1[[#This Row],[STRIDE LM]]="Repudiation",Formatação!J$4,IF(Tabela1[[#This Row],[STRIDE LM]]="Spoofing",Formatação!J$2,IF(Tabela1[[#This Row],[STRIDE LM]]="Tampering",Formatação!J$3, IF(Tabela1[[#This Row],[STRIDE LM]]="Denial of Service",Formatação!J$6,IF(Tabela1[[#This Row],[STRIDE LM]]="Elevation of Privilege",Formatação!J$7,IF(Tabela1[[#This Row],[STRIDE LM]]="Lateral Movement",Formatação!J$8,Errado)))))))} -> Regulatório/Compliance | G67: A09:2021-Security Logging and Monitoring Failures | H67: Processamento | I67: Threat Detection & Response | J67: Sim | K67: Sim | L67: Sim | M67: Sim
A68: No caso de aplicações e infraestrutura de sistemas caracterizados como SoX, os logs precisam ser armazenados por 1 ano | B68: A retenção por 1 ano atende a requisitos regulatórios e possibilita auditorias e investigações forenses quando necessário. A não retenção adequada pode gerar penalizações e dificultar a análise de incidentes antigos. | C68: Rastreabilidade | D68: {=IF(Tabela1[[#This Row],[STRIDE LM]]="Information Disclosure",Formatação!H$5,IF(Tabela1[[#This Row],[STRIDE LM]]="Repudiation",Formatação!H$4,IF(Tabela1[[#This Row],[STRIDE LM]]="Spoofing",Formatação!H$2,IF(Tabela1[[#This Row],[STRIDE LM]]="Tampering",Formatação!H$3, IF(Tabela1[[#This Row],[STRIDE LM]]="Denial of Service",Formatação!H$6,IF(Tabela1[[#This Row],[STRIDE LM]]="Elevation of Privilege",Formatação!H$7,IF(Tabela1[[#This Row],[STRIDE LM]]="Lateral Movement",Formatação!H$8,Errado)))))))} -> Não repúdio | E68: Repudiation | F68: {=IF(Tabela1[[#This Row],[STRIDE LM]]="Information Disclosure",Formatação!J$5,IF(Tabela1[[#This Row],[STRIDE LM]]="Repudiation",Formatação!J$4,IF(Tabela1[[#This Row],[STRIDE LM]]="Spoofing",Formatação!J$2,IF(Tabela1[[#This Row],[STRIDE LM]]="Tampering",Formatação!J$3, IF(Tabela1[[#This Row],[STRIDE LM]]="Denial of Service",Formatação!J$6,IF(Tabela1[[#This Row],[STRIDE LM]]="Elevation of Privilege",Formatação!J$7,IF(Tabela1[[#This Row],[STRIDE LM]]="Lateral Movement",Formatação!J$8,Errado)))))))} -> Regulatório/Compliance | G68: A09:2021-Security Logging and Monitoring Failures | H68: Processamento | I68: Threat Detection & Response | J68: Sim | K68: Sim | L68: Sim | M68: Sim
A69: Os logs devem ser integrados com o SIEM via modelo json ou via API Rest (para esse cenário de coleta de logs o payload não deve estar criptografado para garantir que a ferramenta de SIEM consiga consumir os logs) | B69: A padronização do formato JSON ou API REST garante que os logs sejam facilmente processados pelo SIEM. O payload não criptografado nesse contexto evita falhas na ingestão e análise automatizada. | C69: Rastreabilidade | D69: {=IF(Tabela1[[#This Row],[STRIDE LM]]="Information Disclosure",Formatação!H$5,IF(Tabela1[[#This Row],[STRIDE LM]]="Repudiation",Formatação!H$4,IF(Tabela1[[#This Row],[STRIDE LM]]="Spoofing",Formatação!H$2,IF(Tabela1[[#This Row],[STRIDE LM]]="Tampering",Formatação!H$3, IF(Tabela1[[#This Row],[STRIDE LM]]="Denial of Service",Formatação!H$6,IF(Tabela1[[#This Row],[STRIDE LM]]="Elevation of Privilege",Formatação!H$7,IF(Tabela1[[#This Row],[STRIDE LM]]="Lateral Movement",Formatação!H$8,Errado)))))))} -> Não repúdio | E69: Repudiation | F69: {=IF(Tabela1[[#This Row],[STRIDE LM]]="Information Disclosure",Formatação!J$5,IF(Tabela1[[#This Row],[STRIDE LM]]="Repudiation",Formatação!J$4,IF(Tabela1[[#This Row],[STRIDE LM]]="Spoofing",Formatação!J$2,IF(Tabela1[[#This Row],[STRIDE LM]]="Tampering",Formatação!J$3, IF(Tabela1[[#This Row],[STRIDE LM]]="Denial of Service",Formatação!J$6,IF(Tabela1[[#This Row],[STRIDE LM]]="Elevation of Privilege",Formatação!J$7,IF(Tabela1[[#This Row],[STRIDE LM]]="Lateral Movement",Formatação!J$8,Errado)))))))} -> Regulatório/Compliance | G69: A04:2021-Insecure Design | H69: Processamento | I69: Threat Detection & Response | J69: Sim | K69: Sim | L69: Sim | M69: Sim
A70: Os dados precisam ser criptografados durante o trânsito (TLS 1.3) | B70: A criptografia TLS 1.3 protege os dados contra interceptação durante a transmissão, prevenindo ataques de man-in-the-middle (MITM). A falta de criptografia pode expor logs sensíveis a ataques. | C70: Rastreabilidade | D70: {=IF(Tabela1[[#This Row],[STRIDE LM]]="Information Disclosure",Formatação!H$5,IF(Tabela1[[#This Row],[STRIDE LM]]="Repudiation",Formatação!H$4,IF(Tabela1[[#This Row],[STRIDE LM]]="Spoofing",Formatação!H$2,IF(Tabela1[[#This Row],[STRIDE LM]]="Tampering",Formatação!H$3, IF(Tabela1[[#This Row],[STRIDE LM]]="Denial of Service",Formatação!H$6,IF(Tabela1[[#This Row],[STRIDE LM]]="Elevation of Privilege",Formatação!H$7,IF(Tabela1[[#This Row],[STRIDE LM]]="Lateral Movement",Formatação!H$8,Errado)))))))} -> Confidencialidade | E70: Information Disclosure | F70: {=IF(Tabela1[[#This Row],[STRIDE LM]]="Information Disclosure",Formatação!J$5,IF(Tabela1[[#This Row],[STRIDE LM]]="Repudiation",Formatação!J$4,IF(Tabela1[[#This Row],[STRIDE LM]]="Spoofing",Formatação!J$2,IF(Tabela1[[#This Row],[STRIDE LM]]="Tampering",Formatação!J$3, IF(Tabela1[[#This Row],[STRIDE LM]]="Denial of Service",Formatação!J$6,IF(Tabela1[[#This Row],[STRIDE LM]]="Elevation of Privilege",Formatação!J$7,IF(Tabela1[[#This Row],[STRIDE LM]]="Lateral Movement",Formatação!J$8,Errado)))))))} -> Vazamento de dados | G70: A02:2021-Cryptographic Failures | H70: Processamento | I70: Data Security | J70: Sim | K70: Sim | L70: Sim | M70: Sim
A71: A solução para o consumo desses logs deve possuir controle de acesso adequado e ser gerenciado pelo time de gestão de identidades da Vivo | B71: O controle de acesso evita que usuários não autorizados acessem ou modifiquem logs. Sem essa proteção, logs podem ser manipulados ou acessados por atacantes. | C71: Rastreabilidade | D71: {=IF(Tabela1[[#This Row],[STRIDE LM]]="Information Disclosure",Formatação!H$5,IF(Tabela1[[#This Row],[STRIDE LM]]="Repudiation",Formatação!H$4,IF(Tabela1[[#This Row],[STRIDE LM]]="Spoofing",Formatação!H$2,IF(Tabela1[[#This Row],[STRIDE LM]]="Tampering",Formatação!H$3, IF(Tabela1[[#This Row],[STRIDE LM]]="Denial of Service",Formatação!H$6,IF(Tabela1[[#This Row],[STRIDE LM]]="Elevation of Privilege",Formatação!H$7,IF(Tabela1[[#This Row],[STRIDE LM]]="Lateral Movement",Formatação!H$8,Errado)))))))} -> Autorização | E71: Elevation of Privilege | F71: {=IF(Tabela1[[#This Row],[STRIDE LM]]="Information Disclosure",Formatação!J$5,IF(Tabela1[[#This Row],[STRIDE LM]]="Repudiation",Formatação!J$4,IF(Tabela1[[#This Row],[STRIDE LM]]="Spoofing",Formatação!J$2,IF(Tabela1[[#This Row],[STRIDE LM]]="Tampering",Formatação!J$3, IF(Tabela1[[#This Row],[STRIDE LM]]="Denial of Service",Formatação!J$6,IF(Tabela1[[#This Row],[STRIDE LM]]="Elevation of Privilege",Formatação!J$7,IF(Tabela1[[#This Row],[STRIDE LM]]="Lateral Movement",Formatação!J$8,Errado)))))))} -> Danos financeiros/Vazamento de dados | G71: A07:2021-Identification and Authentication Failures | H71: Processamento | I71: Threat Detection & Response | J71: Sim | K71: Sim | L71: Sim | M71: Sim
A72: Para sistemas SoX é preciso gerar trilhas dos eventos detalhados nesse link: clique aqui. | B72: A criação de trilhas detalhadas de eventos atende a requisitos regulatórios e facilita auditorias de conformidade. A ausência dessas trilhas pode levar a falhas na rastreabilidade de ações críticas. | C72: Rastreabilidade | D72: {=IF(Tabela1[[#This Row],[STRIDE LM]]="Information Disclosure",Formatação!H$5,IF(Tabela1[[#This Row],[STRIDE LM]]="Repudiation",Formatação!H$4,IF(Tabela1[[#This Row],[STRIDE LM]]="Spoofing",Formatação!H$2,IF(Tabela1[[#This Row],[STRIDE LM]]="Tampering",Formatação!H$3, IF(Tabela1[[#This Row],[STRIDE LM]]="Denial of Service",Formatação!H$6,IF(Tabela1[[#This Row],[STRIDE LM]]="Elevation of Privilege",Formatação!H$7,IF(Tabela1[[#This Row],[STRIDE LM]]="Lateral Movement",Formatação!H$8,Errado)))))))} -> Não repúdio | E72: Repudiation | F72: {=IF(Tabela1[[#This Row],[STRIDE LM]]="Information Disclosure",Formatação!J$5,IF(Tabela1[[#This Row],[STRIDE LM]]="Repudiation",Formatação!J$4,IF(Tabela1[[#This Row],[STRIDE LM]]="Spoofing",Formatação!J$2,IF(Tabela1[[#This Row],[STRIDE LM]]="Tampering",Formatação!J$3, IF(Tabela1[[#This Row],[STRIDE LM]]="Denial of Service",Formatação!J$6,IF(Tabela1[[#This Row],[STRIDE LM]]="Elevation of Privilege",Formatação!J$7,IF(Tabela1[[#This Row],[STRIDE LM]]="Lateral Movement",Formatação!J$8,Errado)))))))} -> Regulatório/Compliance | G72: A09:2021-Security Logging and Monitoring Failures | H72: Processamento | I72: Threat Detection & Response | J72: Sim | K72: Sim | L72: Sim | M72: Sim
A73: Todo e qualquer custo referente a log (ingestão; consumo) na nuvem precisa ser mensurado e considerado na etapa inicial do projeto durante a definição do orçamento. As trilhas de segurança fazem parte dos requisitos e os projetos precisam garantir que estejam habilitadas nos padrões definidos. | B73: Prever o custo de armazenamento e processamento de logs evita surpresas financeiras e garante que a retenção de logs esteja conforme os padrões de segurança. A falta de planejamento pode levar a cortes que prejudicam a visibilidade de segurança. | C73: Rastreabilidade | D73: {=IF(Tabela1[[#This Row],[STRIDE LM]]="Information Disclosure",Formatação!H$5,IF(Tabela1[[#This Row],[STRIDE LM]]="Repudiation",Formatação!H$4,IF(Tabela1[[#This Row],[STRIDE LM]]="Spoofing",Formatação!H$2,IF(Tabela1[[#This Row],[STRIDE LM]]="Tampering",Formatação!H$3, IF(Tabela1[[#This Row],[STRIDE LM]]="Denial of Service",Formatação!H$6,IF(Tabela1[[#This Row],[STRIDE LM]]="Elevation of Privilege",Formatação!H$7,IF(Tabela1[[#This Row],[STRIDE LM]]="Lateral Movement",Formatação!H$8,Errado)))))))} -> Não repúdio | E73: Repudiation | F73: {=IF(Tabela1[[#This Row],[STRIDE LM]]="Information Disclosure",Formatação!J$5,IF(Tabela1[[#This Row],[STRIDE LM]]="Repudiation",Formatação!J$4,IF(Tabela1[[#This Row],[STRIDE LM]]="Spoofing",Formatação!J$2,IF(Tabela1[[#This Row],[STRIDE LM]]="Tampering",Formatação!J$3, IF(Tabela1[[#This Row],[STRIDE LM]]="Denial of Service",Formatação!J$6,IF(Tabela1[[#This Row],[STRIDE LM]]="Elevation of Privilege",Formatação!J$7,IF(Tabela1[[#This Row],[STRIDE LM]]="Lateral Movement",Formatação!J$8,Errado)))))))} -> Regulatório/Compliance | G73: A09:2021-Security Logging and Monitoring Failures | H73: Processamento | I73: Cloud Security | J73: Sim | K73: Sim | L73: Sim | M73: Sim
A74: Para logs na nuvem trataremos de duas fontes de recursos que precisam ter suas trilhas de logs de cyber habilitadas: as aplicações e os recursos/serviços nativos da nuvem. Essas duas fontes precisam seguir todos os requisitos aqui apresentados. | B74: Tanto logs de aplicações quanto de infraestrutura precisam ser monitorados para detectar atividades suspeitas. A ausência de logging nesses ambientes pode deixar brechas para ataques sem rastreamento. | C74: Rastreabilidade | D74: {=IF(Tabela1[[#This Row],[STRIDE LM]]="Information Disclosure",Formatação!H$5,IF(Tabela1[[#This Row],[STRIDE LM]]="Repudiation",Formatação!H$4,IF(Tabela1[[#This Row],[STRIDE LM]]="Spoofing",Formatação!H$2,IF(Tabela1[[#This Row],[STRIDE LM]]="Tampering",Formatação!H$3, IF(Tabela1[[#This Row],[STRIDE LM]]="Denial of Service",Formatação!H$6,IF(Tabela1[[#This Row],[STRIDE LM]]="Elevation of Privilege",Formatação!H$7,IF(Tabela1[[#This Row],[STRIDE LM]]="Lateral Movement",Formatação!H$8,Errado)))))))} -> Não repúdio | E74: Repudiation | F74: {=IF(Tabela1[[#This Row],[STRIDE LM]]="Information Disclosure",Formatação!J$5,IF(Tabela1[[#This Row],[STRIDE LM]]="Repudiation",Formatação!J$4,IF(Tabela1[[#This Row],[STRIDE LM]]="Spoofing",Formatação!J$2,IF(Tabela1[[#This Row],[STRIDE LM]]="Tampering",Formatação!J$3, IF(Tabela1[[#This Row],[STRIDE LM]]="Denial of Service",Formatação!J$6,IF(Tabela1[[#This Row],[STRIDE LM]]="Elevation of Privilege",Formatação!J$7,IF(Tabela1[[#This Row],[STRIDE LM]]="Lateral Movement",Formatação!J$8,Errado)))))))} -> Regulatório/Compliance | G74: A09:2021-Security Logging and Monitoring Failures | H74: Processamento | I74: Cloud Security | J74: Sim | K74: Sim | L74: Sim | M74: Sim
A75: Garantir as devidas configurações nos recursos e serviços da cloud para que seja possível a geração dos logs (para cada provedor existe um controle específico que na maioria das vezes é baseado na instalação de um agente nesses recursos). Já na aplicação precisa estar garantido no próprio desenvolvimento. | B75: A configuração correta garante que logs sejam gerados e capturados corretamente. Sem essa configuração, eventos críticos podem não ser registrados, dificultando a resposta a incidentes e a auditoria. | C75: Rastreabilidade | D75: {=IF(Tabela1[[#This Row],[STRIDE LM]]="Information Disclosure",Formatação!H$5,IF(Tabela1[[#This Row],[STRIDE LM]]="Repudiation",Formatação!H$4,IF(Tabela1[[#This Row],[STRIDE LM]]="Spoofing",Formatação!H$2,IF(Tabela1[[#This Row],[STRIDE LM]]="Tampering",Formatação!H$3, IF(Tabela1[[#This Row],[STRIDE LM]]="Denial of Service",Formatação!H$6,IF(Tabela1[[#This Row],[STRIDE LM]]="Elevation of Privilege",Formatação!H$7,IF(Tabela1[[#This Row],[STRIDE LM]]="Lateral Movement",Formatação!H$8,Errado)))))))} -> Não repúdio | E75: Repudiation | F75: {=IF(Tabela1[[#This Row],[STRIDE LM]]="Information Disclosure",Formatação!J$5,IF(Tabela1[[#This Row],[STRIDE LM]]="Repudiation",Formatação!J$4,IF(Tabela1[[#This Row],[STRIDE LM]]="Spoofing",Formatação!J$2,IF(Tabela1[[#This Row],[STRIDE LM]]="Tampering",Formatação!J$3, IF(Tabela1[[#This Row],[STRIDE LM]]="Denial of Service",Formatação!J$6,IF(Tabela1[[#This Row],[STRIDE LM]]="Elevation of Privilege",Formatação!J$7,IF(Tabela1[[#This Row],[STRIDE LM]]="Lateral Movement",Formatação!J$8,Errado)))))))} -> Regulatório/Compliance | G75: A09:2021-Security Logging and Monitoring Failures | H75: Processamento | I75: Cloud Security | J75: Sim | K75: Sim | L75: Sim | M75: Sim
A76: Obrigatorio publicar serviços na arquitetura “Hub-Spoken”, estabelecidas durante cada Landingzone, com todas as proteções | C76: Cloud Security | D76: {=IF(Tabela1[[#This Row],[STRIDE LM]]="Information Disclosure",Formatação!H$5,IF(Tabela1[[#This Row],[STRIDE LM]]="Repudiation",Formatação!H$4,IF(Tabela1[[#This Row],[STRIDE LM]]="Spoofing",Formatação!H$2,IF(Tabela1[[#This Row],[STRIDE LM]]="Tampering",Formatação!H$3, IF(Tabela1[[#This Row],[STRIDE LM]]="Denial of Service",Formatação!H$6,IF(Tabela1[[#This Row],[STRIDE LM]]="Elevation of Privilege",Formatação!H$7,IF(Tabela1[[#This Row],[STRIDE LM]]="Lateral Movement",Formatação!H$8,Errado)))))))} -> Contenção | E76: Lateral Movement | F76: {=IF(Tabela1[[#This Row],[STRIDE LM]]="Information Disclosure",Formatação!J$5,IF(Tabela1[[#This Row],[STRIDE LM]]="Repudiation",Formatação!J$4,IF(Tabela1[[#This Row],[STRIDE LM]]="Spoofing",Formatação!J$2,IF(Tabela1[[#This Row],[STRIDE LM]]="Tampering",Formatação!J$3, IF(Tabela1[[#This Row],[STRIDE LM]]="Denial of Service",Formatação!J$6,IF(Tabela1[[#This Row],[STRIDE LM]]="Elevation of Privilege",Formatação!J$7,IF(Tabela1[[#This Row],[STRIDE LM]]="Lateral Movement",Formatação!J$8,Errado)))))))} -> Vazamento de dados | G76: A04:2021-Insecure Design | J76: Não | K76: Sim | L76: Sim | M76: Não | N76: Cloud Adoption Framework
A77: A arquitetura deve seguir o modelo de segregação por funcionalidades. (Apresentação, Lógica de negócio, Persistência/Dados) | C77: Cloud Security | D77: {=IF(Tabela1[[#This Row],[STRIDE LM]]="Information Disclosure",Formatação!H$5,IF(Tabela1[[#This Row],[STRIDE LM]]="Repudiation",Formatação!H$4,IF(Tabela1[[#This Row],[STRIDE LM]]="Spoofing",Formatação!H$2,IF(Tabela1[[#This Row],[STRIDE LM]]="Tampering",Formatação!H$3, IF(Tabela1[[#This Row],[STRIDE LM]]="Denial of Service",Formatação!H$6,IF(Tabela1[[#This Row],[STRIDE LM]]="Elevation of Privilege",Formatação!H$7,IF(Tabela1[[#This Row],[STRIDE LM]]="Lateral Movement",Formatação!H$8,Errado)))))))} -> Contenção | E77: Lateral Movement | F77: {=IF(Tabela1[[#This Row],[STRIDE LM]]="Information Disclosure",Formatação!J$5,IF(Tabela1[[#This Row],[STRIDE LM]]="Repudiation",Formatação!J$4,IF(Tabela1[[#This Row],[STRIDE LM]]="Spoofing",Formatação!J$2,IF(Tabela1[[#This Row],[STRIDE LM]]="Tampering",Formatação!J$3, IF(Tabela1[[#This Row],[STRIDE LM]]="Denial of Service",Formatação!J$6,IF(Tabela1[[#This Row],[STRIDE LM]]="Elevation of Privilege",Formatação!J$7,IF(Tabela1[[#This Row],[STRIDE LM]]="Lateral Movement",Formatação!J$8,Errado)))))))} -> Vazamento de dados | G77: A04:2021-Insecure Design | J77: Não | K77: Sim | L77: Sim | M77: Não | N77: Well-Architected Framework
A78: O control plane deve seguir modelos de segurança adaptativo | C78: Cloud Security | D78: {=IF(Tabela1[[#This Row],[STRIDE LM]]="Information Disclosure",Formatação!H$5,IF(Tabela1[[#This Row],[STRIDE LM]]="Repudiation",Formatação!H$4,IF(Tabela1[[#This Row],[STRIDE LM]]="Spoofing",Formatação!H$2,IF(Tabela1[[#This Row],[STRIDE LM]]="Tampering",Formatação!H$3, IF(Tabela1[[#This Row],[STRIDE LM]]="Denial of Service",Formatação!H$6,IF(Tabela1[[#This Row],[STRIDE LM]]="Elevation of Privilege",Formatação!H$7,IF(Tabela1[[#This Row],[STRIDE LM]]="Lateral Movement",Formatação!H$8,Errado)))))))} -> Autorização | E78: Elevation of Privilege | F78: {=IF(Tabela1[[#This Row],[STRIDE LM]]="Information Disclosure",Formatação!J$5,IF(Tabela1[[#This Row],[STRIDE LM]]="Repudiation",Formatação!J$4,IF(Tabela1[[#This Row],[STRIDE LM]]="Spoofing",Formatação!J$2,IF(Tabela1[[#This Row],[STRIDE LM]]="Tampering",Formatação!J$3, IF(Tabela1[[#This Row],[STRIDE LM]]="Denial of Service",Formatação!J$6,IF(Tabela1[[#This Row],[STRIDE LM]]="Elevation of Privilege",Formatação!J$7,IF(Tabela1[[#This Row],[STRIDE LM]]="Lateral Movement",Formatação!J$8,Errado)))))))} -> Danos financeiros/Vazamento de dados | G78: A01:2021-Broken Access Control | J78: Não | K78: Sim | L78: Sim | M78: Sim | N78: Cloud Adoption Framework
A79: Especificar política a nível de organização para NÃO PERMITIR que portas de serviços sejam expostas para internet. Ex: 22, 1433, 1521, 3306, 3389, 5432, 6379, 6380, 8000, 8080, 27017 e 21 | C79: Cloud Security | D79: {=IF(Tabela1[[#This Row],[STRIDE LM]]="Information Disclosure",Formatação!H$5,IF(Tabela1[[#This Row],[STRIDE LM]]="Repudiation",Formatação!H$4,IF(Tabela1[[#This Row],[STRIDE LM]]="Spoofing",Formatação!H$2,IF(Tabela1[[#This Row],[STRIDE LM]]="Tampering",Formatação!H$3, IF(Tabela1[[#This Row],[STRIDE LM]]="Denial of Service",Formatação!H$6,IF(Tabela1[[#This Row],[STRIDE LM]]="Elevation of Privilege",Formatação!H$7,IF(Tabela1[[#This Row],[STRIDE LM]]="Lateral Movement",Formatação!H$8,Errado)))))))} -> Integridade | E79: Tampering | F79: {=IF(Tabela1[[#This Row],[STRIDE LM]]="Information Disclosure",Formatação!J$5,IF(Tabela1[[#This Row],[STRIDE LM]]="Repudiation",Formatação!J$4,IF(Tabela1[[#This Row],[STRIDE LM]]="Spoofing",Formatação!J$2,IF(Tabela1[[#This Row],[STRIDE LM]]="Tampering",Formatação!J$3, IF(Tabela1[[#This Row],[STRIDE LM]]="Denial of Service",Formatação!J$6,IF(Tabela1[[#This Row],[STRIDE LM]]="Elevation of Privilege",Formatação!J$7,IF(Tabela1[[#This Row],[STRIDE LM]]="Lateral Movement",Formatação!J$8,Errado)))))))} -> Danos a imagem | G79: A05:2021-Security Misconfiguration | J79: Não | K79: Sim | L79: Sim | M79: Não | N79: Cis Benchmark
A80: Especificar política a nível de organização para NÃO PERMITIR exposição na internet de interfaces administrativas de recursos. | C80: Cloud Security | D80: {=IF(Tabela1[[#This Row],[STRIDE LM]]="Information Disclosure",Formatação!H$5,IF(Tabela1[[#This Row],[STRIDE LM]]="Repudiation",Formatação!H$4,IF(Tabela1[[#This Row],[STRIDE LM]]="Spoofing",Formatação!H$2,IF(Tabela1[[#This Row],[STRIDE LM]]="Tampering",Formatação!H$3, IF(Tabela1[[#This Row],[STRIDE LM]]="Denial of Service",Formatação!H$6,IF(Tabela1[[#This Row],[STRIDE LM]]="Elevation of Privilege",Formatação!H$7,IF(Tabela1[[#This Row],[STRIDE LM]]="Lateral Movement",Formatação!H$8,Errado)))))))} -> Integridade | E80: Tampering | F80: {=IF(Tabela1[[#This Row],[STRIDE LM]]="Information Disclosure",Formatação!J$5,IF(Tabela1[[#This Row],[STRIDE LM]]="Repudiation",Formatação!J$4,IF(Tabela1[[#This Row],[STRIDE LM]]="Spoofing",Formatação!J$2,IF(Tabela1[[#This Row],[STRIDE LM]]="Tampering",Formatação!J$3, IF(Tabela1[[#This Row],[STRIDE LM]]="Denial of Service",Formatação!J$6,IF(Tabela1[[#This Row],[STRIDE LM]]="Elevation of Privilege",Formatação!J$7,IF(Tabela1[[#This Row],[STRIDE LM]]="Lateral Movement",Formatação!J$8,Errado)))))))} -> Danos a imagem | G80: A05:2021-Security Misconfiguration | J80: Não | K80: Sim | L80: Sim | M80: Não | N80: Cis Benchmark
A81: Especificar política a nível de organização para NÃO PERMITIR provisionamento de endereços sem filtragem de origem; destino e serviço/porta | C81: Cloud Security | D81: {=IF(Tabela1[[#This Row],[STRIDE LM]]="Information Disclosure",Formatação!H$5,IF(Tabela1[[#This Row],[STRIDE LM]]="Repudiation",Formatação!H$4,IF(Tabela1[[#This Row],[STRIDE LM]]="Spoofing",Formatação!H$2,IF(Tabela1[[#This Row],[STRIDE LM]]="Tampering",Formatação!H$3, IF(Tabela1[[#This Row],[STRIDE LM]]="Denial of Service",Formatação!H$6,IF(Tabela1[[#This Row],[STRIDE LM]]="Elevation of Privilege",Formatação!H$7,IF(Tabela1[[#This Row],[STRIDE LM]]="Lateral Movement",Formatação!H$8,Errado)))))))} -> Integridade | E81: Tampering | F81: {=IF(Tabela1[[#This Row],[STRIDE LM]]="Information Disclosure",Formatação!J$5,IF(Tabela1[[#This Row],[STRIDE LM]]="Repudiation",Formatação!J$4,IF(Tabela1[[#This Row],[STRIDE LM]]="Spoofing",Formatação!J$2,IF(Tabela1[[#This Row],[STRIDE LM]]="Tampering",Formatação!J$3, IF(Tabela1[[#This Row],[STRIDE LM]]="Denial of Service",Formatação!J$6,IF(Tabela1[[#This Row],[STRIDE LM]]="Elevation of Privilege",Formatação!J$7,IF(Tabela1[[#This Row],[STRIDE LM]]="Lateral Movement",Formatação!J$8,Errado)))))))} -> Danos a imagem | G81: A02:2021-Cryptographic Failures | J81: Não | K81: Sim | L81: Sim | M81: Não | N81: Politicas de Segurança
A82: Todos os recursos provisionados deveram estar com sua trilha de logs cyber habilitados | C82: Cloud Security | D82: {=IF(Tabela1[[#This Row],[STRIDE LM]]="Information Disclosure",Formatação!H$5,IF(Tabela1[[#This Row],[STRIDE LM]]="Repudiation",Formatação!H$4,IF(Tabela1[[#This Row],[STRIDE LM]]="Spoofing",Formatação!H$2,IF(Tabela1[[#This Row],[STRIDE LM]]="Tampering",Formatação!H$3, IF(Tabela1[[#This Row],[STRIDE LM]]="Denial of Service",Formatação!H$6,IF(Tabela1[[#This Row],[STRIDE LM]]="Elevation of Privilege",Formatação!H$7,IF(Tabela1[[#This Row],[STRIDE LM]]="Lateral Movement",Formatação!H$8,Errado)))))))} -> Não repúdio | E82: Repudiation | F82: {=IF(Tabela1[[#This Row],[STRIDE LM]]="Information Disclosure",Formatação!J$5,IF(Tabela1[[#This Row],[STRIDE LM]]="Repudiation",Formatação!J$4,IF(Tabela1[[#This Row],[STRIDE LM]]="Spoofing",Formatação!J$2,IF(Tabela1[[#This Row],[STRIDE LM]]="Tampering",Formatação!J$3, IF(Tabela1[[#This Row],[STRIDE LM]]="Denial of Service",Formatação!J$6,IF(Tabela1[[#This Row],[STRIDE LM]]="Elevation of Privilege",Formatação!J$7,IF(Tabela1[[#This Row],[STRIDE LM]]="Lateral Movement",Formatação!J$8,Errado)))))))} -> Regulatório/Compliance | G82: A09:2021-Security Logging and Monitoring Failures | J82: Não | K82: Sim | L82: Sim | M82: Sim | N82: Log Analytics, Cloud Logging, Oracle Management Agent/Cloud Adoption Framework
A83: Recursos provisionados não podem ter interface exposta para a internet, o consumo deverá passar por camadas de proteção. | C83: Cloud Security | D83: {=IF(Tabela1[[#This Row],[STRIDE LM]]="Information Disclosure",Formatação!H$5,IF(Tabela1[[#This Row],[STRIDE LM]]="Repudiation",Formatação!H$4,IF(Tabela1[[#This Row],[STRIDE LM]]="Spoofing",Formatação!H$2,IF(Tabela1[[#This Row],[STRIDE LM]]="Tampering",Formatação!H$3, IF(Tabela1[[#This Row],[STRIDE LM]]="Denial of Service",Formatação!H$6,IF(Tabela1[[#This Row],[STRIDE LM]]="Elevation of Privilege",Formatação!H$7,IF(Tabela1[[#This Row],[STRIDE LM]]="Lateral Movement",Formatação!H$8,Errado)))))))} -> Confidencialidade | E83: Information Disclosure | F83: {=IF(Tabela1[[#This Row],[STRIDE LM]]="Information Disclosure",Formatação!J$5,IF(Tabela1[[#This Row],[STRIDE LM]]="Repudiation",Formatação!J$4,IF(Tabela1[[#This Row],[STRIDE LM]]="Spoofing",Formatação!J$2,IF(Tabela1[[#This Row],[STRIDE LM]]="Tampering",Formatação!J$3, IF(Tabela1[[#This Row],[STRIDE LM]]="Denial of Service",Formatação!J$6,IF(Tabela1[[#This Row],[STRIDE LM]]="Elevation of Privilege",Formatação!J$7,IF(Tabela1[[#This Row],[STRIDE LM]]="Lateral Movement",Formatação!J$8,Errado)))))))} -> Vazamento de dados | G83: A02:2021-Cryptographic Failures | J83: Não | K83: Sim | L83: Sim | M83: Sim | N83: Well-Architected Framework
A84: Em novas construções de Landing Zone considerar a implementação dos Guardrails (políticas de segurança da Companhia) a nível do novo Tenant | C84: Cloud Security | D84: {=IF(Tabela1[[#This Row],[STRIDE LM]]="Information Disclosure",Formatação!H$5,IF(Tabela1[[#This Row],[STRIDE LM]]="Repudiation",Formatação!H$4,IF(Tabela1[[#This Row],[STRIDE LM]]="Spoofing",Formatação!H$2,IF(Tabela1[[#This Row],[STRIDE LM]]="Tampering",Formatação!H$3, IF(Tabela1[[#This Row],[STRIDE LM]]="Denial of Service",Formatação!H$6,IF(Tabela1[[#This Row],[STRIDE LM]]="Elevation of Privilege",Formatação!H$7,IF(Tabela1[[#This Row],[STRIDE LM]]="Lateral Movement",Formatação!H$8,Errado)))))))} -> Integridade | E84: Tampering | F84: {=IF(Tabela1[[#This Row],[STRIDE LM]]="Information Disclosure",Formatação!J$5,IF(Tabela1[[#This Row],[STRIDE LM]]="Repudiation",Formatação!J$4,IF(Tabela1[[#This Row],[STRIDE LM]]="Spoofing",Formatação!J$2,IF(Tabela1[[#This Row],[STRIDE LM]]="Tampering",Formatação!J$3, IF(Tabela1[[#This Row],[STRIDE LM]]="Denial of Service",Formatação!J$6,IF(Tabela1[[#This Row],[STRIDE LM]]="Elevation of Privilege",Formatação!J$7,IF(Tabela1[[#This Row],[STRIDE LM]]="Lateral Movement",Formatação!J$8,Errado)))))))} -> Danos a imagem | G84: A04:2021-Insecure Design | J84: Não | K84: Sim | L84: Sim | M84: Não | N84: Cloud Adoption Framework
A85: Integrar o tenant a ferramenta corporativa de CNAPP (mandatório as funções de CSPM e CWPP) | C85: Cloud Security | D85: {=IF(Tabela1[[#This Row],[STRIDE LM]]="Information Disclosure",Formatação!H$5,IF(Tabela1[[#This Row],[STRIDE LM]]="Repudiation",Formatação!H$4,IF(Tabela1[[#This Row],[STRIDE LM]]="Spoofing",Formatação!H$2,IF(Tabela1[[#This Row],[STRIDE LM]]="Tampering",Formatação!H$3, IF(Tabela1[[#This Row],[STRIDE LM]]="Denial of Service",Formatação!H$6,IF(Tabela1[[#This Row],[STRIDE LM]]="Elevation of Privilege",Formatação!H$7,IF(Tabela1[[#This Row],[STRIDE LM]]="Lateral Movement",Formatação!H$8,Errado)))))))} -> Integridade | E85: Tampering | F85: {=IF(Tabela1[[#This Row],[STRIDE LM]]="Information Disclosure",Formatação!J$5,IF(Tabela1[[#This Row],[STRIDE LM]]="Repudiation",Formatação!J$4,IF(Tabela1[[#This Row],[STRIDE LM]]="Spoofing",Formatação!J$2,IF(Tabela1[[#This Row],[STRIDE LM]]="Tampering",Formatação!J$3, IF(Tabela1[[#This Row],[STRIDE LM]]="Denial of Service",Formatação!J$6,IF(Tabela1[[#This Row],[STRIDE LM]]="Elevation of Privilege",Formatação!J$7,IF(Tabela1[[#This Row],[STRIDE LM]]="Lateral Movement",Formatação!J$8,Errado)))))))} -> Danos a imagem | G85: A06:2021-Vulnerable and Outdated Components | J85: Não | K85: Sim | L85: Sim | M85: Não | N85: Requisitos de Cloud da Global
A86: Respeitar o processo de exceções estabelecido por governança | C86: Cloud Security | D86: {=IF(Tabela1[[#This Row],[STRIDE LM]]="Information Disclosure",Formatação!H$5,IF(Tabela1[[#This Row],[STRIDE LM]]="Repudiation",Formatação!H$4,IF(Tabela1[[#This Row],[STRIDE LM]]="Spoofing",Formatação!H$2,IF(Tabela1[[#This Row],[STRIDE LM]]="Tampering",Formatação!H$3, IF(Tabela1[[#This Row],[STRIDE LM]]="Denial of Service",Formatação!H$6,IF(Tabela1[[#This Row],[STRIDE LM]]="Elevation of Privilege",Formatação!H$7,IF(Tabela1[[#This Row],[STRIDE LM]]="Lateral Movement",Formatação!H$8,Errado)))))))} -> Confidencialidade | E86: Information Disclosure | F86: {=IF(Tabela1[[#This Row],[STRIDE LM]]="Information Disclosure",Formatação!J$5,IF(Tabela1[[#This Row],[STRIDE LM]]="Repudiation",Formatação!J$4,IF(Tabela1[[#This Row],[STRIDE LM]]="Spoofing",Formatação!J$2,IF(Tabela1[[#This Row],[STRIDE LM]]="Tampering",Formatação!J$3, IF(Tabela1[[#This Row],[STRIDE LM]]="Denial of Service",Formatação!J$6,IF(Tabela1[[#This Row],[STRIDE LM]]="Elevation of Privilege",Formatação!J$7,IF(Tabela1[[#This Row],[STRIDE LM]]="Lateral Movement",Formatação!J$8,Errado)))))))} -> Vazamento de dados | G86: N/A - Sem correlação | J86: Não | K86: Sim | L86: Sim | M86: Não | N86: Modelo de exceções na Cloud
A87: Segurança na comunicação | B87: Todas as comunicações entre APIs e clientes devem ser protegidas por TLS 1.3 ou superior. Comunicação entre ambientes distintos deve seguir regras de segurança, incluindo limitação de requisições, blocklist de IPs e inspeção de tráfego. | C87: API | D87: {=IF(Tabela1[[#This Row],[STRIDE LM]]="Information Disclosure",Formatação!H$5,IF(Tabela1[[#This Row],[STRIDE LM]]="Repudiation",Formatação!H$4,IF(Tabela1[[#This Row],[STRIDE LM]]="Spoofing",Formatação!H$2,IF(Tabela1[[#This Row],[STRIDE LM]]="Tampering",Formatação!H$3, IF(Tabela1[[#This Row],[STRIDE LM]]="Denial of Service",Formatação!H$6,IF(Tabela1[[#This Row],[STRIDE LM]]="Elevation of Privilege",Formatação!H$7,IF(Tabela1[[#This Row],[STRIDE LM]]="Lateral Movement",Formatação!H$8,Errado)))))))} -> Autenticação | E87: Spoofing | F87: {=IF(Tabela1[[#This Row],[STRIDE LM]]="Information Disclosure",Formatação!J$5,IF(Tabela1[[#This Row],[STRIDE LM]]="Repudiation",Formatação!J$4,IF(Tabela1[[#This Row],[STRIDE LM]]="Spoofing",Formatação!J$2,IF(Tabela1[[#This Row],[STRIDE LM]]="Tampering",Formatação!J$3, IF(Tabela1[[#This Row],[STRIDE LM]]="Denial of Service",Formatação!J$6,IF(Tabela1[[#This Row],[STRIDE LM]]="Elevation of Privilege",Formatação!J$7,IF(Tabela1[[#This Row],[STRIDE LM]]="Lateral Movement",Formatação!J$8,Errado)))))))} -> Fraudes/Vazamento de dados | G87: A01:2021-Broken Access Control | H87: Processamento | I87: Application Security | J87: Sim | K87: Sim | L87: Sim | M87: Sim
A88: Autenticação e autorização | B88: APIs devem implementar autenticação forte e autorização baseada em políticas como RBAC ou ABAC, garantindo revalidação contínua, princípio do privilégio mínimo e proteção contra sequestro de sessão. | C88: API | D88: {=IF(Tabela1[[#This Row],[STRIDE LM]]="Information Disclosure",Formatação!H$5,IF(Tabela1[[#This Row],[STRIDE LM]]="Repudiation",Formatação!H$4,IF(Tabela1[[#This Row],[STRIDE LM]]="Spoofing",Formatação!H$2,IF(Tabela1[[#This Row],[STRIDE LM]]="Tampering",Formatação!H$3, IF(Tabela1[[#This Row],[STRIDE LM]]="Denial of Service",Formatação!H$6,IF(Tabela1[[#This Row],[STRIDE LM]]="Elevation of Privilege",Formatação!H$7,IF(Tabela1[[#This Row],[STRIDE LM]]="Lateral Movement",Formatação!H$8,Errado)))))))} -> Autenticação | E88: Spoofing | F88: {=IF(Tabela1[[#This Row],[STRIDE LM]]="Information Disclosure",Formatação!J$5,IF(Tabela1[[#This Row],[STRIDE LM]]="Repudiation",Formatação!J$4,IF(Tabela1[[#This Row],[STRIDE LM]]="Spoofing",Formatação!J$2,IF(Tabela1[[#This Row],[STRIDE LM]]="Tampering",Formatação!J$3, IF(Tabela1[[#This Row],[STRIDE LM]]="Denial of Service",Formatação!J$6,IF(Tabela1[[#This Row],[STRIDE LM]]="Elevation of Privilege",Formatação!J$7,IF(Tabela1[[#This Row],[STRIDE LM]]="Lateral Movement",Formatação!J$8,Errado)))))))} -> Fraudes/Vazamento de dados
A89: Controle de sessão | B89: APIs que exigem autenticação devem adotar mecanismos seguros, incluindo expiração automática de tokens, proteção contra ataques de repetição (Replay Attacks) e prevenção de falsificação de sessão. | C89: API | D89: {=IF(Tabela1[[#This Row],[STRIDE LM]]="Information Disclosure",Formatação!H$5,IF(Tabela1[[#This Row],[STRIDE LM]]="Repudiation",Formatação!H$4,IF(Tabela1[[#This Row],[STRIDE LM]]="Spoofing",Formatação!H$2,IF(Tabela1[[#This Row],[STRIDE LM]]="Tampering",Formatação!H$3, IF(Tabela1[[#This Row],[STRIDE LM]]="Denial of Service",Formatação!H$6,IF(Tabela1[[#This Row],[STRIDE LM]]="Elevation of Privilege",Formatação!H$7,IF(Tabela1[[#This Row],[STRIDE LM]]="Lateral Movement",Formatação!H$8,Errado)))))))} -> Autenticação | E89: Spoofing | F89: {=IF(Tabela1[[#This Row],[STRIDE LM]]="Information Disclosure",Formatação!J$5,IF(Tabela1[[#This Row],[STRIDE LM]]="Repudiation",Formatação!J$4,IF(Tabela1[[#This Row],[STRIDE LM]]="Spoofing",Formatação!J$2,IF(Tabela1[[#This Row],[STRIDE LM]]="Tampering",Formatação!J$3, IF(Tabela1[[#This Row],[STRIDE LM]]="Denial of Service",Formatação!J$6,IF(Tabela1[[#This Row],[STRIDE LM]]="Elevation of Privilege",Formatação!J$7,IF(Tabela1[[#This Row],[STRIDE LM]]="Lateral Movement",Formatação!J$8,Errado)))))))} -> Fraudes/Vazamento de dados
A90: Validação de entrada | B90: APIs devem validar todas as entradas de usuários e sistemas para evitar ataques de injeção (SQL Injection, XSS, entre outros), garantindo integridade e segurança dos dados. | C90: API | D90: {=IF(Tabela1[[#This Row],[STRIDE LM]]="Information Disclosure",Formatação!H$5,IF(Tabela1[[#This Row],[STRIDE LM]]="Repudiation",Formatação!H$4,IF(Tabela1[[#This Row],[STRIDE LM]]="Spoofing",Formatação!H$2,IF(Tabela1[[#This Row],[STRIDE LM]]="Tampering",Formatação!H$3, IF(Tabela1[[#This Row],[STRIDE LM]]="Denial of Service",Formatação!H$6,IF(Tabela1[[#This Row],[STRIDE LM]]="Elevation of Privilege",Formatação!H$7,IF(Tabela1[[#This Row],[STRIDE LM]]="Lateral Movement",Formatação!H$8,Errado)))))))} -> Autenticação | E90: Spoofing | F90: {=IF(Tabela1[[#This Row],[STRIDE LM]]="Information Disclosure",Formatação!J$5,IF(Tabela1[[#This Row],[STRIDE LM]]="Repudiation",Formatação!J$4,IF(Tabela1[[#This Row],[STRIDE LM]]="Spoofing",Formatação!J$2,IF(Tabela1[[#This Row],[STRIDE LM]]="Tampering",Formatação!J$3, IF(Tabela1[[#This Row],[STRIDE LM]]="Denial of Service",Formatação!J$6,IF(Tabela1[[#This Row],[STRIDE LM]]="Elevation of Privilege",Formatação!J$7,IF(Tabela1[[#This Row],[STRIDE LM]]="Lateral Movement",Formatação!J$8,Errado)))))))} -> Fraudes/Vazamento de dados
A91: Governança e monitoramento | B91: APIs devem contar com mecanismos de governança para rastreabilidade de integrações, autenticação, áreas responsáveis e políticas de segurança aplicadas. | C91: API | D91: {=IF(Tabela1[[#This Row],[STRIDE LM]]="Information Disclosure",Formatação!H$5,IF(Tabela1[[#This Row],[STRIDE LM]]="Repudiation",Formatação!H$4,IF(Tabela1[[#This Row],[STRIDE LM]]="Spoofing",Formatação!H$2,IF(Tabela1[[#This Row],[STRIDE LM]]="Tampering",Formatação!H$3, IF(Tabela1[[#This Row],[STRIDE LM]]="Denial of Service",Formatação!H$6,IF(Tabela1[[#This Row],[STRIDE LM]]="Elevation of Privilege",Formatação!H$7,IF(Tabela1[[#This Row],[STRIDE LM]]="Lateral Movement",Formatação!H$8,Errado)))))))} -> Autenticação | E91: Spoofing | F91: {=IF(Tabela1[[#This Row],[STRIDE LM]]="Information Disclosure",Formatação!J$5,IF(Tabela1[[#This Row],[STRIDE LM]]="Repudiation",Formatação!J$4,IF(Tabela1[[#This Row],[STRIDE LM]]="Spoofing",Formatação!J$2,IF(Tabela1[[#This Row],[STRIDE LM]]="Tampering",Formatação!J$3, IF(Tabela1[[#This Row],[STRIDE LM]]="Denial of Service",Formatação!J$6,IF(Tabela1[[#This Row],[STRIDE LM]]="Elevation of Privilege",Formatação!J$7,IF(Tabela1[[#This Row],[STRIDE LM]]="Lateral Movement",Formatação!J$8,Errado)))))))} -> Fraudes/Vazamento de dados
A92: Tratamento de erros | B92: APIs devem implementar manuseio adequado de erros para evitar exposição de informações sensíveis em mensagens de resposta. | C92: API | D92: {=IF(Tabela1[[#This Row],[STRIDE LM]]="Information Disclosure",Formatação!H$5,IF(Tabela1[[#This Row],[STRIDE LM]]="Repudiation",Formatação!H$4,IF(Tabela1[[#This Row],[STRIDE LM]]="Spoofing",Formatação!H$2,IF(Tabela1[[#This Row],[STRIDE LM]]="Tampering",Formatação!H$3, IF(Tabela1[[#This Row],[STRIDE LM]]="Denial of Service",Formatação!H$6,IF(Tabela1[[#This Row],[STRIDE LM]]="Elevation of Privilege",Formatação!H$7,IF(Tabela1[[#This Row],[STRIDE LM]]="Lateral Movement",Formatação!H$8,Errado)))))))} -> Autenticação | E92: Spoofing | F92: {=IF(Tabela1[[#This Row],[STRIDE LM]]="Information Disclosure",Formatação!J$5,IF(Tabela1[[#This Row],[STRIDE LM]]="Repudiation",Formatação!J$4,IF(Tabela1[[#This Row],[STRIDE LM]]="Spoofing",Formatação!J$2,IF(Tabela1[[#This Row],[STRIDE LM]]="Tampering",Formatação!J$3, IF(Tabela1[[#This Row],[STRIDE LM]]="Denial of Service",Formatação!J$6,IF(Tabela1[[#This Row],[STRIDE LM]]="Elevation of Privilege",Formatação!J$7,IF(Tabela1[[#This Row],[STRIDE LM]]="Lateral Movement",Formatação!J$8,Errado)))))))} -> Fraudes/Vazamento de dados
A94: Caso o sistema/aplicação possa ser acessado à partir da Internet, ele precisa estar segregado por uma DMZ
A95: Implementar a pinagem do Certificado Digital em soluções mobile (Evitar MITM)
A96: Ativação da criptografia de payload e handshake entre front-end e camada de exposição de APIs
A97: A aplicação deve implementar Controle de Sessão (timeout, sessão simultânea, etc)
A98: A aplicação de implementar validação de Sessão (Front e Back via Mutual TLS)
A99: Implementar mecanismos para controle de Abuso de recursos/limite de requisições
A100: Implementar mecanismos para bloqueio de ataques de “Brute Force” (exemplo: CAPTCH)
A101: A aplicação deve efetuar a ofuscação de dados sensíveis, tanto no frontend quanto no backend
...

Sheet Sheet1
A1: Qualquer transferência de arquivos para fora do ambiente Vivo (parceiros) precisa da aprovação do time de Proteção de Dados e DPO. | B1: A aprovação do time de Proteção de Dados e do DPO garante que a transferência esteja em conformidade com as políticas de privacidade e proteção de dados, como a LGPD. Sem essa aprovação, há risco de vazamentos ou não conformidade.
A2: A transferência de dados deve ocorrer via soluções homologadas pelo time de Segurança Digital. Apenas comunicação via SFTP não é permitida, por não suportar controles como os de rastreabilidade. | B2: O uso de soluções homologadas garante que a transferência atenda a padrões de segurança, como rastreabilidade e auditoria. O SFTP, sozinho, não oferece esses controles, aumentando o risco de transferências não rastreáveis ou inseguras.
A3: Caso possua dados classificados como restritos ou reservados, os arquivos, obrigatoriamente, precisam ser criptografados desde a origem. | B3: A criptografia desde a origem protege dados sensíveis contra interceptações ou acessos não autorizados durante a transferência. Sem ela, dados restritos ou reservados podem ser expostos, comprometendo a segurança e a privacidade.
A4: Qualquer transferência de arquivos, independente dos ambientes de comunicação, precisa ser realizada utilizando protocolos de comunicação criptografados, como TLS 1.3. | B4: A criptografia durante o trânsito (ex: TLS 1.3) protege os dados contra interceptações e espionagem. Sem ela, os arquivos podem ser lidos ou alterados por atacantes durante a transferência.
A5: Caso a transferência possua dados pessoais/sensíveis (de acordo com a LGPD) e/ou dados críticos para o negócio, e a transferência seja realizada para ambientes distintos, existe a necessidade de criptografar os arquivos desde a origem. | B5: A criptografia desde a origem é essencial para proteger dados pessoais/sensíveis e críticos, garantindo que apenas o destinatário autorizado possa acessá-los. Sem ela, há risco de vazamentos e não conformidade com a LGPD.
A12: Controle | B12: OWASP Top 10 | C12: Explicação da Correlação
A13: Toda transferência de arquivos deve utilizar protocolos de criptografia de trânsito robustos (ex: TLS 1.3 ou SFTP). | B13: A02:2021 - Cryptographic Failures | C13: A criptografia de trânsito protege contra falhas criptográficas, como interceptação de dados sensíveis durante a transferência.
A14: Toda transferência de arquivos precisa validar a autenticidade do destinatário antes da comunicação. | B14: A01:2021 - Broken Access Control | C14: A validação da autenticidade do destinatário garante que apenas entidades autorizadas possam receber os dados, evitando acesso não autorizado. | E14: Toda transferência de arquivos deve utilizar protocolos de criptografia de trânsito robustos (ex: TLS 1.3 ou SFTP). | F14: Interface | G14: Network Security
A15: Implementar verificação de integridade dos arquivos (ex: checksum ou hash). | B15: A08:2021 - Software and Data Integrity Failures | C15: A verificação de integridade garante que os arquivos não foram alterados durante a transferência, prevenindo falhas de integridade. | E15: Toda transferência de arquivos precisa validar a autenticidade do destinatário antes da comunicação. | F15: Interface | G15: Identity Security
A16: Para consumo de dados que necessitem de utilização de caixa postal, é necessário implementar autenticação multifator (MFA). | B16: A07:2021 - Identification and Authentication Failures | C16: A MFA reforça a autenticação, reduzindo o risco de acesso não autorizado a caixas postais ou sistemas de transferência. | E16: Implementar verificação de integridade dos arquivos (ex: checksum ou hash). | F16: Processamento | G16: Data Security
A17: A transferência de dados e arquivos precisa necessariamente gerar logs conforme descrito no componente de rastreabilidade. | B17: A09:2021 - Security Logging and Monitoring Failures | C17: A geração de logs é essencial para monitoramento e detecção de atividades suspeitas, alinhando-se ao requisito de logging e monitoramento do OWASP. | E17: Para consumo de dados que necessitem de utilização de caixa postal, é necessário implementar autenticação multifator (MFA). | F17: Interface | G17: Identity Security
A18: Configurar políticas de retenção e exclusão segura de arquivos após a transferência. | B18: Sem correlação | C18: Este controle está mais relacionado à governança de dados e privacidade, não tendo uma correlação direta com os itens do OWASP Top 10. | E18: A transferência de dados e arquivos precisa necessariamente gerar logs conforme descrito no componente de rastreabilidade. | F18: Processamento | G18: Security Governance & Compliance
A19: Qualquer transferência de arquivos para fora do ambiente Vivo (parceiros) precisa da aprovação do time de Proteção de Dados e DPO. | B19: Sem correlação | C19: Este controle está focado em conformidade e governança, não tendo uma correlação direta com os itens do OWASP Top 10. | E19: Configurar políticas de retenção e exclusão segura de arquivos após a transferência. | F19: Armazenamento | G19: Data Security
A20: A transferência de dados deve ocorrer via soluções homologadas pelo time de Segurança Digital. Apenas comunicação via SFTP não é permitida, por não suportar controles como os de rastreabilidade. | B20: A09:2021 - Security Logging and Monitoring Failures | C20: O uso de soluções homologadas com rastreabilidade está alinhado ao requisito de logging e monitoramento do OWASP. | E20: Qualquer transferência de arquivos para fora do ambiente Vivo (parceiros) precisa da aprovação do time de Proteção de Dados e DPO. | F20: Processamento | G20: Security Governance & Compliance
A21: Caso possua dados classificados como restritos ou reservados, os arquivos, obrigatoriamente, precisam ser criptografados desde a origem. | B21: A02:2021 - Cryptographic Failures | C21: A criptografia desde a origem protege contra falhas criptográficas, garantindo que dados restritos ou reservados não sejam expostos. | E21: A transferência de dados deve ocorrer via soluções homologadas pelo time de Segurança Digital. Apenas comunicação via SFTP não é permitida, por não suportar controles como os de rastreabilidade. | F21: Interface | G21: Application Security
A22: Caso a transferência possua dados pessoais/sensíveis (de acordo com a LGPD) e/ou dados críticos para o negócio, e a transferência seja realizada para ambientes distintos, existe a necessidade de criptografar os arquivos desde a origem. | B22: A02:2021 - Cryptographic Failures | C22: A criptografia desde a origem protege dados pessoais/sensíveis e críticos contra vazamentos, alinhando-se ao requisito de proteção criptográfica do OWASP. | E22: Caso possua dados classificados como restritos ou reservados, os arquivos, obrigatoriamente, precisam ser criptografados desde a origem. | F22: Armazenamento | G22: Data Security
E23: Caso a transferência possua dados pessoais/sensíveis (de acordo com a LGPD) e/ou dados críticos para o negócio, e a transferência seja realizada para ambientes distintos, existe a necessidade de criptografar os arquivos desde a origem. | F23: Armazenamento | G23: Data Security
A49: Controle | B49: Detalhamento do Requisito | C49: Propriedade | D49: Stride-LM | E49: Impacto - Risco | F49: Correlação com Frameworks | G49: Estrutura - Sistema da Informação | H49: Categoria de Segurança | I49: On-Prem | J49: IaaS | K49: PaaS | L49: SaaS
A50: O Sistema deve notificar o usuário após uma ação de redefinição, reset ou alteração de senha. | B50: Sem notificação, o usuário pode não estar ciente de alterações em sua conta, o que pode indicar atividades maliciosas ou não autorizadas. | C50: Autenticação | D50: Spoofing | E50: Fraudes | F50: A07:2021-Identification and Authentication Failures | G50: Interface | H50: Identity Security | I50: Sim | J50: Sim | K50: Sim | L50: Sim
A51: O sistema deve obrigar o usuário a alterar a senha em seu primeiro acesso. | B51: Sem a alteração obrigatória no primeiro acesso, credenciais padrão ou temporárias podem ser usadas indevidamente, aumentando o risco de acesso não autorizado. | C51: Autenticação | D51: Spoofing | E51: Fraudes | F51: A07:2021-Identification and Authentication Failures | G51: Interface | H51: Identity Security | I51: Sim | J51: Sim | K51: Sim | L51: Sim
A52: O sistema deve bloquear o usuário na aplicação após no máximo 5 tentativas inválidas de acesso. | B52: Sem bloqueio após tentativas falhas, atacantes podem usar ataques de força bruta para adivinhar senhas, comprometendo a segurança da conta. | C52: Autenticação | D52: Spoofing | E52: Fraudes | F52: A07:2021-Identification and Authentication Failures | G52: Interface | H52: Identity Security | I52: Sim | J52: Sim | K52: Sim | L52: Sim
A53: A aplicação deve bloquear a credencial de acesso do usuário após 60 dias sem uso e desativar a credencial após 120 dias de inatividade. | B53: Sem bloqueio e desativação, credenciais inativas podem ser usadas por atacantes para acessar o sistema, especialmente se forem comprometidas. | C53: Autenticação | D53: Spoofing | E53: Fraudes | F53: A07:2021-Identification and Authentication Failures | G53: Interface | H53: Identity Security | I53: Sim | J53: Sim | K53: Sim | L53: Sim
A54: Senhas deverão conter: mínimo 8 caracteres; letras maiúscula e minúsculas, caracteres especiais e números. | B54: Senhas fracas são facilmente adivinhadas ou quebradas em ataques de força bruta, permitindo acesso não autorizado ao sistema. | C54: Autenticação | D54: Spoofing | E54: Fraudes | F54: A07:2021-Identification and Authentication Failures | G54: Interface | H54: Identity Security | I54: Sim | J54: Sim | K54: Sim | L54: Sim
A55: As senhas devem ser armazenadas de forma segura segira ma aplicação | B55: Sem armazenamento seguro, senhas podem ser expostas em caso de vazamento de dados, permitindo que atacantes as usem para acessar outras contas. | C55: Confidencialidade | D55: Information disclosure | E55: Vazamento de dados | F55: A02:2021-Cryptographic Failures | G55: Armazenamento | H55: Data Security | I55: Sim | J55: Sim | K55: Sim | L55: Sim
F59: Controle | G59: Detalhamento do Requisito | H59: Propriedade | I59: Stride-LM | J59: Impacto - Risco | K59: Correlação com Frameworks | L59: Estrutura - Sistema da Informação | M59: Categoria de Segurança | N59: On-Prem | O59: IaaS | P59: PaaS | Q59: SaaS
F60: A solução deverá ter capacidade de fornecer explicações compreensíveis aos usuários sobre as decisões tomadas pela IA. | G60: Sem explicações claras, os usuários podem não confiar nas decisões da IA, e eventuais erros ou vieses podem passar despercebidos. | H60: Não repúdio | I60: Repudiação | J60: Danos a imagem | K60: Sem correlação | L60: Saída e feedback | M60: Security Governance & Compliance | N60: Sim | O60: Sim | P60: Sim | Q60: Sim
F61: Deverá ter uma verificação rigorosa de fornecedores e parceiros envolvidos no desenvolvimento e operação de sistemas de IA. | G61: Sem verificação rigorosa, fornecedores ou parceiros podem introduzir vulnerabilidades ou vieses nos sistemas de IA, comprometendo a segurança e a confiabilidade. | H61: Não repúdio | I61: Repudiação | J61: Regulatório/Compliance | K61: Sem correlação | L61: Processamento | M61: Supply Chain Security | N61: Sim | O61: Sim | P61: Sim | Q61: Sim
F62: Deverá ser utilizado técnicas de robustez adversarial para fortalecer modelos de IA contra ataques. | G62: Sem robustez adversarial, modelos de IA podem ser enganados por ataques maliciosos, resultando em decisões incorretas ou prejudiciais. | H62: Integridade | I62: Tampering | J62: Fraudes | K62: Sem correlação | L62: Processamento | M62: Threat Detection & Response | N62: Sim | O62: Sim | P62: Sim | Q62: Sim
F63: Implementar técnicas de aprendizado federado para treinar modelos sem centralizar dados sensíveis. | G63: O aprendizado federado reduz o risco de vazamento de dados sensíveis, pois os dados não precisam ser centralizados para treinamento. | H63: Confidencialidade | I63: Information disclosure | J63: Vazamento de dados | K63: Sem correlação | L63: Processamento | M63: Data Security | N63: Sim | O63: Sim | P63: Sim | Q63: Sim
F64: Necessário utilizar técnicas de aprendizado diferencial privado para preservar a privacidade dos dados de treinamento. | G64: Sem privacidade diferencial, dados de treinamento podem ser expostos, comprometendo a privacidade dos usuários. | H64: Confidencialidade | I64: Information disclosure | J64: Vazamento de dados | K64: Sem correlação | L64: Processamento | M64: Data Security | N64: Sim | O64: Sim | P64: Sim | Q64: Sim
F65: Necessário manter registros detalhados (logs) das operações e decisões dos sistemas de IA. | G65: Sem logs, não há como auditar ou investigar decisões da IA, dificultando a detecção de vieses, erros ou atividades maliciosas. | H65: Não repúdio | I65: Repudiação | J65: Regulatório/Compliance | K65: A09:2021-Security Logging and Monitoring Failures | L65: Processamento | M65: Security Governance & Compliance | N65: Sim | O65: Sim | P65: Sim | Q65: Sim
F66: Necessário manter registros detalhados de todas as versões de modelos e dados utilizados no treinamento. | G66: Sem registro de versões, não há como rastrear mudanças nos modelos ou dados, dificultando a identificação de problemas ou a conformidade com regulamentações. | H66: Não repúdio | I66: Repudiação | J66: Regulatório/Compliance | K66: A09:2021-Security Logging and Monitoring Failures | L66: Processamento | M66: Security Governance & Compliance | N66: Sim | O66: Sim | P66: Sim | Q66: Sim
F67: Necessário adotar técnicas de IA explicável (XAI) para tornar as decisões de IA mais transparentes. | G67: Sem XAI, as decisões da IA podem parecer "caixas pretas", reduzindo a confiança dos usuários e dificultando a identificação de vieses ou erros. | H67: Não repúdio | I67: Repudiação | J67: Danos a imagem | K67: Sem correlação | L67: Saída e feedback | M67: Security Governance & Compliance | N67: Sim | O67: Sim | P67: Sim | Q67: Sim
F68: Necessário a utilização de uma sandbox (ambiente para consumo do LLM - Large Language Model) onde os dados são isolados, evitando assim possíveis vazamentos/trocas de informação para alimentar outras Inteligências artificiais. | G68: Sem uma sandbox, dados sensíveis podem vazar ou ser usados indevidamente para treinar outros modelos de IA. | H68: Confidencialidade | I68: Information disclosure | J68: Vazamento de dados | K68: Sem correlação | L68: Processamento | M68: Data Security | N68: Sim | O68: Sim | P68: Sim | Q68: Sim
F69: Toda IA utilizada deve se basear em uma versão enterprise, que respeite os direitos dos usuários e que possua proteções contra ataques cibernéticos diversos. | G69: O uso de versões não enterprise pode resultar em violações de privacidade ou falta de proteções adequadas contra ataques. | H69: Confidencialidade | I69: Information disclosure | J69: Vazamento de dados | K69: Sem correlação | L69: Processamento | M69: Data Security | N69: Sim | O69: Sim | P69: Sim | Q69: Sim
F70: A solução de AI deve ser treinada a fim de evitar/monitorar vieses que porventura possam gerar algum tipo de discriminação, seja por cor, sexo, religião, condição social e outros. | G70: Sem monitoramento de vieses, a IA pode tomar decisões discriminatórias, causando danos à reputação e problemas regulatórios. | H70: Integridade | I70: Tampering | J70: Danos a imagem | K70: Sem correlação | L70: Processamento | M70: Security Governance & Compliance | N70: Sim | O70: Sim | P70: Sim | Q70: Sim
... F73: Havendo necessidade de compartilhamento de dados com parceiros, por meio de arquivos, esses deverão ser realizados por meio de ferramentas homologadas da Telefônica e só poderão ser realizados quando existir um contrato previamente firmado com o parceiro que contenha o Anexo de Segurança. | G73: Sem ferramentas homologadas e contratos, o compartilhamento de dados pode resultar em vazamentos ou uso indevido de informações sensíveis. | H73: Confidencialidade | I73: Information disclosure | J73: Vazamento de dados | K73: Sem correlação | L73: Processamento | M73: Data Security | N73: Sim | O73: Sim | P73: Sim | Q73: Si
I76: Quando a solução prever a utilização de PowerBI, caso esteja em capacidade premium, deverá ser criado o link de compartilhamento diretamente do relatório e não da "capacidade"/ "workspace premium". | J76: Compartilhar o link da capacidade/workspace premium pode expor outros relatórios ou dados sensíveis a usuários não autorizados. O compartilhamento direto do relatório limita o acesso apenas ao conteúdo necessário. | K76: Confidencialidade | L76: Information disclosure | M76: Vazamento de dados | N76: Sem correlação | O76: Interface | P76: Data Security | Q76: Não | R76: Não | S76: Sim | T76: Sim
I77: Quando a solução prever a utilização de PowerBI, é necessário inibir o checkbox que permite o recompartilhamento do relatório com outros usuários pelo destinatário. Ex.: "Permitir que o destinatário compartilhe este relatório" Deverá ser desmarcado no momento do compartilhamento. | J77: Permitir o recompartilhamento pode resultar em acesso não autorizado a dados sensíveis, já que o controle sobre quem acessa o relatório é perdido. | K77: Confidencialidade | L77: Information disclosure | M77: Vazamento de dados | N77: Sem correlação | O77: Interface | P77: Data Security | Q77: Não | R77: Não | S77: Sim | T77: Sim
I78: Quando a solução prever a utilização de PowerBI, deverão ser ocultadas de forma definitiva quaisquer outras abas no relatório que não sejam necessárias para a atuação dos usuários. | J78: Abas desnecessárias podem expor informações sensíveis ou confidenciais a usuários que não deveriam ter acesso a elas. | K78: Confidencialidade | L78: Information disclosure | M78: Vazamento de dados | N78: Sem correlação | O78: Interface | P78: Data Security | Q78: Não | R78: Não | S78: Sim | T78: Sim
I79: Quando a solução prever a utilização de PowerBI, é necessário inibir o checkbox que permite criação de conteúdo pelo destinatário baseada no relatório compartilhado. Ex.: "Permitir que o destinatário crie conteúdo com os dados associados a este relatório" Não deverá ser marcado no momento do compartilhamento. | J79: Permitir a criação de conteúdo com base no relatório compartilhado pode resultar em vazamento de dados, já que o destinatário pode usar os dados de forma não controlada. | K79: Confidencialidade | L79: Information disclosure | M79: Vazamento de dados | N79: Sem correlação | O79: Interface | P79: Data Security | Q79: Não | R79: Não | S79: Sim | T79: Sim
A84: anco de Dados | B84: Criptografia em repouso e em trânsito | C84: Garantir que os dados armazenados e transmitidos estejam protegidos com algoritmos criptográficos fortes. | I84: RPAs precisam ter comprimento mínimo de senha de 12 caracteres alfanuméricos. | J84: Senhas curtas ou simples são facilmente quebradas em ataques de força bruta, permitindo acesso não autorizado ao RPA. | K84: Autenticação | L84: Spoofing | M84: Fraudes | N84: A07:2021-Identification and Authentication Failures | O84: Interface | P84: Identity Security | Q84: Sim | R84: Sim | S84: Sim | T84: Sim
B85: Gestão de acessos e privilégios mínimos | C85: Implementar RBAC/ABAC para restringir acessos apenas a usuários autorizados, evitando privilégios excessivos. | I85: RPAs devem ter um período máximo de 30 dias para expiração de senha. | J85: Senhas que não expiram aumentam o risco de serem comprometidas e usadas por atacantes. | K85: Autenticação | L85: Spoofing | M85: Fraudes | N85: A07:2021-Identification and Authentication Failures | O85: Interface | P85: Identity Security | Q85: Sim | R85: Sim | S85: Sim | T85: Sim
B86: Auditoria e monitoramento de atividades | C86: Registrar e revisar logs de acesso, alterações e consultas sensíveis para detectar atividades suspeitas. | I86: RPAs devem ter um histórico para impedir repetição das últimas 9 senhas. | J86: A repetição de senhas antigas facilita o acesso não autorizado, já que senhas comprometidas podem ser reutilizadas. | K86: Autenticação | L86: Spoofing | M86: Fraudes | N86: A07:2021-Identification and Authentication Failures | O86: Interface | P86: Identity Security | Q86: Sim | R86: Sim | S86: Sim | T86: Sim
B87: Segregação de ambientes | C87: Evitar que ambientes de desenvolvimento, teste e homologação contenham dados reais, utilizando dados fictícios ou mascarados. | I87: RPAs não devem acessar APIs via RPA Screen Scraping, esse tipo de integração deve sempre ocorrer através do backend. | J87: O Screen Scraping é vulnerável a alterações na interface e pode expor dados sensíveis. A integração via backend é mais segura e confiável. | K87: Integridade | L87: Tampering | M87: Vazamento de dados | N87: A03:2021-Injection | O87: Interface | P87: Application Security | Q87: Sim | R87: Sim | S87: Sim | T87: Sim
B88: Proteção contra SQL Injection e outras vulnerabilidades | C88: Implementar validação de entrada e uso de prepared statements para prevenir ataques. | I88: RPAs não podem acessar diretamente banco de dados, qualquer acesso desse tipo realizado por RPAs deve ser feito via API. Com todos os controles apontados no grupo de "Arquitetura de APIs". | J88: O acesso direto a bancos de dados aumenta o risco de vazamentos ou alterações não autorizadas. O uso de APIs com controles de segurança reduz esse risco. | K88: Confidencialidade | L88: Information disclosure | M88: Vazamento de dados | N88: A01:2021-Broken Access Control | O88: Interface | P88: Application Security | Q88: Sim | R88: Sim | S88: Sim | T88: Sim
B89: Backup e recuperação de desastres | C89: Garantir backup periódico com testes regulares de restauração para evitar perda de dados. | I89: O acesso de RPAs deve ser permitido apenas para máquinas com certificado digital válido. Dessa forma, com validação de usuário, senha e certificado digital (MFA). | J89: Sem MFA, o acesso ao RPA pode ser comprometido apenas com a senha, aumentando o risco de acesso não autorizado. | K89: Autenticação | L89: Spoofing | M89: Fraudes | N89: A07:2021-Identification and Authentication Failures | O89: Interface | P89: Identity Security | Q89: Sim | R89: Sim | S89: Sim | T89: Sim
A90: Servidores | B90: Hardening de sistema operacional | C90: Aplicar práticas de segurança como desativação de serviços desnecessários, configuração segura de logs e remoção de contas padrão. | I90: O software de desenvolvimento dos RPAs deve estar homologado pela Vivo e possuir gestão de acessos adequada de acordo com o grupo de "Gestão de Acessos". | J90: O uso de software não homologado ou sem gestão de acessos adequada pode resultar em vulnerabilidades ou acesso não autorizado ao ambiente de desenvolvimento. | K90: Autenticação | L90: Spoofing | M90: Fraudes | N90: A07:2021-Identification and Authentication Failures | O90: Interface | P90: Identity Security | Q90: Sim | R90: Sim | S90: Sim | T90: Sim
B91: Gerenciamento de patches e atualizações | C91: Manter o sistema operacional e aplicativos atualizados com correções de segurança. | I91: RPAs que utilizem de mecanismos de transferência de arquivos devem seguir todos os controles de File GTW e criptografia apontados nos Requisitos de Segurança Digital. | J91: Sem controles de transferência de arquivos, dados sensíveis podem ser interceptados ou vazados durante a transferência. | K91: Confidencialidade | L91: Information disclosure | M91: Vazamento de dados | N91: A02:2021-Cryptographic Failures | O91: Interface | P91: Data Security | Q91: Sim | R91: Sim | S91: Sim | T91: Sim
B92: Controle de acesso administrativo | C92: Utilizar autenticação multifator (MFA) e restringir acessos administrativos por meio de bastion hosts/jump servers.
B93: Monitoramento e detecção de ameaças | C93: Implementar EDR/XDR para identificar e responder a comportamentos suspeitos em tempo real.
B94: Configuração segura de logs e retenção | C94: Garantir que logs sejam armazenados de forma segura e acessíveis apenas para análise forense e auditorias. | I94: Garantir que cada token OTP (One Time Password), se aplicável, só possa ser usado uma única vez. | J94: Tokens OTP reutilizáveis podem ser capturados e usados por atacantes para acessar o sistema. | K94: Autenticação | L94: Spoofing | M94: Fraudes | N94: A07:2021-Identification and Authentication Failures | O94: Interface | P94: Identity Security | Q94: Sim | R94: Sim | S94: Sim | T94: Sim
B95: Segregação de rede | C95: Isolar servidores críticos em segmentos seguros para evitar movimentação lateral em caso de incidente. | I95: Solução obrigatoriamente precisa se integrar com o Identity Provider definido pela Companhia para autenticação e autorização através de modelos de segurança seguros como OpenID, OAuth2 e SAML2.0 no fluxo 3-Legged Authentication. | J95: Sem integração com o IdP, a autenticação e autorização podem ser inconsistentes ou inseguras, aumentando o risco de acesso não autorizado. | K95: Autenticação | L95: Spoofing | M95: Fraudes | N95: A07:2021-Identification and Authentication Failures | O95: Interface | P95: Identity Security | Q95: Sim | R95: Sim | S95: Sim | T95: Sim
A96: Workstations | B96: Proteção contra malware e ameaças avançadas | C96: Utilizar soluções EPP/EDR para detectar e bloquear malware, phishing e ataques de engenharia social. | I96: É mandatório que a solução suporte e implemente o modelo de autorização baseado em perfis de acesso conforme o padrão RBAC (Role Based Access Control). | J96: Sem RBAC, os usuários podem ter permissões excessivas, aumentando o risco de acesso não autorizado a funcionalidades ou dados sensíveis. | K96: Autorização | L96: Elevation of Privilege | M96: Fraudes | N96: A01:2021-Broken Access Control | O96: Interface | P96: Identity Security | Q96: Sim | R96: Sim | S96: Sim | T96: Sim
B97: Aplicação de políticas de hardening | C97: Restringir instalação de softwares não autorizados, desativar execução automática de mídias removíveis e aplicar restrições de scripts. | I97: A interface de administração da solução deve ser federada ao IdP (Identity Provider) da VIVO. | J97: Sem federação ao IdP, a administração da solução pode ser inconsistente ou insegura, aumentando o risco de acesso não autorizado. | K97: Autenticação | L97: Spoofing | M97: Fraudes | N97: A07:2021-Identification and Authentication Failures | O97: Interface | P97: Identity Security | Q97: Sim | R97: Sim | S97: Sim | T97: Sim
B98: Gerenciamento de identidade e acesso | C98: Implementar políticas de senha forte, MFA e controle de sessão para evitar acessos indevidos. | I98: Toda a gestão de acessos da solução deve ser efetuada exclusivamente através do IDM (Identity Manager) homologado pela Vivo, por meio de integração sistêmica com o uso de API. | J98: Sem integração com o IDM, a gestão de acessos pode ser inconsistente ou insegura, aumentando o risco de acesso não autorizado. | K98: Autenticação | L98: Spoofing | M98: Fraudes | N98: A07:2021-Identification and Authentication Failures | O98: Interface | P98: Identity Security | Q98: Sim | R98: Sim | S98: Sim | T98: Sim
B99: Bloqueio de dispositivos removíveis e conexões não seguras | C99: Restringir uso de pendrives e dispositivos externos para evitar exfiltração de dados e infecções. | I99: A solução suporta prover uma API que permita executar TODAS as tarefas de gestão de acessos e do ciclo de vida do usuário, provendo, no mínimo, as seguintes capacidades: Criar Usuários, Remover usuários, Bloquear/Desbloquear usuários, Atribuir usuários a perfis, Remover usuários de perfis. | J99: Sem uma API para gestão de acessos, a administração de usuários pode ser manual e propensa a erros, aumentando o risco de acesso não autorizado. | K99: Autenticação | L99: Spoofing | M99: Fraudes | N99: A07:2021-Identification and Authentication Failures | O99: Interface | P99: Identity Security | Q99: Sim | R99: Sim | S99: Sim | T99: Sim
B100: Treinamento e conscientização de usuários | C100: Realizar campanhas de conscientização sobre boas práticas de segurança, phishing e riscos de engenharia social. | I100: É mandatório suportar e implementar que o processo de Gestão de Acessos seja efetuado através de um perfil exclusivo diferente de outros perfis, incluindo o ADMINISTRADOR. | J100: Sem segregação de perfis, administradores podem ter permissões excessivas, aumentando o risco de abuso ou erro humano. | K100: Autorização | L100: Elevation of Privilege | M100: Fraudes | N100: A01:2021-Broken Access Control | O100: Interface | P100: Identity Security | Q100: Sim | R100: Sim | S100: Sim | T100: Sim
I101: A solução deve suportar permitir criação de perfis dedicados para a gestão de acesso segregado das tarefas administrativas, desenvolvimento e/ou operação da plataforma. | J101: Sem segregação de perfis, usuários podem ter permissões conflitantes, aumentando o risco de acesso não autorizado ou abuso de funcionalidades. | K101: Autorização | L101: Elevation of Privilege | M101: Fraudes | N101: A01:2021-Broken Access Control | O101: Interface | P101: Identity Security | Q101: Sim | R101: Sim | S101: Sim | T101: Sim
I102: Mandatório existir segregação de perfis funcionais quando houver funcionalidades críticas identificadas e/ou permissividade de alterações de parâmetros. | J102: Sem segregação de perfis, usuários podem ter acesso a funcionalidades críticas sem necessidade, aumentando o risco de erros ou abusos. | K102: Autorização | L102: Elevation of Privilege | M102: Fraudes | N102: A01:2021-Broken Access Control | O102: Interface | P102: Identity Security | Q102: Sim | R102: Sim | S102: Sim | T102: Sim
I103: A solução precisa permitir criar perfis dedicados para a gestão de auditoria segregado das tarefas administrativas, desenvolvimento e/ou operação da plataforma. | J103: Sem perfis dedicados para auditoria, as trilhas de auditoria podem ser manipuladas ou acessadas indevidamente, comprometendo a integridade dos logs. | K103: Não repúdio | L103: Repudiação | M103: Regulatório/Compliance | N103: A09:2021-Security Logging and Monitoring Failures | O103: Processamento | P103: Security Governance & Compliance | Q103: Sim | R103: Sim | S103: Sim | T103: Sim
B104: Gestão de atualizações e patches | C104: Garantir que o sistema operacional e aplicativos recebam atualizações críticas de segurança regularmente. | I104: É mandatório suportar a nomenclatura dos usuários privilegiados siga o padrão estabelecido pela equipe de Gestão de Acessos e Identidade Digital da VIVO. | J104: Sem padronização, a identificação de usuários privilegiados pode ser inconsistente, dificultando a gestão e o monitoramento. | K104: Autenticação | L104: Spoofing | M104: Fraudes | N104: A07:2021-Identification and Authentication Failures | O104: Interface | P104: Identity Security | Q104: Sim | R104: Sim | S104: Sim | T104: Sim
I105: A solução precisa suportar gerar uma matriz SoD (Separation of Duties) que permita identificar papéis e responsabilidades conflitantes em termos de perfil de acesso que o sistema apresenta. | J105: Sem uma matriz SoD, conflitos de permissões podem passar despercebidos, aumentando o risco de abuso ou erro humano. | K105: Autorização | L105: Elevation of Privilege | M105: Fraudes | N105: A01:2021-Broken Access Control | O105: Interface | P105: Identity Security | Q105: Sim | R105: Sim | S105: Sim | T105: Sim
I106: É mandatório que a solução tenha usuários privilegiados gerenciados exclusivamente pelo Cofre de Senhas Corporativo administrado pela equipe de Gestão de Acessos e Identidade Digital da VIVO. | J106: Sem gestão centralizada, senhas de usuários privilegiados podem ser comprometidas, permitindo acesso não autorizado. | K106: Autenticação | L106: Spoofing | M106: Fraudes | N106: A07:2021-Identification and Authentication Failures | O106: Interface | P106: Identity Security | Q106: Sim | R106: Sim | S106: Sim | T106: Sim
I107: É mandatório que a solução suporte que a senha do usuário privilegiado seja de conhecimento e gestão exclusiva do Cofre de Senhas Corporativo administrado pela equipe de Gestão de Acessos e Identidade Digital da VIVO. | J107: Sem gestão centralizada, senhas de usuários privilegiados podem ser comprometidas, permitindo acesso não autorizado. | K107: Autenticação | L107: Spoofing | M107: Fraudes | N107: A07:2021-Identification and Authentication Failures | O107: Interface | P107: Identity Security | Q107: Sim | R107: Sim | S107: Sim | T107: Sim
I108: É mandatório que a solução suporte que a utilização do acesso do usuário privilegiado somente deverá ocorrer através do gateway do Cofre de Senhas Corporativo administrado pela equipe de Gestão de Acessos e Identidade Digital da VIVO, através de protocolos de acesso remoto suportados e autorizados por esta solução. | J108: Sem acesso controlado, usuários privilegiados podem acessar o sistema de forma insegura, aumentando o risco de vazamentos ou abusos. | K108: Autenticação | L108: Spoofing | M108: Fraudes | N108: A07:2021-Identification and Authentication Failures | O108: Interface | P108: Identity Security | Q108: Sim | R108: Sim | S108: Sim | T108: Sim
I109: Usuários serviços com acessos privilegiados deverão estar em uma ferramenta de PAM (Privileged Access Management) em todos os ambientes. | J109: Sem PAM, o acesso privilegiado pode ser comprometido, permitindo que atacantes assumam o controle de sistemas críticos. | K109: Autenticação | L109: Spoofing | M109: Fraudes | N109: A07:2021-Identification and Authentication Failures | O109: Interface | P109: Identity Security | Q109: Sim | R109: Sim | S109: Sim | T109: Sim
I110: Qualquer sistema exposto à internet precisa possuir Múltiplo Fator de Autenticação (MFA). | J110: Sem MFA, o acesso a sistemas expostos à internet pode ser comprometido apenas com a senha, aumentando o risco de acesso não autorizado. | K110: Autenticação | L110: Spoofing | M110: Fraudes | N110: A07:2021-Identification and Authentication Failures | O110: Interface | P110: Identity Security | Q110: Sim | R110: Sim | S110: Sim | T110: Sim
I111: Todas as camadas da aplicação (Backend, Frontend, banco de dados e etc) precisam autenticar e autorizar o usuário. | J111: Sem autenticação e autorização em todas as camadas, usuários podem acessar funcionalidades ou dados não autorizados. | K111: Autenticação | L111: Spoofing | M111: Fraudes | N111: A07:2021-Identification and Authentication Failures | O111: Interface | P111: Identity Security | Q111: Sim | R111: Sim | S111: Sim | T111: Sim
I112: Qualquer aplicação que possua acesso administrativos precisa possuir Multi-Factor Authentication. | J112: Sem MFA, o acesso administrativo pode ser comprometido apenas com a senha, permitindo que atacantes assumam o controle do sistema. | K112: Autenticação | L112: Spoofing | M112: Fraudes | N112: A07:2021-Identification and Authentication Failures | O112: Interface | P112: Identity Security | Q112: Sim | R112: Sim | S112: Sim | T112: Sim
I113: O sistema precisa possuir perfis de acesso baseados no princípio de mínimo privilégio. | J113: Sem o princípio de mínimo privilégio, usuários podem ter permissões excessivas, aumentando o risco de acesso não autorizado ou abuso de funcionalidades. | K113: Autorização | L113: Elevation of Privilege | M113: Fraudes | N113: A01:2021-Broken Access Control | O113: Interface | P113: Identity Security | Q113: Sim | R113: Sim | S113: Sim | T113: Sim
I114: As credenciais de conta de serviço e senhas de servidores e/ou banco de dados devem ser administradas na ferramenta de PAM (Privileged Access Management) definido pela Vivo. | J114: Sem PAM, credenciais de contas de serviço podem ser comprometidas, permitindo que atacantes assumam o controle de sistemas críticos. | K114: Autenticação | L114: Spoofing | M114: Fraudes | N114: A07:2021-Identification and Authentication Failures | O114: Interface | P114: Identity Security | Q114: Sim | R114: Sim | S114: Sim | T114: Sim
I115: Obter as informações de perfil de acesso para autorizar o acesso dos usuários através de atributos constantes no Access Token do fluxo OAUTH/JWT ou do SAML Assertion. | J115: Sem autorização baseada em tokens, o acesso pode ser inconsistente ou inseguro, aumentando o risco de acesso não autorizado. | K115: Autorização | L115: Elevation of Privilege | M115: Fraudes | N115: A01:2021-Broken Access Control | O115: Interface | P115: Identity Security | Q115: Sim | R115: Sim | S115: Sim | T115: Sim
I116: A solução deve suportar a NÃO UTILIZAÇÃO E/OU EXIGIR que permissões de acesso sejam atribuídas diretamente a usuários. | J116: Atribuir permissões diretamente a usuários pode resultar em inconsistências ou permissões excessivas, aumentando o risco de acesso não autorizado. | K116: Autorização | L116: Elevation of Privilege | M116: Fraudes | N116: A01:2021-Broken Access Control | O116: Interface | P116: Identity Security | Q116: Sim | R116: Sim | S116: Sim | T116: Sim
... I118: A solução permitirá que os perfis devem ser associados a grupos no sistema de autenticação da CONTRATANTE (Ex: Access Token OAUTH ou SAML Assertion) de forma a permitir a autorização através de grupos sem a necessidade de administração de usuários e perfis diretamente na solução. | J118: Sem associação a grupos, a gestão de acessos pode ser manual e propensa a erros, aumentando o risco de acesso não autorizado. | K118: Autorização | L118: Elevation of Privilege | M118: Fraudes | N118: A01:2021-Broken Access Control | O118: Interface | P118: Identity Security | Q118: Sim | R118: Sim | S118: Sim | T118: Sim
I119: Contas de serviço precisam estar em uma ferramenta de Key Vault e/ou PAM (Cofre de Senhas e Azure Key Vault, por exemplo). | J119: Sem gestão centralizada, credenciais de contas de serviço podem ser comprometidas, permitindo que atacantes assumam o controle de sistemas críticos. | K119: Autenticação | L119: Spoofing | M119: Fraudes | N119: A07:2021-Identification and Authentication Failures | O119: Interface | P119: Identity Security
I120: Gestão de Identidade e acesso nas plataformas deve ser realizado pelo time de Identidade da Vivo. | J120: Sem gestão centralizada, a administração de identidades pode ser inconsistente ou insegura, aumentando o risco de acesso não autorizado. | K120: Autenticação | L120: Spoofing | M120: Fraudes | N120: A07:2021-Identification and Authentication Failures | O120: Interface | P120: Identity Security
I121: Garantir políticas de Roles Based Access Controls (RBAC). | J121: Sem RBAC, os usuários podem ter permissões excessivas, aumentando o risco de acesso não autorizado a funcionalidades ou dados sensíveis. | K121: Autorização | L121: Elevation of Privilege | M121: Fraudes | N121: A01:2021-Broken Access Control | O121: Interface | P121: Identity Security
